Workbook
Name IQ_CH: 110000
Name IQ_CQ: 5000
Name IQ_CY: 10000
Name IQ_DAILY: 500000
Name IQ_FH: 100000
Name IQ_FQ: 500
Name IQ_FY: 1000
Name IQ_LTM: 2000
Name IQ_MONTH: 15000
Name IQ_NTM: 6000
Name IQ_WEEK: 50000
Name IQ_YTD: 3000

Sheet VMI IV Calculator (20 years)
B2: ="Intrinsic Value Calculator ("&VLOOKUP(F12,AI32:AP34,7,FALSE)&" 20 years)" -> Intrinsic Value Calculator (Discounted Free Cash Flow Method 20 years)
B3: (Be consistent with the denominations used. Usually Millions $)
C6: KEY IN THE VALUES IN THE WHITE BOXES
C8: Name of Stock | F8: Microsoft | J8: Financial Statement Currency | M8: USD$
C10: Stock Symbol | F10: MSFT | J10: Stock Listing Currency | M10: USD$
C12: Valuation Method | F12: Discounted Free Cash Flow | J12: Exchange Rate | L12: ="1 "&M8&" is equivalent to " -> 1 USD$ is equivalent to | M12: 1 | N12: =M10 -> USD$
C14: =VLOOKUP(F12,AI32:AP34,2,FALSE) -> Free Cash Flow (Current) | F14: =$M$8 -> USD$ | G14: 101030.4 | J14: ="PV of 20 yr "&VLOOKUP(F12,AI32:AP34,3,FALSE) -> PV of 20 yr Free Cash Flow | M14: =$M$8 -> USD$ | N14: =SUM(F35:O35)+SUM(F40:O40) -> 3815917.2
C16: Total Debt (Short Term + LT Debt) | F16: =$M$8 -> USD$ | G16: 43208 | J16: Intrinsic Value before cash/debt | M16: =$M$8 -> USD$ | N16: =IF(F26<>0,N14/F26,0) -> 511.10597
C18: Cash and Short Term Investments | F18: =$M$8 -> USD$ | G18: 102012 | J18: less Debt per Share | M18: =$M$8 -> USD$ | N18: =IF(F26<>0,G16/F26,0) -> 5.7873024
C20: =VLOOKUP(F12,AI32:AP34,4,FALSE) -> Free Cash Flow Growth Rate (Yr 1 - 5) | F20: 0.1748 | J20: Plus (+) Cash Per Share | M20: =$M$8 -> USD$ | N20: =IF(F26<>0,G18/F26,0) -> 13.663541
C22: =VLOOKUP(F12,AI32:AP34,5,FALSE) -> Free Cash Flow growth rate (Yr 6 - 10) | F22: 0.15
C24: =VLOOKUP(F12,AI32:AP34,8,FALSE) -> Free Cash Flow Growth Rate (Yr 11 - 20) | F24: 0.04 | J24: Intrinsic Value Per Share (In Financial Statement Currency) | M24: =$M$8 -> USD$ | N24: =N16-N18+N20 -> 518.98221
C26: No. of Shares Outstanding | F26: 7466 | J26: Final Intrinsic Value Per Share (In Stock Listing Currency) | M26: =$M$10 -> USD$ | N26: =N24*M12 -> 518.98221
C28: Discount Rate | E28: 0.0661 | J28: (Discount)/Premium | M28: =N30/N26-1 -> -0.21816202
C30: Current Year | E30: 2025 | G30: NB: Take the last Fiscal Year as the Current Year | J30: Last Close | M30: =$M$10 -> USD$ | N30: 405.76
C32: Year | F32: =$E$30+1 -> 2026 | G32: =$E$30+2 -> 2027 | H32: =$E$30+3 -> 2028 | I32: =$E$30+4 -> 2029 | J32: =$E$30+5 -> 2030 | K32: =$E$30+6 -> 2031 | L32: =$E$30+7 -> 2032 | M32: =$E$30+8 -> 2033 | N32: =$E$30+9 -> 2034 | O32: =$E$30+10 -> 2035 | AI32: Discounted Cash Flow | AJ32: Operating Cash Flow (Current) | AK32: Operating Cash Flow | AL32: Cash Flow Growth Rate (Yr 1 - 5) | AM32: Cash Flow Growth Rate (Yr 6 - 10) | AN32: Operating Cash Flow (Projected) | AO32: Discounted Cash Flow Method | AP32: Cash Flow Growth Rate (Yr 11 - 20)
C33: =VLOOKUP(F12,AI32:AP34,6,FALSE) -> Free Cash Flow (Projected) | F33: =(G14)*(1+F20) -> 118690.51 | G33: =($F33)*(1+$F$20) -> 139437.62 | H33: =(G$33)*(1+$F$20) -> 163811.31 | I33: =(H$33)*(1+$F$20) -> 192445.53 | J33: =(I$33)*(1+$F$20) -> 226085.01 | K33: =(J$33)*(1+$F$22) -> 259997.76 | L33: =(K$33)*(1+$F$22) -> 298997.42 | M33: =(L$33)*(1+$F$22) -> 343847.03 | N33: =(M$33)*(1+$F$22) -> 395424.09 | O33: =(N$33)*(1+$F$22) -> 454737.7 | AI33: Discounted Net Income | AJ33: Net Income (Current) | AK33: Net Income | AL33: Net Income Growth Rate (Yr 1 - 5) | AM33: Net Income Growth Rate (Yr 6 - 10) | AN33: Net Income (Projected) | AO33: Discounted Net Income Method | AP33: Net Income Growth Rate (Yr 11 - 20)
C34: Discount Factor | F34: =1/(1+$E$28) -> 0.93799831 | G34: =F$34/(1+$E$28) -> 0.87984083 | H34: =G$34/(1+$E$28) -> 0.82528922 | I34: =H$34/(1+$E$28) -> 0.77411989 | J34: =I$34/(1+$E$28) -> 0.72612315 | K34: =J$34/(1+$E$28) -> 0.68110229 | L34: =K$34/(1+$E$28) -> 0.6388728 | M34: =L$34/(1+$E$28) -> 0.59926161 | N34: =M$34/(1+$E$28) -> 0.56210637 | O34: =N$34/(1+$E$28) -> 0.52725483 | AI34: Discounted Free Cash Flow | AJ34: Free Cash Flow (Current) | AK34: Free Cash Flow | AL34: Free Cash Flow Growth Rate (Yr 1 - 5) | AM34: Free Cash Flow growth rate (Yr 6 - 10) | AN34: Free Cash Flow (Projected) | AO34: Discounted Free Cash Flow Method | AP34: Free Cash Flow Growth Rate (Yr 11 - 20)
C35: Discounted Value | F35: =F33*F34 -> 111331.5 | G35: =G33*G34 -> 122682.91 | H35: =H33*H34 -> 135191.71 | I35: =I33*I34 -> 148975.91 | J35: =J33*J34 -> 164165.56 | K35: =K33*K34 -> 177085.07 | L35: =L33*L34 -> 191021.32 | M35: =M33*M34 -> 206054.33 | ... O35: =O33*O34 -> 239762.65
C37: Year | F37: =$E$30+11 -> 2036 | G37: =$E$30+12 -> 2037 | H37: =$E$30+13 -> 2038 | I37: =$E$30+14 -> 2039 | J37: =$E$30+15 -> 2040 | K37: =$E$30+16 -> 2041 | L37: =$E$30+17 -> 2042 | M37: =$E$30+18 -> 2043 | N37: =$E$30+19 -> 2044 | O37: =$E$30+20 -> 2045
C38: =VLOOKUP(F12,AI32:AP34,6,FALSE) -> Free Cash Flow (Projected) | F38: =(O$33)*(1+$F$24) -> 472927.21 | G38: =(F$38)*(1+$F$24) -> 491844.3 | H38: =(G$38)*(1+$F$24) -> 511518.07 | I38: =(H$38)*(1+$F$24) -> 531978.79 | J38: =(I$38)*(1+$F$24) -> 553257.95 | K38: =(J$38)*(1+$F$24) -> 575388.26 | L38: =(K$38)*(1+$F$24) -> 598403.79 | M38: =(L$38)*(1+$F$24) -> 622339.95 | N38: =(M$38)*(1+$F$24) -> 647233.54 | O38: =(N$38)*(1+$F$24) -> 673122.89
C39: Discount Factor | F39: =O$34/(1+$E$28) -> 0.49456414 | G39: =F$39/(1+$E$28) -> 0.46390033 | H39: =G$39/(1+$E$28) -> 0.43513772 | I39: =H$39/(1+$E$28) -> 0.40815845 | J39: =I$39/(1+$E$28) -> 0.38285194 | K39: =J$39/(1+$E$28) -> 0.35911447 | L39: =K$39/(1+$E$28) -> 0.33684877 | M39: =L$39/(1+$E$28) -> 0.31596358 | N39: =M$39/(1+$E$28) -> 0.2963733 | O39: =N$39/(1+$E$28) -> 0.27799766
C40: Discounted Value | F40: =F38*F39 -> 233892.84 | G40: =G38*G39 -> 228166.73 | H40: =H38*H39 -> 222580.81 | I40: =I38*I39 -> 217131.64 | J40: =J38*J39 -> 211815.88 | K40: =K38*K39 -> 206630.25 | L40: =L38*L39 -> 201571.58 | M40: =M38*M39 -> 196636.75 | ... O40: =O38*O39 -> 187126.58
C60: Discount Rate for US Stocks | J60: Discount Rate for China/HK Stocks
C62: BETA | E62: DISCOUNT RATE | J62: BETA | L62: DISCOUNT RATE
C63: Less than 0.80 | E63: =E74+0.8*E75 -> 0.057904 | J63: Less than 0.80 | L63: =L74+0.8*L75 -> 0.085576
C64: 0.9 | E64: =E74+C64*E75 -> 0.060632 | J64: 0.9 | L64: =L74+J64*L75 -> 0.092438
C65: 1 | E65: =E74+C65*E75 -> 0.06336 | J65: 1 | L65: =L74+J65*L75 -> 0.0993
C66: 1.1 | E66: =E74+C66*E75 -> 0.066088 | J66: 1.1 | L66: =L74+J66*L75 -> 0.106162
C67: 1.2 | E67: =E74+C67*E75 -> 0.068816 | J67: 1.2 | L67: =L74+J67*L75 -> 0.113024
C68: 1.3 | E68: =E74+C68*E75 -> 0.071544 | J68: 1.3 | L68: =L74+J68*L75 -> 0.119886
C69: 1.4 | E69: =E74+C69*E75 -> 0.074272 | J69: 1.4 | L69: =L74+J69*L75 -> 0.126748
C70: 1.5 | E70: =E74+C70*E75 -> 0.077 | J70: 1.5 | L70: =L74+J70*L75 -> 0.13361
C71: More than 1.6 | E71: =E74+1.6*E75 -> 0.079728 | J71: More than 1.6 | L71: =L74+1.6*L75 -> 0.140472
C73: Discount Rate = Risk Free Rate + Beta x Market Risk Premium | J73: Discount Rate = Risk Free Rate + Beta x Market Risk Premium
D74: Risk Free Rate = | E74: ='Discount Rate Data'!C17 -> 0.03608 | K74: Risk Free Rate = | L74: ='Discount Rate Data'!C31 -> 0.03068
D75: Average market risk premium = | E75: ='Discount Rate Data'!F17 -> 0.02728 | K75: Average market risk premium = | L75: ='Discount Rate Data'!F31 -> 0.06862
D76: Updated on | E76: ='Discount Rate Data'!C4 -> 46092 | K76: Updated on | L76: ='Discount Rate Data'!C4 -> 46092
C78: Source: | J78: Source:
C79: https://www.market-risk-premia.com/us.html | J79: http://www.market-risk-premia.com/hk.html
M85: ="© "&YEAR(TODAY())&" Piranha Ltd. All rights reserved." -> © 2026 Piranha Ltd. All rights reserved.

Sheet Discounted Earnings Per Share
A1: KEY IN THE VALUES IN RED
A2: Assuming a Discount rate of 4% per year.
A4: Intrinsic Value Calculator (Discounted Earnings Per Share Method 10 years)
D5: ( Be consisent with the denominations used. Usually $)
A7: EPS (current) | B7: =#REF! -> #REF!
A8: EPS growth rate | B8: =#REF! -> #REF!
A9: Discount Rate | B9: =#REF! -> #REF!
A10: Year | B10: =#REF!+1 -> #REF! | C10: =B10+1 -> #REF! | D10: =C10+1 -> #REF! | E10: =D10+1 -> #REF! | F10: =E10+1 -> #REF! | G10: =F10+1 -> #REF! | H10: =G10+1 -> #REF! | I10: =H10+1 -> #REF! | J10: =I10+1 -> #REF! | K10: =J10+1 -> #REF!
A11: EPS (Projected) | B11: =B7*(1+B8) -> #REF! | C11: =B11*(1+B8) -> #REF! | D11: =C11*(1+B8) -> #REF! | E11: =D11*(1+B8) -> #REF! | F11: =E11*(1+B8) -> #REF! | G11: =F11*(1+B8) -> #REF! | H11: =G11*(1+B8) -> #REF! | I11: =H11*(1+B8) -> #REF! | J11: =I11*(1+B8) -> #REF! | K11: =J11*(1+B8) -> #REF!
A12: Discount Factor | B12: =1/(1+$B$9) -> #REF! | C12: =B12/(1+$B$9) -> #REF! | D12: =C12/(1+$B$9) -> #REF! | E12: =D12/(1+$B$9) -> #REF! | F12: =E12/(1+$B$9) -> #REF! | G12: =F12/(1+$B$9) -> #REF! | H12: =G12/(1+$B$9) -> #REF! | I12: =H12/(1+$B$9) -> #REF! | J12: =I12/(1+$B$9) -> #REF! | K12: =J12/(1+$B$9) -> #REF!
A13: Discounted Value | B13: =B11*B12 -> #REF! | C13: =C11*C12 -> #REF! | D13: =D11*D12 -> #REF! | E13: =E11*E12 -> #REF! | F13: =F11*F12 -> #REF! | G13: =G11*G12 -> #REF! | H13: =H11*H12 -> #REF! | I13: =I11*I12 -> #REF! | ... K13: =K11*K12 -> #REF!
A15: Intrinsic Value: | B15: =SUM(B13:K13) -> #REF!
A17: Note: This assumes EPS growth rate remains constant throughout the 10 years
A18: In certain cases, you may want to lower or increase the growth rate after a few years.

Sheet Discounted Cash Flow
A1: KEY IN THE VALUES IN RED
A2: Assuming a Discount rate of 4% per year.
A4: Intrinsic Value Calculator (Discounted Cash Flow Method 10 years)
D5: (Be consistent with the denominations used. Usually Millions $)
A7: Operating Cash Flow (current) | C7: =#REF! -> #REF! | D7: million
A8: Cash flow growth rate | C8: =#REF! -> #REF!
A9: Discount Rate | C9: =#REF! -> #REF!
A12: Year | B12: =#REF!+1 -> #REF! | C12: =B12+1 -> #REF! | D12: =C12+1 -> #REF! | E12: =D12+1 -> #REF! | F12: =E12+1 -> #REF! | G12: =F12+1 -> #REF! | H12: =G12+1 -> #REF! | I12: =H12+1 -> #REF! | J12: =I12+1 -> #REF! | K12: =J12+1 -> #REF!
A13: Cash Flow (Projected) | B13: =C7*(1+C8) -> #REF! | C13: =B13*(1+$C$8) -> #REF! | D13: =C13*(1+$C$8) -> #REF! | E13: =D13*(1+$C$8) -> #REF! | F13: =E13*(1+$C$8) -> #REF! | G13: =F13*(1+$C$8) -> #REF! | H13: =G13*(1+$C$8) -> #REF! | I13: =H13*(1+$C$8) -> #REF! | J13: =I13*(1+$C$8) -> #REF! | K13: =J13*(1+$C$8) -> #REF!
A14: Discount Factor | B14: =1/(1+$C$9) -> #REF! | C14: =B14/(1+$C$9) -> #REF! | D14: =C14/(1+$C$9) -> #REF! | E14: =D14/(1+$C$9) -> #REF! | F14: =E14/(1+$C$9) -> #REF! | G14: =F14/(1+$C$9) -> #REF! | H14: =G14/(1+$C$9) -> #REF! | I14: =H14/(1+$C$9) -> #REF! | J14: =I14/(1+$C$9) -> #REF! | K14: =J14/(1+$C$9) -> #REF!
A15: Discounted Value | B15: =B13*B14 -> #REF! | C15: =C13*C14 -> #REF! | D15: =D13*D14 -> #REF! | E15: =E13*E14 -> #REF! | F15: =F13*F14 -> #REF! | G15: =G13*G14 -> #REF! | H15: =H13*H14 -> #REF! | I15: =I13*I14 -> #REF! | ... K15: =K13*K14 -> #REF!
A17: No. Shares Outstanding | C17: =#REF! -> #REF! | D17: million
A19: PV of 10 yr Cash flows | C19: =B15+C15+D15+E15+F15+G15+H15+I15+J15+K15 -> #REF! | D19: million
A20: Intrinsic Value per share | C20: =C19/C17 -> #REF!
A22: Note: This assumes Cash growth rate remains constant throughout the 10 years
A23: In certain cases, you may want to lower or increase the growth rate after a few years.

Sheet VMI IV Calculator (Mean PB)
B2: Intrinsic Value Calculator (Mean Price to Book Ratio / Mean PB Ratio)
C6: KEY IN THE VALUES IN THE WHITE BOXES
C8: Name of Stock | F8: JPMorgan Chase & Co | J8: Financial Statement Currency | M8: USD$
C10: Stock Symbol | F10: JPM | J10: Stock Listing Currency | M10: USD$
C12: Book Value (BV) per Share | F12: =$M$8 -> USD$ | G12: 100 | J12: Exchange Rate | L12: ="1 "&M8&" is equivalent to " -> 1 USD$ is equivalent to | M12: 1 | N12: =M10 -> USD$
C14: Number of Historical Data | F14: 5 years
E16: Date | F16: =DATE(YEAR(G16)-1,MONTH(G16),DAY(G16)) -> 42369 | G16: =DATE(YEAR(H16)-1,MONTH(H16),DAY(H16)) -> 42735 | H16: =DATE(YEAR(I16)-1,MONTH(I16),DAY(I16)) -> 43100 | I16: =DATE(YEAR(J16)-1,MONTH(J16),DAY(J16)) -> 43465 | J16: =DATE(YEAR(K16)-1,MONTH(K16),DAY(K16)) -> 43830 | K16: =DATE(YEAR(L16)-1,MONTH(L16),DAY(L16)) -> 44196 | L16: =DATE(YEAR(M16)-1,MONTH(M16),DAY(M16)) -> 44561 | M16: =DATE(YEAR(N16)-1,MONTH(N16),DAY(N16)) -> 44926 | N16: =DATE(YEAR(O16)-1,MONTH(O16),DAY(O16)) -> 45291 | O16: 45657
C17: Historical Price to Book Ratio | F17: 1.11 | G17: 1.35 | H17: 1.6 | I17: 1.4 | J17: 1.85 | K17: 1.61 | L17: 1.83 | M17: 1.54 | N17: 1.7 | O17: 2.08
C19: Mean Price to Book Ratio | F19: =IF(ISNUMBER(SEARCH("5",$F$14)),AVERAGE($K17:$O17),IF(ISNUMBER(SEARCH("10",$F$14)),AVERAGE($F17:$O17),"")) -> 1.752 | J19: 1 Standard Deviation (SD) Value | M19: =IF(ISNUMBER(SEARCH("5",$F$14)),_xlfn.STDEV.S($K17:$O17),IF(ISNUMBER(SEARCH("10",$F$14)),_xlfn.STDEV.S($F17:$O17),"")) -> 0.21300235
F21: Mean - 1 SD | H21: Mean - 2 SD | J21: Mean | L21: Mean + 1 SD | N21: Mean + 2 SD
C22: PB Ratio | F22: =$F$19-$M$19*2 -> 1.3259953 | H22: =$F$19-$M$19*1 -> 1.5389977 | J22: =F19 -> 1.752 | L22: =$F$19+$M$19*1 -> 1.9650023 | N22: =$F$19+$M$19*2 -> 2.1780047
C23: PB Ratio x BV per Share (In Financial Statement Currency) | E23: =$M$8 -> USD$ | F23: =F22*$G$12 -> 132.59953 | H23: =H22*$G$12 -> 153.89977 | J23: =J22*$G$12 -> 175.2 | L23: =L22*$G$12 -> 196.50023 | N23: =N22*$G$12 -> 217.80047
F25: IV - 2 SD | H25: IV - 1 SD | J25: Intrinsic Value (IV) | L25: IV + 1 SD | N25: IV + 2 SD
C26: PB Ratio x BV per Share (In Stock Listing Currency) | E26: =$M$10 -> USD$ | F26: =F22*$G$12*$M$12 -> 132.59953 | H26: =H22*$G$12*$M$12 -> 153.89977 | J26: =J22*$G$12*$M$12 -> 175.2 | L26: =L22*$G$12*$M$12 -> 196.50023 | N26: =N22*$G$12*$M$12 -> 217.80047
F28: Last Close | I28: =$M$10 -> USD$ | J28: 242.28
H30: (Discount)/Premium | J30: =$J$28/J26-1 -> 0.38287671
M36: ="© "&YEAR(TODAY())&" Piranha Ltd. All rights reserved." -> © 2026 Piranha Ltd. All rights reserved.

Sheet VMI IV Calculator (PSG)
B2: Intrinsic Value Calculator (Price to Sales Growth Ratio)
C6: KEY IN THE VALUES IN THE WHITE BOXES
C8: Name of Stock | F8: Palantir | J8: Financial Statement Currency | M8: USD$
C10: Stock Symbol | F10: PLTR | J10: Stock Listing Currency | M10: USD$
J12: Exchange Rate | L12: ="1 "&M8&" is equivalent to " -> 1 USD$ is equivalent to | M12: 1 | N12: =M10 -> USD$
C14: Sales Per Share | F14: =$M$8 -> USD$ | G14: 1.27 | J14: Current Price to Sales Growth (PSG) Ratio | M14: =N25/G14/(F16*100) -> 2.1574143
C16: Projected Growth Rate | F16: 0.3099 | J16: Fair PSG Ratio | M16: 0.2
J18: Intrinsic Value Per Share (In Financial Statement Currency) | M18: =$M$8 -> USD$ | N18: =M16*G14*F16*100 -> 7.87146
J20: Final Intrinsic Value Per Share (In Stock Listing Currency) | M20: =$M$10 -> USD$ | N20: =N18*M12 -> 7.87146
J22: (Discount)/Premium | M22: =N25/N20-1 -> 9.7870713
J25: Last Close | M25: =$M$10 -> USD$ | N25: 84.91
M31: ="© "&YEAR(TODAY())&" Piranha Ltd. All rights reserved." -> © 2026 Piranha Ltd. All rights reserved.

Sheet VMI Portfolio Dashboard
B2: PORTFOLIO DASHBOARD
B3: NOTE: EVERYTHING IN THIS PAGE IS CALCULATED AUTOMATICALLY
B5: Breakdown by Holdings (Market Value)
B45: Breakdown by Type (Market Value)
B46: TOTAL | G46: US | L46: China/HK | Q46: Singapore | V46: Australia
B47: Type | C47: Count | D47: Market Value (in USD) | E47: Percentage by Market Value | G47: Type | H47: Count | I47: Market Value (in USD) | J47: Percentage by Market Value | L47: Type | M47: Count | N47: Market Value (in USD) | O47: Percentage by Market Value | Q47: Type | R47: Count | S47: Market Value (in USD) | T47: Percentage by Market Value | V47: Type | W47: Count | X47: Market Value (in USD) | Y47: Percentage by Market Value
B48: Cyclical | C48: =COUNTIFS(_TrackerTable35[Type],_USDashboardTable561031[[#This Row],[Type]]) -> 1 | D48: =SUMIFS(_TrackerTable35[Market Value (in USD)],_TrackerTable35[Type],_USDashboardTable561031[[#This Row],[Type]]) -> 2948.1481 | E48: =IF(_USDashboardTable561031[[#Totals],[Market Value (in USD)]]>0,_USDashboardTable561031[[#This Row],[Market Value (in USD)]]/_USDashboardTable561031[[#Totals],[Market Value (in USD)]],0) -> 0.055498548 | G48: Cyclical | H48: =COUNTIFS(_TrackerTable35[Country],G$46,_TrackerTable35[Type],_USDashboardTable429[[#This Row],[Type]]) -> 0 | I48: =SUMIFS(_TrackerTable35[Market Value (in USD)],_TrackerTable35[Country],G$46,_TrackerTable35[Type],_USDashboardTable429[[#This Row],[Type]]) -> 0 | J48: =IF(_USDashboardTable429[[#Totals],[Market Value (in USD)]]>0,_USDashboardTable429[[#This Row],[Market Value (in USD)]]/_USDashboardTable429[[#Totals],[Market Value (in USD)]],0) -> 0 | L48: Cyclical | M48: =COUNTIFS(_TrackerTable35[Country],L$46,_TrackerTable35[Type],_USDashboardTable5930[[#This Row],[Type]]) -> 0 | N48: =SUMIFS(_TrackerTable35[Market Value (in USD)],_TrackerTable35[Country],L$46,_TrackerTable35[Type],_USDashboardTable5930[[#This Row],[Type]]) -> 0 | O48: =IF(_USDashboardTable5930[[#Totals],[Market Value (in USD)]]>0,_USDashboardTable5930[[#This Row],[Market Value (in USD)]]/_USDashboardTable5930[[#Totals],[Market Value (in USD)]],0) -> 0 | Q48: Cyclical | R48: =COUNTIFS(_TrackerTable35[Country],Q$46,_TrackerTable35[Type],_USDashboardTable571132[[#This Row],[Type]]) -> 1 | S48: =SUMIFS(_TrackerTable35[Market Value (in USD)],_TrackerTable35[Country],Q$46,_TrackerTable35[Type],_USDashboardTable571132[[#This Row],[Type]]) -> 2948.1481 | T48: =IF(_USDashboardTable571132[[#Totals],[Market Value (in USD)]]>0,_USDashboardTable571132[[#This Row],[Market Value (in USD)]]/_USDashboardTable571132[[#Totals],[Market Value (in USD)]],0) -> 1 | V48: Cyclical | W48: =COUNTIFS(_TrackerTable35[Country],V$46,_TrackerTable35[Type],_USDashboardTable57111534[[#This Row],[Type]]) -> 0 | X48: =SUMIFS(_TrackerTable35[Market Value (in USD)],_TrackerTable35[Country],V$46,_TrackerTable35[Type],_USDashboardTable57111534[[#This Row],[Type]]) -> 0 | Y48: =IF(_USDashboardTable57111534[[#Totals],[Market Value (in USD)]]>0,_USDashboardTable57111534[[#This Row],[Market Value (in USD)]]/_USDashboardTable57111534[[#Totals],[Market Value (in USD)]],0) -> 0
B49: Defensive | C49: =COUNTIFS(_TrackerTable35[Type],_USDashboardTable561031[[#This Row],[Type]]) -> 2 | D49: =SUMIFS(_TrackerTable35[Market Value (in USD)],_TrackerTable35[Type],_USDashboardTable561031[[#This Row],[Type]]) -> 12776.42 | E49: =IF(_USDashboardTable561031[[#Totals],[Market Value (in USD)]]>0,_USDashboardTable561031[[#This Row],[Market Value (in USD)]]/_USDashboardTable561031[[#Totals],[Market Value (in USD)]],0) -> 0.24051463 | G49: Defensive | H49: =COUNTIFS(_TrackerTable35[Country],G$46,_TrackerTable35[Type],_USDashboardTable429[[#This Row],[Type]]) -> 2 | I49: =SUMIFS(_TrackerTable35[Market Value (in USD)],_TrackerTable35[Country],G$46,_TrackerTable35[Type],_USDashboardTable429[[#This Row],[Type]]) -> 12776.42 | J49: =IF(_USDashboardTable429[[#Totals],[Market Value (in USD)]]>0,_USDashboardTable429[[#This Row],[Market Value (in USD)]]/_USDashboardTable429[[#Totals],[Market Value (in USD)]],0) -> 0.37499971 | L49: Defensive | M49: =COUNTIFS(_TrackerTable35[Country],L$46,_TrackerTable35[Type],_USDashboardTable5930[[#This Row],[Type]]) -> 0 | N49: =SUMIFS(_TrackerTable35[Market Value (in USD)],_TrackerTable35[Country],L$46,_TrackerTable35[Type],_USDashboardTable5930[[#This Row],[Type]]) -> 0 | O49: =IF(_USDashboardTable5930[[#Totals],[Market Value (in USD)]]>0,_USDashboardTable5930[[#This Row],[Market Value (in USD)]]/_USDashboardTable5930[[#Totals],[Market Value (in USD)]],0) -> 0 | Q49: Defensive | R49: =COUNTIFS(_TrackerTable35[Country],Q$46,_TrackerTable35[Type],_USDashboardTable571132[[#This Row],[Type]]) -> 0 | S49: =SUMIFS(_TrackerTable35[Market Value (in USD)],_TrackerTable35[Country],Q$46,_TrackerTable35[Type],_USDashboardTable571132[[#This Row],[Type]]) -> 0 | T49: =IF(_USDashboardTable571132[[#Totals],[Market Value (in USD)]]>0,_USDashboardTable571132[[#This Row],[Market Value (in USD)]]/_USDashboardTable571132[[#Totals],[Market Value (in USD)]],0) -> 0 | V49: Defensive | W49: =COUNTIFS(_TrackerTable35[Country],V$46,_TrackerTable35[Type],_USDashboardTable57111534[[#This Row],[Type]]) -> 0 | X49: =SUMIFS(_TrackerTable35[Market Value (in USD)],_TrackerTable35[Country],V$46,_TrackerTable35[Type],_USDashboardTable57111534[[#This Row],[Type]]) -> 0 | Y49: =IF(_USDashboardTable57111534[[#Totals],[Market Value (in USD)]]>0,_USDashboardTable57111534[[#This Row],[Market Value (in USD)]]/_USDashboardTable57111534[[#Totals],[Market Value (in USD)]],0) -> 0
B50: Moderate Cyclical | C50: =COUNTIFS(_TrackerTable35[Type],_USDashboardTable561031[[#This Row],[Type]]) -> 6 | D50: =SUMIFS(_TrackerTable35[Market Value (in USD)],_TrackerTable35[Type],_USDashboardTable561031[[#This Row],[Type]]) -> 37396.608 | E50: =IF(_USDashboardTable561031[[#Totals],[Market Value (in USD)]]>0,_USDashboardTable561031[[#This Row],[Market Value (in USD)]]/_USDashboardTable561031[[#Totals],[Market Value (in USD)]],0) -> 0.70398682 | G50: Moderate Cyclical | H50: =COUNTIFS(_TrackerTable35[Country],G$46,_TrackerTable35[Type],_USDashboardTable429[[#This Row],[Type]]) -> 3 | I50: =SUMIFS(_TrackerTable35[Market Value (in USD)],_TrackerTable35[Country],G$46,_TrackerTable35[Type],_USDashboardTable429[[#This Row],[Type]]) -> 21294.06 | J50: =IF(_USDashboardTable429[[#Totals],[Market Value (in USD)]]>0,_USDashboardTable429[[#This Row],[Market Value (in USD)]]/_USDashboardTable429[[#Totals],[Market Value (in USD)]],0) -> 0.62500029 | L50: Moderate Cyclical | M50: =COUNTIFS(_TrackerTable35[Country],L$46,_TrackerTable35[Type],_USDashboardTable5930[[#This Row],[Type]]) -> 3 | N50: =SUMIFS(_TrackerTable35[Market Value (in USD)],_TrackerTable35[Country],L$46,_TrackerTable35[Type],_USDashboardTable5930[[#This Row],[Type]]) -> 16102.548 | O50: =IF(_USDashboardTable5930[[#Totals],[Market Value (in USD)]]>0,_USDashboardTable5930[[#This Row],[Market Value (in USD)]]/_USDashboardTable5930[[#Totals],[Market Value (in USD)]],0) -> 1 | Q50: Moderate Cyclical | R50: =COUNTIFS(_TrackerTable35[Country],Q$46,_TrackerTable35[Type],_USDashboardTable571132[[#This Row],[Type]]) -> 0 | S50: =SUMIFS(_TrackerTable35[Market Value (in USD)],_TrackerTable35[Country],Q$46,_TrackerTable35[Type],_USDashboardTable571132[[#This Row],[Type]]) -> 0 | T50: =IF(_USDashboardTable571132[[#Totals],[Market Value (in USD)]]>0,_USDashboardTable571132[[#This Row],[Market Value (in USD)]]/_USDashboardTable571132[[#Totals],[Market Value (in USD)]],0) -> 0 | V50: Moderate Cyclical | W50: =COUNTIFS(_TrackerTable35[Country],V$46,_TrackerTable35[Type],_USDashboardTable57111534[[#This Row],[Type]]) -> 0 | X50: =SUMIFS(_TrackerTable35[Market Value (in USD)],_TrackerTable35[Country],V$46,_TrackerTable35[Type],_USDashboardTable57111534[[#This Row],[Type]]) -> 0 | Y50: =IF(_USDashboardTable57111534[[#Totals],[Market Value (in USD)]]>0,_USDashboardTable57111534[[#This Row],[Market Value (in USD)]]/_USDashboardTable57111534[[#Totals],[Market Value (in USD)]],0) -> 0
B51: TOTAL | C51: =SUBTOTAL(109,_USDashboardTable561031[Count]) -> 9 | D51: =SUBTOTAL(109,_USDashboardTable561031[Market Value (in USD)]) -> 53121.177 | E51: =SUBTOTAL(109,_USDashboardTable561031[Percentage by Market Value]) -> 1 | G51: TOTAL | H51: =SUBTOTAL(109,_USDashboardTable429[Count]) -> 5 | I51: =SUBTOTAL(109,_USDashboardTable429[Market Value (in USD)]) -> 34070.48 | J51: =SUBTOTAL(109,_USDashboardTable429[Percentage by Market Value]) -> 1 | L51: TOTAL | M51: =SUBTOTAL(109,_USDashboardTable5930[Count]) -> 3 | N51: =SUBTOTAL(109,_USDashboardTable5930[Market Value (in USD)]) -> 16102.548 | O51: =SUBTOTAL(109,_USDashboardTable5930[Percentage by Market Value]) -> 1 | Q51: TOTAL | R51: =SUBTOTAL(109,_USDashboardTable571132[Count]) -> 1 | S51: =SUBTOTAL(109,_USDashboardTable571132[Market Value (in USD)]) -> 2948.1481 | T51: =SUBTOTAL(109,_USDashboardTable571132[Percentage by Market Value]) -> 1 | V51: TOTAL | W51: =SUBTOTAL(109,_USDashboardTable57111534[Count]) -> 0 | X51: =SUBTOTAL(109,_USDashboardTable57111534[Market Value (in USD)]) -> 0 | Y51: =SUBTOTAL(109,_USDashboardTable57111534[Percentage by Market Value]) -> 0
B104: Breakdown by Category (Market Value)
B105: TOTAL | G105: US | L105: China/HK | Q105: Singapore | V105: Australia
B106: Category | C106: Count | D106: Market Value (in USD) | E106: Percentage by Market Value | G106: Category | H106: Count | I106: Market Value (in USD) | J106: Percentage by Market Value | L106: Category | M106: Count | N106: Market Value (in USD) | O106: Percentage by Market Value | Q106: Category | R106: Count | S106: Market Value (in USD) | T106: Percentage by Market Value | V106: Category | W106: Count | X106: Market Value (in USD) | Y106: Percentage by Market Value
B107: Cash Cow | C107: =COUNTIFS(_TrackerTable35[Category],_USDashboardTable5626[[#This Row],[Category]]) -> 1 | D107: =SUMIFS(_TrackerTable35[Market Value (in USD)],_TrackerTable35[Category],_USDashboardTable5626[[#This Row],[Category]]) -> 2948.1481 | E107: =IF(_USDashboardTable5626[[#Totals],[Market Value (in USD)]]>0,_USDashboardTable5626[[#This Row],[Market Value (in USD)]]/_USDashboardTable5626[[#Totals],[Market Value (in USD)]],0) -> 0.055498548 | G107: Cash Cow | H107: =COUNTIFS(_TrackerTable35[Country],G$105,_TrackerTable35[Category],_USDashboardTable24[[#This Row],[Category]]) -> 0 | I107: =SUMIFS(_TrackerTable35[Market Value (in USD)],_TrackerTable35[Country],G$105,_TrackerTable35[Category],_USDashboardTable24[[#This Row],[Category]]) -> 0 | J107: =IF(_USDashboardTable24[[#Totals],[Market Value (in USD)]]>0,_USDashboardTable24[[#This Row],[Market Value (in USD)]]/_USDashboardTable24[[#Totals],[Market Value (in USD)]],0) -> 0 | L107: Cash Cow | M107: =COUNTIFS(_TrackerTable35[Country],L$105,_TrackerTable35[Category],_USDashboardTable525[[#This Row],[Category]]) -> 0 | N107: =SUMIFS(_TrackerTable35[Market Value (in USD)],_TrackerTable35[Country],L$105,_TrackerTable35[Category],_USDashboardTable525[[#This Row],[Category]]) -> 0 | O107: =IF(_USDashboardTable525[[#Totals],[Market Value (in USD)]]>0,_USDashboardTable525[[#This Row],[Market Value (in USD)]]/_USDashboardTable525[[#Totals],[Market Value (in USD)]],0) -> 0 | Q107: Cash Cow | R107: =COUNTIFS(_TrackerTable35[Country],Q$105,_TrackerTable35[Category],_USDashboardTable5727[[#This Row],[Category]]) -> 1 | S107: =SUMIFS(_TrackerTable35[Market Value (in USD)],_TrackerTable35[Country],Q$105,_TrackerTable35[Category],_USDashboardTable5727[[#This Row],[Category]]) -> 2948.1481 | T107: =IF(_USDashboardTable5727[[#Totals],[Market Value (in USD)]]>0,_USDashboardTable5727[[#This Row],[Market Value (in USD)]]/_USDashboardTable5727[[#Totals],[Market Value (in USD)]],0) -> 1 | V107: Cash Cow | W107: =COUNTIFS(_TrackerTable35[Country],V$105,_TrackerTable35[Category],_USDashboardTable571433[[#This Row],[Category]]) -> 0 | X107: =SUMIFS(_TrackerTable35[Market Value (in USD)],_TrackerTable35[Country],V$105,_TrackerTable35[Category],_USDashboardTable571433[[#This Row],[Category]]) -> 0 | Y107: =IF(_USDashboardTable571433[[#Totals],[Market Value (in USD)]]>0,_USDashboardTable571433[[#This Row],[Market Value (in USD)]]/_USDashboardTable571433[[#Totals],[Market Value (in USD)]],0) -> 0
B108: Deep Cyclical | C108: =COUNTIFS(_TrackerTable35[Category],_USDashboardTable5626[[#This Row],[Category]]) -> 0 | D108: =SUMIFS(_TrackerTable35[Market Value (in USD)],_TrackerTable35[Category],_USDashboardTable5626[[#This Row],[Category]]) -> 0 | E108: =IF(_USDashboardTable5626[[#Totals],[Market Value (in USD)]]>0,_USDashboardTable5626[[#This Row],[Market Value (in USD)]]/_USDashboardTable5626[[#Totals],[Market Value (in USD)]],0) -> 0 | G108: Deep Cyclical | H108: =COUNTIFS(_TrackerTable35[Country],G$105,_TrackerTable35[Category],_USDashboardTable24[[#This Row],[Category]]) -> 0 | I108: =SUMIFS(_TrackerTable35[Market Value (in USD)],_TrackerTable35[Country],G$105,_TrackerTable35[Category],_USDashboardTable24[[#This Row],[Category]]) -> 0 | J108: =IF(_USDashboardTable24[[#Totals],[Market Value (in USD)]]>0,_USDashboardTable24[[#This Row],[Market Value (in USD)]]/_USDashboardTable24[[#Totals],[Market Value (in USD)]],0) -> 0 | L108: Deep Cyclical | M108: =COUNTIFS(_TrackerTable35[Country],L$105,_TrackerTable35[Category],_USDashboardTable525[[#This Row],[Category]]) -> 0 | N108: =SUMIFS(_TrackerTable35[Market Value (in USD)],_TrackerTable35[Country],L$105,_TrackerTable35[Category],_USDashboardTable525[[#This Row],[Category]]) -> 0 | O108: =IF(_USDashboardTable525[[#Totals],[Market Value (in USD)]]>0,_USDashboardTable525[[#This Row],[Market Value (in USD)]]/_USDashboardTable525[[#Totals],[Market Value (in USD)]],0) -> 0 | Q108: Deep Cyclical | R108: =COUNTIFS(_TrackerTable35[Country],Q$105,_TrackerTable35[Category],_USDashboardTable5727[[#This Row],[Category]]) -> 0 | S108: =SUMIFS(_TrackerTable35[Market Value (in USD)],_TrackerTable35[Country],Q$105,_TrackerTable35[Category],_USDashboardTable5727[[#This Row],[Category]]) -> 0 | T108: =IF(_USDashboardTable5727[[#Totals],[Market Value (in USD)]]>0,_USDashboardTable5727[[#This Row],[Market Value (in USD)]]/_USDashboardTable5727[[#Totals],[Market Value (in USD)]],0) -> 0 | V108: Deep Cyclical | W108: =COUNTIFS(_TrackerTable35[Country],V$105,_TrackerTable35[Category],_USDashboardTable571433[[#This Row],[Category]]) -> 0 | X108: =SUMIFS(_TrackerTable35[Market Value (in USD)],_TrackerTable35[Country],V$105,_TrackerTable35[Category],_USDashboardTable571433[[#This Row],[Category]]) -> 0 | Y108: =IF(_USDashboardTable571433[[#Totals],[Market Value (in USD)]]>0,_USDashboardTable571433[[#This Row],[Market Value (in USD)]]/_USDashboardTable571433[[#Totals],[Market Value (in USD)]],0) -> 0
B109: Deep Value | C109: =COUNTIFS(_TrackerTable35[Category],_USDashboardTable5626[[#This Row],[Category]]) -> 0 | D109: =SUMIFS(_TrackerTable35[Market Value (in USD)],_TrackerTable35[Category],_USDashboardTable5626[[#This Row],[Category]]) -> 0 | E109: =IF(_USDashboardTable5626[[#Totals],[Market Value (in USD)]]>0,_USDashboardTable5626[[#This Row],[Market Value (in USD)]]/_USDashboardTable5626[[#Totals],[Market Value (in USD)]],0) -> 0 | G109: Deep Value | H109: =COUNTIFS(_TrackerTable35[Country],G$105,_TrackerTable35[Category],_USDashboardTable24[[#This Row],[Category]]) -> 0 | I109: =SUMIFS(_TrackerTable35[Market Value (in USD)],_TrackerTable35[Country],G$105,_TrackerTable35[Category],_USDashboardTable24[[#This Row],[Category]]) -> 0 | J109: =IF(_USDashboardTable24[[#Totals],[Market Value (in USD)]]>0,_USDashboardTable24[[#This Row],[Market Value (in USD)]]/_USDashboardTable24[[#Totals],[Market Value (in USD)]],0) -> 0 | L109: Deep Value | M109: =COUNTIFS(_TrackerTable35[Country],L$105,_TrackerTable35[Category],_USDashboardTable525[[#This Row],[Category]]) -> 0 | N109: =SUMIFS(_TrackerTable35[Market Value (in USD)],_TrackerTable35[Country],L$105,_TrackerTable35[Category],_USDashboardTable525[[#This Row],[Category]]) -> 0 | O109: =IF(_USDashboardTable525[[#Totals],[Market Value (in USD)]]>0,_USDashboardTable525[[#This Row],[Market Value (in USD)]]/_USDashboardTable525[[#Totals],[Market Value (in USD)]],0) -> 0 | Q109: Deep Value | R109: =COUNTIFS(_TrackerTable35[Country],Q$105,_TrackerTable35[Category],_USDashboardTable5727[[#This Row],[Category]]) -> 0 | S109: =SUMIFS(_TrackerTable35[Market Value (in USD)],_TrackerTable35[Country],Q$105,_TrackerTable35[Category],_USDashboardTable5727[[#This Row],[Category]]) -> 0 | T109: =IF(_USDashboardTable5727[[#Totals],[Market Value (in USD)]]>0,_USDashboardTable5727[[#This Row],[Market Value (in USD)]]/_USDashboardTable5727[[#Totals],[Market Value (in USD)]],0) -> 0 | V109: Deep Value | W109: =COUNTIFS(_TrackerTable35[Country],V$105,_TrackerTable35[Category],_USDashboardTable571433[[#This Row],[Category]]) -> 0 | X109: =SUMIFS(_TrackerTable35[Market Value (in USD)],_TrackerTable35[Country],V$105,_TrackerTable35[Category],_USDashboardTable571433[[#This Row],[Category]]) -> 0 | Y109: =IF(_USDashboardTable571433[[#Totals],[Market Value (in USD)]]>0,_USDashboardTable571433[[#This Row],[Market Value (in USD)]]/_USDashboardTable571433[[#Totals],[Market Value (in USD)]],0) -> 0
B110: ETF | C110: =COUNTIFS(_TrackerTable35[Category],_USDashboardTable5626[[#This Row],[Category]]) -> 1 | D110: =SUMIFS(_TrackerTable35[Market Value (in USD)],_TrackerTable35[Category],_USDashboardTable5626[[#This Row],[Category]]) -> 5955.18 | E110: =IF(_USDashboardTable5626[[#Totals],[Market Value (in USD)]]>0,_USDashboardTable5626[[#This Row],[Market Value (in USD)]]/_USDashboardTable5626[[#Totals],[Market Value (in USD)]],0) -> 0.11210557 | G110: ETF | H110: =COUNTIFS(_TrackerTable35[Country],G$105,_TrackerTable35[Category],_USDashboardTable24[[#This Row],[Category]]) -> 0 | I110: =SUMIFS(_TrackerTable35[Market Value (in USD)],_TrackerTable35[Country],G$105,_TrackerTable35[Category],_USDashboardTable24[[#This Row],[Category]]) -> 0 | J110: =IF(_USDashboardTable24[[#Totals],[Market Value (in USD)]]>0,_USDashboardTable24[[#This Row],[Market Value (in USD)]]/_USDashboardTable24[[#Totals],[Market Value (in USD)]],0) -> 0 | L110: ETF | M110: =COUNTIFS(_TrackerTable35[Country],L$105,_TrackerTable35[Category],_USDashboardTable525[[#This Row],[Category]]) -> 1 | N110: =SUMIFS(_TrackerTable35[Market Value (in USD)],_TrackerTable35[Country],L$105,_TrackerTable35[Category],_USDashboardTable525[[#This Row],[Category]]) -> 5955.18 | O110: =IF(_USDashboardTable525[[#Totals],[Market Value (in USD)]]>0,_USDashboardTable525[[#This Row],[Market Value (in USD)]]/_USDashboardTable525[[#Totals],[Market Value (in USD)]],0) -> 0.36982842 | Q110: ETF | R110: =COUNTIFS(_TrackerTable35[Country],Q$105,_TrackerTable35[Category],_USDashboardTable5727[[#This Row],[Category]]) -> 0 | S110: =SUMIFS(_TrackerTable35[Market Value (in USD)],_TrackerTable35[Country],Q$105,_TrackerTable35[Category],_USDashboardTable5727[[#This Row],[Category]]) -> 0 | T110: =IF(_USDashboardTable5727[[#Totals],[Market Value (in USD)]]>0,_USDashboardTable5727[[#This Row],[Market Value (in USD)]]/_USDashboardTable5727[[#Totals],[Market Value (in USD)]],0) -> 0 | V110: ETF | W110: =COUNTIFS(_TrackerTable35[Country],V$105,_TrackerTable35[Category],_USDashboardTable571433[[#This Row],[Category]]) -> 0 | X110: =SUMIFS(_TrackerTable35[Market Value (in USD)],_TrackerTable35[Country],V$105,_TrackerTable35[Category],_USDashboardTable571433[[#This Row],[Category]]) -> 0 | Y110: =IF(_USDashboardTable571433[[#Totals],[Market Value (in USD)]]>0,_USDashboardTable571433[[#This Row],[Market Value (in USD)]]/_USDashboardTable571433[[#Totals],[Market Value (in USD)]],0) -> 0
B111: Growth | C111: =COUNTIFS(_TrackerTable35[Category],_USDashboardTable5626[[#This Row],[Category]]) -> 5 | D111: =SUMIFS(_TrackerTable35[Market Value (in USD)],_TrackerTable35[Category],_USDashboardTable5626[[#This Row],[Category]]) -> 30648.528 | E111: =IF(_USDashboardTable5626[[#Totals],[Market Value (in USD)]]>0,_USDashboardTable5626[[#This Row],[Market Value (in USD)]]/_USDashboardTable5626[[#Totals],[Market Value (in USD)]],0) -> 0.576955 | G111: Growth | H111: =COUNTIFS(_TrackerTable35[Country],G$105,_TrackerTable35[Category],_USDashboardTable24[[#This Row],[Category]]) -> 3 | I111: =SUMIFS(_TrackerTable35[Market Value (in USD)],_TrackerTable35[Country],G$105,_TrackerTable35[Category],_USDashboardTable24[[#This Row],[Category]]) -> 20501.16 | J111: =IF(_USDashboardTable24[[#Totals],[Market Value (in USD)]]>0,_USDashboardTable24[[#This Row],[Market Value (in USD)]]/_USDashboardTable24[[#Totals],[Market Value (in USD)]],0) -> 0.60172795 | L111: Growth | M111: =COUNTIFS(_TrackerTable35[Country],L$105,_TrackerTable35[Category],_USDashboardTable525[[#This Row],[Category]]) -> 2 | N111: =SUMIFS(_TrackerTable35[Market Value (in USD)],_TrackerTable35[Country],L$105,_TrackerTable35[Category],_USDashboardTable525[[#This Row],[Category]]) -> 10147.368 | O111: =IF(_USDashboardTable525[[#Totals],[Market Value (in USD)]]>0,_USDashboardTable525[[#This Row],[Market Value (in USD)]]/_USDashboardTable525[[#Totals],[Market Value (in USD)]],0) -> 0.63017158 | Q111: Growth | R111: =COUNTIFS(_TrackerTable35[Country],Q$105,_TrackerTable35[Category],_USDashboardTable5727[[#This Row],[Category]]) -> 0 | S111: =SUMIFS(_TrackerTable35[Market Value (in USD)],_TrackerTable35[Country],Q$105,_TrackerTable35[Category],_USDashboardTable5727[[#This Row],[Category]]) -> 0 | T111: =IF(_USDashboardTable5727[[#Totals],[Market Value (in USD)]]>0,_USDashboardTable5727[[#This Row],[Market Value (in USD)]]/_USDashboardTable5727[[#Totals],[Market Value (in USD)]],0) -> 0 | V111: Growth | W111: =COUNTIFS(_TrackerTable35[Country],V$105,_TrackerTable35[Category],_USDashboardTable571433[[#This Row],[Category]]) -> 0 | X111: =SUMIFS(_TrackerTable35[Market Value (in USD)],_TrackerTable35[Country],V$105,_TrackerTable35[Category],_USDashboardTable571433[[#This Row],[Category]]) -> 0 | Y111: =IF(_USDashboardTable571433[[#Totals],[Market Value (in USD)]]>0,_USDashboardTable571433[[#This Row],[Market Value (in USD)]]/_USDashboardTable571433[[#Totals],[Market Value (in USD)]],0) -> 0
B112: Other | C112: =COUNTIFS(_TrackerTable35[Category],_USDashboardTable5626[[#This Row],[Category]]) -> 0 | D112: =SUMIFS(_TrackerTable35[Market Value (in USD)],_TrackerTable35[Category],_USDashboardTable5626[[#This Row],[Category]]) -> 0 | E112: =IF(_USDashboardTable5626[[#Totals],[Market Value (in USD)]]>0,_USDashboardTable5626[[#This Row],[Market Value (in USD)]]/_USDashboardTable5626[[#Totals],[Market Value (in USD)]],0) -> 0 | G112: Other | H112: =COUNTIFS(_TrackerTable35[Country],G$105,_TrackerTable35[Category],_USDashboardTable24[[#This Row],[Category]]) -> 0 | I112: =SUMIFS(_TrackerTable35[Market Value (in USD)],_TrackerTable35[Country],G$105,_TrackerTable35[Category],_USDashboardTable24[[#This Row],[Category]]) -> 0 | J112: =IF(_USDashboardTable24[[#Totals],[Market Value (in USD)]]>0,_USDashboardTable24[[#This Row],[Market Value (in USD)]]/_USDashboardTable24[[#Totals],[Market Value (in USD)]],0) -> 0 | L112: Other | M112: =COUNTIFS(_TrackerTable35[Country],L$105,_TrackerTable35[Category],_USDashboardTable525[[#This Row],[Category]]) -> 0 | N112: =SUMIFS(_TrackerTable35[Market Value (in USD)],_TrackerTable35[Country],L$105,_TrackerTable35[Category],_USDashboardTable525[[#This Row],[Category]]) -> 0 | O112: =IF(_USDashboardTable525[[#Totals],[Market Value (in USD)]]>0,_USDashboardTable525[[#This Row],[Market Value (in USD)]]/_USDashboardTable525[[#Totals],[Market Value (in USD)]],0) -> 0 | Q112: Other | R112: =COUNTIFS(_TrackerTable35[Country],Q$105,_TrackerTable35[Category],_USDashboardTable5727[[#This Row],[Category]]) -> 0 | S112: =SUMIFS(_TrackerTable35[Market Value (in USD)],_TrackerTable35[Country],Q$105,_TrackerTable35[Category],_USDashboardTable5727[[#This Row],[Category]]) -> 0 | T112: =IF(_USDashboardTable5727[[#Totals],[Market Value (in USD)]]>0,_USDashboardTable5727[[#This Row],[Market Value (in USD)]]/_USDashboardTable5727[[#Totals],[Market Value (in USD)]],0) -> 0 | V112: Other | W112: =COUNTIFS(_TrackerTable35[Country],V$105,_TrackerTable35[Category],_USDashboardTable571433[[#This Row],[Category]]) -> 0 | X112: =SUMIFS(_TrackerTable35[Market Value (in USD)],_TrackerTable35[Country],V$105,_TrackerTable35[Category],_USDashboardTable571433[[#This Row],[Category]]) -> 0 | Y112: =IF(_USDashboardTable571433[[#Totals],[Market Value (in USD)]]>0,_USDashboardTable571433[[#This Row],[Market Value (in USD)]]/_USDashboardTable571433[[#Totals],[Market Value (in USD)]],0) -> 0
B113: Predictable | C113: =COUNTIFS(_TrackerTable35[Category],_USDashboardTable5626[[#This Row],[Category]]) -> 2 | D113: =SUMIFS(_TrackerTable35[Market Value (in USD)],_TrackerTable35[Category],_USDashboardTable5626[[#This Row],[Category]]) -> 13569.32 | E113: =IF(_USDashboardTable5626[[#Totals],[Market Value (in USD)]]>0,_USDashboardTable5626[[#This Row],[Market Value (in USD)]]/_USDashboardTable5626[[#Totals],[Market Value (in USD)]],0) -> 0.25544088 | G113: Predictable | H113: =COUNTIFS(_TrackerTable35[Country],G$105,_TrackerTable35[Category],_USDashboardTable24[[#This Row],[Category]]) -> 2 | I113: =SUMIFS(_TrackerTable35[Market Value (in USD)],_TrackerTable35[Country],G$105,_TrackerTable35[Category],_USDashboardTable24[[#This Row],[Category]]) -> 13569.32 | J113: =IF(_USDashboardTable24[[#Totals],[Market Value (in USD)]]>0,_USDashboardTable24[[#This Row],[Market Value (in USD)]]/_USDashboardTable24[[#Totals],[Market Value (in USD)]],0) -> 0.39827205 | L113: Predictable | M113: =COUNTIFS(_TrackerTable35[Country],L$105,_TrackerTable35[Category],_USDashboardTable525[[#This Row],[Category]]) -> 0 | N113: =SUMIFS(_TrackerTable35[Market Value (in USD)],_TrackerTable35[Country],L$105,_TrackerTable35[Category],_USDashboardTable525[[#This Row],[Category]]) -> 0 | O113: =IF(_USDashboardTable525[[#Totals],[Market Value (in USD)]]>0,_USDashboardTable525[[#This Row],[Market Value (in USD)]]/_USDashboardTable525[[#Totals],[Market Value (in USD)]],0) -> 0 | Q113: Predictable | R113: =COUNTIFS(_TrackerTable35[Country],Q$105,_TrackerTable35[Category],_USDashboardTable5727[[#This Row],[Category]]) -> 0 | S113: =SUMIFS(_TrackerTable35[Market Value (in USD)],_TrackerTable35[Country],Q$105,_TrackerTable35[Category],_USDashboardTable5727[[#This Row],[Category]]) -> 0 | T113: =IF(_USDashboardTable5727[[#Totals],[Market Value (in USD)]]>0,_USDashboardTable5727[[#This Row],[Market Value (in USD)]]/_USDashboardTable5727[[#Totals],[Market Value (in USD)]],0) -> 0 | V113: Predictable | W113: =COUNTIFS(_TrackerTable35[Country],V$105,_TrackerTable35[Category],_USDashboardTable571433[[#This Row],[Category]]) -> 0 | X113: =SUMIFS(_TrackerTable35[Market Value (in USD)],_TrackerTable35[Country],V$105,_TrackerTable35[Category],_USDashboardTable571433[[#This Row],[Category]]) -> 0 | Y113: =IF(_USDashboardTable571433[[#Totals],[Market Value (in USD)]]>0,_USDashboardTable571433[[#This Row],[Market Value (in USD)]]/_USDashboardTable571433[[#Totals],[Market Value (in USD)]],0) -> 0
B114: Speculative | C114: =COUNTIFS(_TrackerTable35[Category],_USDashboardTable5626[[#This Row],[Category]]) -> 0 | D114: =SUMIFS(_TrackerTable35[Market Value (in USD)],_TrackerTable35[Category],_USDashboardTable5626[[#This Row],[Category]]) -> 0 | E114: =IF(_USDashboardTable5626[[#Totals],[Market Value (in USD)]]>0,_USDashboardTable5626[[#This Row],[Market Value (in USD)]]/_USDashboardTable5626[[#Totals],[Market Value (in USD)]],0) -> 0 | G114: Speculative | H114: =COUNTIFS(_TrackerTable35[Country],G$105,_TrackerTable35[Category],_USDashboardTable24[[#This Row],[Category]]) -> 0 | I114: =SUMIFS(_TrackerTable35[Market Value (in USD)],_TrackerTable35[Country],G$105,_TrackerTable35[Category],_USDashboardTable24[[#This Row],[Category]]) -> 0 | J114: =IF(_USDashboardTable24[[#Totals],[Market Value (in USD)]]>0,_USDashboardTable24[[#This Row],[Market Value (in USD)]]/_USDashboardTable24[[#Totals],[Market Value (in USD)]],0) -> 0 | L114: Speculative | M114: =COUNTIFS(_TrackerTable35[Country],L$105,_TrackerTable35[Category],_USDashboardTable525[[#This Row],[Category]]) -> 0 | N114: =SUMIFS(_TrackerTable35[Market Value (in USD)],_TrackerTable35[Country],L$105,_TrackerTable35[Category],_USDashboardTable525[[#This Row],[Category]]) -> 0 | O114: =IF(_USDashboardTable525[[#Totals],[Market Value (in USD)]]>0,_USDashboardTable525[[#This Row],[Market Value (in USD)]]/_USDashboardTable525[[#Totals],[Market Value (in USD)]],0) -> 0 | Q114: Speculative | R114: =COUNTIFS(_TrackerTable35[Country],Q$105,_TrackerTable35[Category],_USDashboardTable5727[[#This Row],[Category]]) -> 0 | S114: =SUMIFS(_TrackerTable35[Market Value (in USD)],_TrackerTable35[Country],Q$105,_TrackerTable35[Category],_USDashboardTable5727[[#This Row],[Category]]) -> 0 | T114: =IF(_USDashboardTable5727[[#Totals],[Market Value (in USD)]]>0,_USDashboardTable5727[[#This Row],[Market Value (in USD)]]/_USDashboardTable5727[[#Totals],[Market Value (in USD)]],0) -> 0 | V114: Speculative | W114: =COUNTIFS(_TrackerTable35[Country],V$105,_TrackerTable35[Category],_USDashboardTable571433[[#This Row],[Category]]) -> 0 | X114: =SUMIFS(_TrackerTable35[Market Value (in USD)],_TrackerTable35[Country],V$105,_TrackerTable35[Category],_USDashboardTable571433[[#This Row],[Category]]) -> 0 | Y114: =IF(_USDashboardTable571433[[#Totals],[Market Value (in USD)]]>0,_USDashboardTable571433[[#This Row],[Market Value (in USD)]]/_USDashboardTable571433[[#Totals],[Market Value (in USD)]],0) -> 0
B115: Turnaround | C115: =COUNTIFS(_TrackerTable35[Category],_USDashboardTable5626[[#This Row],[Category]]) -> 0 | D115: =SUMIFS(_TrackerTable35[Market Value (in USD)],_TrackerTable35[Category],_USDashboardTable5626[[#This Row],[Category]]) -> 0 | E115: =IF(_USDashboardTable5626[[#Totals],[Market Value (in USD)]]>0,_USDashboardTable5626[[#This Row],[Market Value (in USD)]]/_USDashboardTable5626[[#Totals],[Market Value (in USD)]],0) -> 0 | G115: Turnaround | H115: =COUNTIFS(_TrackerTable35[Country],G$105,_TrackerTable35[Category],_USDashboardTable24[[#This Row],[Category]]) -> 0 | I115: =SUMIFS(_TrackerTable35[Market Value (in USD)],_TrackerTable35[Country],G$105,_TrackerTable35[Category],_USDashboardTable24[[#This Row],[Category]]) -> 0 | J115: =IF(_USDashboardTable24[[#Totals],[Market Value (in USD)]]>0,_USDashboardTable24[[#This Row],[Market Value (in USD)]]/_USDashboardTable24[[#Totals],[Market Value (in USD)]],0) -> 0 | L115: Turnaround | M115: =COUNTIFS(_TrackerTable35[Country],L$105,_TrackerTable35[Category],_USDashboardTable525[[#This Row],[Category]]) -> 0 | N115: =SUMIFS(_TrackerTable35[Market Value (in USD)],_TrackerTable35[Country],L$105,_TrackerTable35[Category],_USDashboardTable525[[#This Row],[Category]]) -> 0 | O115: =IF(_USDashboardTable525[[#Totals],[Market Value (in USD)]]>0,_USDashboardTable525[[#This Row],[Market Value (in USD)]]/_USDashboardTable525[[#Totals],[Market Value (in USD)]],0) -> 0 | Q115: Turnaround | R115: =COUNTIFS(_TrackerTable35[Country],Q$105,_TrackerTable35[Category],_USDashboardTable5727[[#This Row],[Category]]) -> 0 | S115: =SUMIFS(_TrackerTable35[Market Value (in USD)],_TrackerTable35[Country],Q$105,_TrackerTable35[Category],_USDashboardTable5727[[#This Row],[Category]]) -> 0 | T115: =IF(_USDashboardTable5727[[#Totals],[Market Value (in USD)]]>0,_USDashboardTable5727[[#This Row],[Market Value (in USD)]]/_USDashboardTable5727[[#Totals],[Market Value (in USD)]],0) -> 0 | V115: Turnaround | W115: =COUNTIFS(_TrackerTable35[Country],V$105,_TrackerTable35[Category],_USDashboardTable571433[[#This Row],[Category]]) -> 0 | X115: =SUMIFS(_TrackerTable35[Market Value (in USD)],_TrackerTable35[Country],V$105,_TrackerTable35[Category],_USDashboardTable571433[[#This Row],[Category]]) -> 0 | Y115: =IF(_USDashboardTable571433[[#Totals],[Market Value (in USD)]]>0,_USDashboardTable571433[[#This Row],[Market Value (in USD)]]/_USDashboardTable571433[[#Totals],[Market Value (in USD)]],0) -> 0
B116: TOTAL | C116: =SUBTOTAL(109,_USDashboardTable5626[Count]) -> 9 | D116: =SUBTOTAL(109,_USDashboardTable5626[Market Value (in USD)]) -> 53121.177 | E116: =SUBTOTAL(109,_USDashboardTable5626[Percentage by Market Value]) -> 1 | G116: TOTAL | H116: =SUBTOTAL(109,_USDashboardTable24[Count]) -> 5 | I116: =SUBTOTAL(109,_USDashboardTable24[Market Value (in USD)]) -> 34070.48 | J116: =SUBTOTAL(109,_USDashboardTable24[Percentage by Market Value]) -> 1 | L116: TOTAL | M116: =SUBTOTAL(109,_USDashboardTable525[Count]) -> 3 | N116: =SUBTOTAL(109,_USDashboardTable525[Market Value (in USD)]) -> 16102.548 | O116: =SUBTOTAL(109,_USDashboardTable525[Percentage by Market Value]) -> 1 | Q116: TOTAL | R116: =SUBTOTAL(109,_USDashboardTable5727[Count]) -> 1 | S116: =SUBTOTAL(109,_USDashboardTable5727[Market Value (in USD)]) -> 2948.1481 | T116: =SUBTOTAL(109,_USDashboardTable5727[Percentage by Market Value]) -> 1 | V116: TOTAL | W116: =SUBTOTAL(109,_USDashboardTable571433[Count]) -> 0 | X116: =SUBTOTAL(109,_USDashboardTable571433[Market Value (in USD)]) -> 0 | Y116: =SUBTOTAL(109,_USDashboardTable571433[Percentage by Market Value]) -> 0
B168: Breakdown by Sector (Market Value)
B169: TOTAL | G169: US | L169: China/HK | Q169: Singapore | V169: Australia
B170: Sector | C170: Count | D170: Market Value (in USD) | E170: Percentage by Market Value | G170: Sector | H170: Count | I170: Market Value (in USD) | J170: Percentage by Market Value | L170: Sector | M170: Count | N170: Market Value (in USD) | O170: Percentage by Market Value | Q170: Sector | R170: Count | S170: Market Value (in USD) | T170: Percentage by Market Value | V170: Sector | W170: Count | X170: Market Value (in USD) | Y170: Percentage by Market Value
B171: Communication Services | C171: =COUNTIFS(_TrackerTable35[Sector],_USDashboardTable56265[[#This Row],[Sector]]) -> 2 | D171: =SUMIFS(_TrackerTable35[Market Value (in USD)],_TrackerTable35[Sector],_USDashboardTable56265[[#This Row],[Sector]]) -> 16256.16 | E171: =IF(_USDashboardTable56265[[#Totals],[Market Value (in USD)]]>0,_USDashboardTable56265[[#This Row],[Market Value (in USD)]]/_USDashboardTable56265[[#Totals],[Market Value (in USD)]],0) -> 0.30602033 | G171: Communication Services | H171: =COUNTIFS(_TrackerTable35[Country],G$169,_TrackerTable35[Sector],_USDashboardTable243[[#This Row],[Sector]]) -> 1 | I171: =SUMIFS(_TrackerTable35[Market Value (in USD)],_TrackerTable35[Country],G$169,_TrackerTable35[Sector],_USDashboardTable243[[#This Row],[Sector]]) -> 11314.44 | J171: =IF(_USDashboardTable243[[#Totals],[Market Value (in USD)]]>0,_USDashboardTable243[[#This Row],[Market Value (in USD)]]/_USDashboardTable243[[#Totals],[Market Value (in USD)]],0) -> 0.33208925 | L171: Communication Services | M171: =COUNTIFS(_TrackerTable35[Country],L$169,_TrackerTable35[Sector],_USDashboardTable5254[[#This Row],[Sector]]) -> 1 | N171: =SUMIFS(_TrackerTable35[Market Value (in USD)],_TrackerTable35[Country],L$169,_TrackerTable35[Sector],_USDashboardTable5254[[#This Row],[Sector]]) -> 4941.7202 | O171: =IF(_USDashboardTable5254[[#Totals],[Market Value (in USD)]]>0,_USDashboardTable5254[[#This Row],[Market Value (in USD)]]/_USDashboardTable5254[[#Totals],[Market Value (in USD)]],0) -> 0.30689056 | Q171: Communication Services | R171: =COUNTIFS(_TrackerTable35[Country],Q$169,_TrackerTable35[Sector],_USDashboardTable57276[[#This Row],[Sector]]) -> 0 | S171: =SUMIFS(_TrackerTable35[Market Value (in USD)],_TrackerTable35[Country],Q$169,_TrackerTable35[Sector],_USDashboardTable57276[[#This Row],[Sector]]) -> 0 | T171: =IF(_USDashboardTable57276[[#Totals],[Market Value (in USD)]]>0,_USDashboardTable57276[[#This Row],[Market Value (in USD)]]/_USDashboardTable57276[[#Totals],[Market Value (in USD)]],0) -> 0 | V171: Communication Services | W171: =COUNTIFS(_TrackerTable35[Country],V$169,_TrackerTable35[Sector],_USDashboardTable5714337[[#This Row],[Sector]]) -> 0 | X171: =SUMIFS(_TrackerTable35[Market Value (in USD)],_TrackerTable35[Country],V$169,_TrackerTable35[Sector],_USDashboardTable5714337[[#This Row],[Sector]]) -> 0 | Y171: =IF(_USDashboardTable5714337[[#Totals],[Market Value (in USD)]]>0,_USDashboardTable5714337[[#This Row],[Market Value (in USD)]]/_USDashboardTable5714337[[#Totals],[Market Value (in USD)]],0) -> 0
B172: Consumer Discretionary | C172: =COUNTIFS(_TrackerTable35[Sector],_USDashboardTable56265[[#This Row],[Sector]]) -> 1 | D172: =SUMIFS(_TrackerTable35[Market Value (in USD)],_TrackerTable35[Sector],_USDashboardTable56265[[#This Row],[Sector]]) -> 5205.6483 | E172: =IF(_USDashboardTable56265[[#Totals],[Market Value (in USD)]]>0,_USDashboardTable56265[[#This Row],[Market Value (in USD)]]/_USDashboardTable56265[[#Totals],[Market Value (in USD)]],0) -> 0.097995726 | G172: Consumer Discretionary | H172: =COUNTIFS(_TrackerTable35[Country],G$169,_TrackerTable35[Sector],_USDashboardTable243[[#This Row],[Sector]]) -> 0 | I172: =SUMIFS(_TrackerTable35[Market Value (in USD)],_TrackerTable35[Country],G$169,_TrackerTable35[Sector],_USDashboardTable243[[#This Row],[Sector]]) -> 0 | J172: =IF(_USDashboardTable243[[#Totals],[Market Value (in USD)]]>0,_USDashboardTable243[[#This Row],[Market Value (in USD)]]/_USDashboardTable243[[#Totals],[Market Value (in USD)]],0) -> 0 | L172: Consumer Discretionary | M172: =COUNTIFS(_TrackerTable35[Country],L$169,_TrackerTable35[Sector],_USDashboardTable5254[[#This Row],[Sector]]) -> 1 | N172: =SUMIFS(_TrackerTable35[Market Value (in USD)],_TrackerTable35[Country],L$169,_TrackerTable35[Sector],_USDashboardTable5254[[#This Row],[Sector]]) -> 5205.6483 | O172: =IF(_USDashboardTable5254[[#Totals],[Market Value (in USD)]]>0,_USDashboardTable5254[[#This Row],[Market Value (in USD)]]/_USDashboardTable5254[[#Totals],[Market Value (in USD)]],0) -> 0.32328102 | Q172: Consumer Discretionary | R172: =COUNTIFS(_TrackerTable35[Country],Q$169,_TrackerTable35[Sector],_USDashboardTable57276[[#This Row],[Sector]]) -> 0 | S172: =SUMIFS(_TrackerTable35[Market Value (in USD)],_TrackerTable35[Country],Q$169,_TrackerTable35[Sector],_USDashboardTable57276[[#This Row],[Sector]]) -> 0 | T172: =IF(_USDashboardTable57276[[#Totals],[Market Value (in USD)]]>0,_USDashboardTable57276[[#This Row],[Market Value (in USD)]]/_USDashboardTable57276[[#Totals],[Market Value (in USD)]],0) -> 0 | V172: Consumer Discretionary | W172: =COUNTIFS(_TrackerTable35[Country],V$169,_TrackerTable35[Sector],_USDashboardTable5714337[[#This Row],[Sector]]) -> 0 | X172: =SUMIFS(_TrackerTable35[Market Value (in USD)],_TrackerTable35[Country],V$169,_TrackerTable35[Sector],_USDashboardTable5714337[[#This Row],[Sector]]) -> 0 | Y172: =IF(_USDashboardTable5714337[[#Totals],[Market Value (in USD)]]>0,_USDashboardTable5714337[[#This Row],[Market Value (in USD)]]/_USDashboardTable5714337[[#Totals],[Market Value (in USD)]],0) -> 0
B173: Consumer Staples | C173: =COUNTIFS(_TrackerTable35[Sector],_USDashboardTable56265[[#This Row],[Sector]]) -> 1 | D173: =SUMIFS(_TrackerTable35[Market Value (in USD)],_TrackerTable35[Sector],_USDashboardTable56265[[#This Row],[Sector]]) -> 6783.92 | E173: =IF(_USDashboardTable56265[[#Totals],[Market Value (in USD)]]>0,_USDashboardTable56265[[#This Row],[Market Value (in USD)]]/_USDashboardTable56265[[#Totals],[Market Value (in USD)]],0) -> 0.12770651 | G173: Consumer Staples | H173: =COUNTIFS(_TrackerTable35[Country],G$169,_TrackerTable35[Sector],_USDashboardTable243[[#This Row],[Sector]]) -> 1 | I173: =SUMIFS(_TrackerTable35[Market Value (in USD)],_TrackerTable35[Country],G$169,_TrackerTable35[Sector],_USDashboardTable243[[#This Row],[Sector]]) -> 6783.92 | J173: =IF(_USDashboardTable243[[#Totals],[Market Value (in USD)]]>0,_USDashboardTable243[[#This Row],[Market Value (in USD)]]/_USDashboardTable243[[#Totals],[Market Value (in USD)]],0) -> 0.19911431 | L173: Consumer Staples | M173: =COUNTIFS(_TrackerTable35[Country],L$169,_TrackerTable35[Sector],_USDashboardTable5254[[#This Row],[Sector]]) -> 0 | N173: =SUMIFS(_TrackerTable35[Market Value (in USD)],_TrackerTable35[Country],L$169,_TrackerTable35[Sector],_USDashboardTable5254[[#This Row],[Sector]]) -> 0 | O173: =IF(_USDashboardTable5254[[#Totals],[Market Value (in USD)]]>0,_USDashboardTable5254[[#This Row],[Market Value (in USD)]]/_USDashboardTable5254[[#Totals],[Market Value (in USD)]],0) -> 0 | Q173: Consumer Staples | R173: =COUNTIFS(_TrackerTable35[Country],Q$169,_TrackerTable35[Sector],_USDashboardTable57276[[#This Row],[Sector]]) -> 0 | S173: =SUMIFS(_TrackerTable35[Market Value (in USD)],_TrackerTable35[Country],Q$169,_TrackerTable35[Sector],_USDashboardTable57276[[#This Row],[Sector]]) -> 0 | T173: =IF(_USDashboardTable57276[[#Totals],[Market Value (in USD)]]>0,_USDashboardTable57276[[#This Row],[Market Value (in USD)]]/_USDashboardTable57276[[#Totals],[Market Value (in USD)]],0) -> 0 | V173: Consumer Staples | W173: =COUNTIFS(_TrackerTable35[Country],V$169,_TrackerTable35[Sector],_USDashboardTable5714337[[#This Row],[Sector]]) -> 0 | X173: =SUMIFS(_TrackerTable35[Market Value (in USD)],_TrackerTable35[Country],V$169,_TrackerTable35[Sector],_USDashboardTable5714337[[#This Row],[Sector]]) -> 0 | Y173: =IF(_USDashboardTable5714337[[#Totals],[Market Value (in USD)]]>0,_USDashboardTable5714337[[#This Row],[Market Value (in USD)]]/_USDashboardTable5714337[[#Totals],[Market Value (in USD)]],0) -> 0
B174: Diversified | C174: =COUNTIFS(_TrackerTable35[Sector],_USDashboardTable56265[[#This Row],[Sector]]) -> 1 | D174: =SUMIFS(_TrackerTable35[Market Value (in USD)],_TrackerTable35[Sector],_USDashboardTable56265[[#This Row],[Sector]]) -> 5955.18 | E174: =IF(_USDashboardTable56265[[#Totals],[Market Value (in USD)]]>0,_USDashboardTable56265[[#This Row],[Market Value (in USD)]]/_USDashboardTable56265[[#Totals],[Market Value (in USD)]],0) -> 0.11210557 | G174: Diversified | H174: =COUNTIFS(_TrackerTable35[Country],G$169,_TrackerTable35[Sector],_USDashboardTable243[[#This Row],[Sector]]) -> 0 | I174: =SUMIFS(_TrackerTable35[Market Value (in USD)],_TrackerTable35[Country],G$169,_TrackerTable35[Sector],_USDashboardTable243[[#This Row],[Sector]]) -> 0 | J174: =IF(_USDashboardTable243[[#Totals],[Market Value (in USD)]]>0,_USDashboardTable243[[#This Row],[Market Value (in USD)]]/_USDashboardTable243[[#Totals],[Market Value (in USD)]],0) -> 0 | L174: Diversified | M174: =COUNTIFS(_TrackerTable35[Country],L$169,_TrackerTable35[Sector],_USDashboardTable5254[[#This Row],[Sector]]) -> 1 | N174: =SUMIFS(_TrackerTable35[Market Value (in USD)],_TrackerTable35[Country],L$169,_TrackerTable35[Sector],_USDashboardTable5254[[#This Row],[Sector]]) -> 5955.18 | O174: =IF(_USDashboardTable5254[[#Totals],[Market Value (in USD)]]>0,_USDashboardTable5254[[#This Row],[Market Value (in USD)]]/_USDashboardTable5254[[#Totals],[Market Value (in USD)]],0) -> 0.36982842 | Q174: Diversified | R174: =COUNTIFS(_TrackerTable35[Country],Q$169,_TrackerTable35[Sector],_USDashboardTable57276[[#This Row],[Sector]]) -> 0 | S174: =SUMIFS(_TrackerTable35[Market Value (in USD)],_TrackerTable35[Country],Q$169,_TrackerTable35[Sector],_USDashboardTable57276[[#This Row],[Sector]]) -> 0 | T174: =IF(_USDashboardTable57276[[#Totals],[Market Value (in USD)]]>0,_USDashboardTable57276[[#This Row],[Market Value (in USD)]]/_USDashboardTable57276[[#Totals],[Market Value (in USD)]],0) -> 0 | V174: Diversified | W174: =COUNTIFS(_TrackerTable35[Country],V$169,_TrackerTable35[Sector],_USDashboardTable5714337[[#This Row],[Sector]]) -> 0 | X174: =SUMIFS(_TrackerTable35[Market Value (in USD)],_TrackerTable35[Country],V$169,_TrackerTable35[Sector],_USDashboardTable5714337[[#This Row],[Sector]]) -> 0 | Y174: =IF(_USDashboardTable5714337[[#Totals],[Market Value (in USD)]]>0,_USDashboardTable5714337[[#This Row],[Market Value (in USD)]]/_USDashboardTable5714337[[#Totals],[Market Value (in USD)]],0) -> 0
B175: Energy | C175: =COUNTIFS(_TrackerTable35[Sector],_USDashboardTable56265[[#This Row],[Sector]]) -> 0 | D175: =SUMIFS(_TrackerTable35[Market Value (in USD)],_TrackerTable35[Sector],_USDashboardTable56265[[#This Row],[Sector]]) -> 0 | E175: =IF(_USDashboardTable56265[[#Totals],[Market Value (in USD)]]>0,_USDashboardTable56265[[#This Row],[Market Value (in USD)]]/_USDashboardTable56265[[#Totals],[Market Value (in USD)]],0) -> 0 | G175: Energy | H175: =COUNTIFS(_TrackerTable35[Country],G$169,_TrackerTable35[Sector],_USDashboardTable243[[#This Row],[Sector]]) -> 0 | I175: =SUMIFS(_TrackerTable35[Market Value (in USD)],_TrackerTable35[Country],G$169,_TrackerTable35[Sector],_USDashboardTable243[[#This Row],[Sector]]) -> 0 | J175: =IF(_USDashboardTable243[[#Totals],[Market Value (in USD)]]>0,_USDashboardTable243[[#This Row],[Market Value (in USD)]]/_USDashboardTable243[[#Totals],[Market Value (in USD)]],0) -> 0 | L175: Energy | M175: =COUNTIFS(_TrackerTable35[Country],L$169,_TrackerTable35[Sector],_USDashboardTable5254[[#This Row],[Sector]]) -> 0 | N175: =SUMIFS(_TrackerTable35[Market Value (in USD)],_TrackerTable35[Country],L$169,_TrackerTable35[Sector],_USDashboardTable5254[[#This Row],[Sector]]) -> 0 | O175: =IF(_USDashboardTable5254[[#Totals],[Market Value (in USD)]]>0,_USDashboardTable5254[[#This Row],[Market Value (in USD)]]/_USDashboardTable5254[[#Totals],[Market Value (in USD)]],0) -> 0 | Q175: Energy | R175: =COUNTIFS(_TrackerTable35[Country],Q$169,_TrackerTable35[Sector],_USDashboardTable57276[[#This Row],[Sector]]) -> 0 | S175: =SUMIFS(_TrackerTable35[Market Value (in USD)],_TrackerTable35[Country],Q$169,_TrackerTable35[Sector],_USDashboardTable57276[[#This Row],[Sector]]) -> 0 | T175: =IF(_USDashboardTable57276[[#Totals],[Market Value (in USD)]]>0,_USDashboardTable57276[[#This Row],[Market Value (in USD)]]/_USDashboardTable57276[[#Totals],[Market Value (in USD)]],0) -> 0 | V175: Energy | W175: =COUNTIFS(_TrackerTable35[Country],V$169,_TrackerTable35[Sector],_USDashboardTable5714337[[#This Row],[Sector]]) -> 0 | X175: =SUMIFS(_TrackerTable35[Market Value (in USD)],_TrackerTable35[Country],V$169,_TrackerTable35[Sector],_USDashboardTable5714337[[#This Row],[Sector]]) -> 0 | Y175: =IF(_USDashboardTable5714337[[#Totals],[Market Value (in USD)]]>0,_USDashboardTable5714337[[#This Row],[Market Value (in USD)]]/_USDashboardTable5714337[[#Totals],[Market Value (in USD)]],0) -> 0
B176: Financials | C176: =COUNTIFS(_TrackerTable35[Sector],_USDashboardTable56265[[#This Row],[Sector]]) -> 1 | D176: =SUMIFS(_TrackerTable35[Market Value (in USD)],_TrackerTable35[Sector],_USDashboardTable56265[[#This Row],[Sector]]) -> 6785.4 | E176: =IF(_USDashboardTable56265[[#Totals],[Market Value (in USD)]]>0,_USDashboardTable56265[[#This Row],[Market Value (in USD)]]/_USDashboardTable56265[[#Totals],[Market Value (in USD)]],0) -> 0.12773437 | G176: Financials | H176: =COUNTIFS(_TrackerTable35[Country],G$169,_TrackerTable35[Sector],_USDashboardTable243[[#This Row],[Sector]]) -> 1 | I176: =SUMIFS(_TrackerTable35[Market Value (in USD)],_TrackerTable35[Country],G$169,_TrackerTable35[Sector],_USDashboardTable243[[#This Row],[Sector]]) -> 6785.4 | J176: =IF(_USDashboardTable243[[#Totals],[Market Value (in USD)]]>0,_USDashboardTable243[[#This Row],[Market Value (in USD)]]/_USDashboardTable243[[#Totals],[Market Value (in USD)]],0) -> 0.19915775 | L176: Financials | M176: =COUNTIFS(_TrackerTable35[Country],L$169,_TrackerTable35[Sector],_USDashboardTable5254[[#This Row],[Sector]]) -> 0 | N176: =SUMIFS(_TrackerTable35[Market Value (in USD)],_TrackerTable35[Country],L$169,_TrackerTable35[Sector],_USDashboardTable5254[[#This Row],[Sector]]) -> 0 | O176: =IF(_USDashboardTable5254[[#Totals],[Market Value (in USD)]]>0,_USDashboardTable5254[[#This Row],[Market Value (in USD)]]/_USDashboardTable5254[[#Totals],[Market Value (in USD)]],0) -> 0 | Q176: Financials | R176: =COUNTIFS(_TrackerTable35[Country],Q$169,_TrackerTable35[Sector],_USDashboardTable57276[[#This Row],[Sector]]) -> 0 | S176: =SUMIFS(_TrackerTable35[Market Value (in USD)],_TrackerTable35[Country],Q$169,_TrackerTable35[Sector],_USDashboardTable57276[[#This Row],[Sector]]) -> 0 | T176: =IF(_USDashboardTable57276[[#Totals],[Market Value (in USD)]]>0,_USDashboardTable57276[[#This Row],[Market Value (in USD)]]/_USDashboardTable57276[[#Totals],[Market Value (in USD)]],0) -> 0 | V176: Financials | W176: =COUNTIFS(_TrackerTable35[Country],V$169,_TrackerTable35[Sector],_USDashboardTable5714337[[#This Row],[Sector]]) -> 0 | X176: =SUMIFS(_TrackerTable35[Market Value (in USD)],_TrackerTable35[Country],V$169,_TrackerTable35[Sector],_USDashboardTable5714337[[#This Row],[Sector]]) -> 0 | Y176: =IF(_USDashboardTable5714337[[#Totals],[Market Value (in USD)]]>0,_USDashboardTable5714337[[#This Row],[Market Value (in USD)]]/_USDashboardTable5714337[[#Totals],[Market Value (in USD)]],0) -> 0
B177: Health Care | C177: =COUNTIFS(_TrackerTable35[Sector],_USDashboardTable56265[[#This Row],[Sector]]) -> 1 | D177: =SUMIFS(_TrackerTable35[Market Value (in USD)],_TrackerTable35[Sector],_USDashboardTable56265[[#This Row],[Sector]]) -> 5992.5 | E177: =IF(_USDashboardTable56265[[#Totals],[Market Value (in USD)]]>0,_USDashboardTable56265[[#This Row],[Market Value (in USD)]]/_USDashboardTable56265[[#Totals],[Market Value (in USD)]],0) -> 0.11280812 | G177: Health Care | H177: =COUNTIFS(_TrackerTable35[Country],G$169,_TrackerTable35[Sector],_USDashboardTable243[[#This Row],[Sector]]) -> 1 | I177: =SUMIFS(_TrackerTable35[Market Value (in USD)],_TrackerTable35[Country],G$169,_TrackerTable35[Sector],_USDashboardTable243[[#This Row],[Sector]]) -> 5992.5 | J177: =IF(_USDashboardTable243[[#Totals],[Market Value (in USD)]]>0,_USDashboardTable243[[#This Row],[Market Value (in USD)]]/_USDashboardTable243[[#Totals],[Market Value (in USD)]],0) -> 0.1758854 | L177: Health Care | M177: =COUNTIFS(_TrackerTable35[Country],L$169,_TrackerTable35[Sector],_USDashboardTable5254[[#This Row],[Sector]]) -> 0 | N177: =SUMIFS(_TrackerTable35[Market Value (in USD)],_TrackerTable35[Country],L$169,_TrackerTable35[Sector],_USDashboardTable5254[[#This Row],[Sector]]) -> 0 | O177: =IF(_USDashboardTable5254[[#Totals],[Market Value (in USD)]]>0,_USDashboardTable5254[[#This Row],[Market Value (in USD)]]/_USDashboardTable5254[[#Totals],[Market Value (in USD)]],0) -> 0 | Q177: Health Care | R177: =COUNTIFS(_TrackerTable35[Country],Q$169,_TrackerTable35[Sector],_USDashboardTable57276[[#This Row],[Sector]]) -> 0 | S177: =SUMIFS(_TrackerTable35[Market Value (in USD)],_TrackerTable35[Country],Q$169,_TrackerTable35[Sector],_USDashboardTable57276[[#This Row],[Sector]]) -> 0 | T177: =IF(_USDashboardTable57276[[#Totals],[Market Value (in USD)]]>0,_USDashboardTable57276[[#This Row],[Market Value (in USD)]]/_USDashboardTable57276[[#Totals],[Market Value (in USD)]],0) -> 0 | V177: Health Care | W177: =COUNTIFS(_TrackerTable35[Country],V$169,_TrackerTable35[Sector],_USDashboardTable5714337[[#This Row],[Sector]]) -> 0 | X177: =SUMIFS(_TrackerTable35[Market Value (in USD)],_TrackerTable35[Country],V$169,_TrackerTable35[Sector],_USDashboardTable5714337[[#This Row],[Sector]]) -> 0 | Y177: =IF(_USDashboardTable5714337[[#Totals],[Market Value (in USD)]]>0,_USDashboardTable5714337[[#This Row],[Market Value (in USD)]]/_USDashboardTable5714337[[#Totals],[Market Value (in USD)]],0) -> 0
B178: Industrials | C178: =COUNTIFS(_TrackerTable35[Sector],_USDashboardTable56265[[#This Row],[Sector]]) -> 0 | D178: =SUMIFS(_TrackerTable35[Market Value (in USD)],_TrackerTable35[Sector],_USDashboardTable56265[[#This Row],[Sector]]) -> 0 | E178: =IF(_USDashboardTable56265[[#Totals],[Market Value (in USD)]]>0,_USDashboardTable56265[[#This Row],[Market Value (in USD)]]/_USDashboardTable56265[[#Totals],[Market Value (in USD)]],0) -> 0 | G178: Industrials | H178: =COUNTIFS(_TrackerTable35[Country],G$169,_TrackerTable35[Sector],_USDashboardTable243[[#This Row],[Sector]]) -> 0 | I178: =SUMIFS(_TrackerTable35[Market Value (in USD)],_TrackerTable35[Country],G$169,_TrackerTable35[Sector],_USDashboardTable243[[#This Row],[Sector]]) -> 0 | J178: =IF(_USDashboardTable243[[#Totals],[Market Value (in USD)]]>0,_USDashboardTable243[[#This Row],[Market Value (in USD)]]/_USDashboardTable243[[#Totals],[Market Value (in USD)]],0) -> 0 | L178: Industrials | M178: =COUNTIFS(_TrackerTable35[Country],L$169,_TrackerTable35[Sector],_USDashboardTable5254[[#This Row],[Sector]]) -> 0 | N178: =SUMIFS(_TrackerTable35[Market Value (in USD)],_TrackerTable35[Country],L$169,_TrackerTable35[Sector],_USDashboardTable5254[[#This Row],[Sector]]) -> 0 | O178: =IF(_USDashboardTable5254[[#Totals],[Market Value (in USD)]]>0,_USDashboardTable5254[[#This Row],[Market Value (in USD)]]/_USDashboardTable5254[[#Totals],[Market Value (in USD)]],0) -> 0 | Q178: Industrials | R178: =COUNTIFS(_TrackerTable35[Country],Q$169,_TrackerTable35[Sector],_USDashboardTable57276[[#This Row],[Sector]]) -> 0 | S178: =SUMIFS(_TrackerTable35[Market Value (in USD)],_TrackerTable35[Country],Q$169,_TrackerTable35[Sector],_USDashboardTable57276[[#This Row],[Sector]]) -> 0 | T178: =IF(_USDashboardTable57276[[#Totals],[Market Value (in USD)]]>0,_USDashboardTable57276[[#This Row],[Market Value (in USD)]]/_USDashboardTable57276[[#Totals],[Market Value (in USD)]],0) -> 0 | V178: Industrials | W178: =COUNTIFS(_TrackerTable35[Country],V$169,_TrackerTable35[Sector],_USDashboardTable5714337[[#This Row],[Sector]]) -> 0 | X178: =SUMIFS(_TrackerTable35[Market Value (in USD)],_TrackerTable35[Country],V$169,_TrackerTable35[Sector],_USDashboardTable5714337[[#This Row],[Sector]]) -> 0 | Y178: =IF(_USDashboardTable5714337[[#Totals],[Market Value (in USD)]]>0,_USDashboardTable5714337[[#This Row],[Market Value (in USD)]]/_USDashboardTable5714337[[#Totals],[Market Value (in USD)]],0) -> 0
B179: Materials | C179: =COUNTIFS(_TrackerTable35[Sector],_USDashboardTable56265[[#This Row],[Sector]]) -> 0 | D179: =SUMIFS(_TrackerTable35[Market Value (in USD)],_TrackerTable35[Sector],_USDashboardTable56265[[#This Row],[Sector]]) -> 0 | E179: =IF(_USDashboardTable56265[[#Totals],[Market Value (in USD)]]>0,_USDashboardTable56265[[#This Row],[Market Value (in USD)]]/_USDashboardTable56265[[#Totals],[Market Value (in USD)]],0) -> 0 | G179: Materials | H179: =COUNTIFS(_TrackerTable35[Country],G$169,_TrackerTable35[Sector],_USDashboardTable243[[#This Row],[Sector]]) -> 0 | I179: =SUMIFS(_TrackerTable35[Market Value (in USD)],_TrackerTable35[Country],G$169,_TrackerTable35[Sector],_USDashboardTable243[[#This Row],[Sector]]) -> 0 | J179: =IF(_USDashboardTable243[[#Totals],[Market Value (in USD)]]>0,_USDashboardTable243[[#This Row],[Market Value (in USD)]]/_USDashboardTable243[[#Totals],[Market Value (in USD)]],0) -> 0 | L179: Materials | M179: =COUNTIFS(_TrackerTable35[Country],L$169,_TrackerTable35[Sector],_USDashboardTable5254[[#This Row],[Sector]]) -> 0 | N179: =SUMIFS(_TrackerTable35[Market Value (in USD)],_TrackerTable35[Country],L$169,_TrackerTable35[Sector],_USDashboardTable5254[[#This Row],[Sector]]) -> 0 | O179: =IF(_USDashboardTable5254[[#Totals],[Market Value (in USD)]]>0,_USDashboardTable5254[[#This Row],[Market Value (in USD)]]/_USDashboardTable5254[[#Totals],[Market Value (in USD)]],0) -> 0 | Q179: Materials | R179: =COUNTIFS(_TrackerTable35[Country],Q$169,_TrackerTable35[Sector],_USDashboardTable57276[[#This Row],[Sector]]) -> 0 | S179: =SUMIFS(_TrackerTable35[Market Value (in USD)],_TrackerTable35[Country],Q$169,_TrackerTable35[Sector],_USDashboardTable57276[[#This Row],[Sector]]) -> 0 | T179: =IF(_USDashboardTable57276[[#Totals],[Market Value (in USD)]]>0,_USDashboardTable57276[[#This Row],[Market Value (in USD)]]/_USDashboardTable57276[[#Totals],[Market Value (in USD)]],0) -> 0 | V179: Materials | W179: =COUNTIFS(_TrackerTable35[Country],V$169,_TrackerTable35[Sector],_USDashboardTable5714337[[#This Row],[Sector]]) -> 0 | X179: =SUMIFS(_TrackerTable35[Market Value (in USD)],_TrackerTable35[Country],V$169,_TrackerTable35[Sector],_USDashboardTable5714337[[#This Row],[Sector]]) -> 0 | Y179: =IF(_USDashboardTable5714337[[#Totals],[Market Value (in USD)]]>0,_USDashboardTable5714337[[#This Row],[Market Value (in USD)]]/_USDashboardTable5714337[[#Totals],[Market Value (in USD)]],0) -> 0
B180: Real Estate | C180: =COUNTIFS(_TrackerTable35[Sector],_USDashboardTable56265[[#This Row],[Sector]]) -> 1 | D180: =SUMIFS(_TrackerTable35[Market Value (in USD)],_TrackerTable35[Sector],_USDashboardTable56265[[#This Row],[Sector]]) -> 2948.1481 | E180: =IF(_USDashboardTable56265[[#Totals],[Market Value (in USD)]]>0,_USDashboardTable56265[[#This Row],[Market Value (in USD)]]/_USDashboardTable56265[[#Totals],[Market Value (in USD)]],0) -> 0.055498548 | G180: Real Estate | H180: =COUNTIFS(_TrackerTable35[Country],G$169,_TrackerTable35[Sector],_USDashboardTable243[[#This Row],[Sector]]) -> 0 | I180: =SUMIFS(_TrackerTable35[Market Value (in USD)],_TrackerTable35[Country],G$169,_TrackerTable35[Sector],_USDashboardTable243[[#This Row],[Sector]]) -> 0 | J180: =IF(_USDashboardTable243[[#Totals],[Market Value (in USD)]]>0,_USDashboardTable243[[#This Row],[Market Value (in USD)]]/_USDashboardTable243[[#Totals],[Market Value (in USD)]],0) -> 0 | L180: Real Estate | M180: =COUNTIFS(_TrackerTable35[Country],L$169,_TrackerTable35[Sector],_USDashboardTable5254[[#This Row],[Sector]]) -> 0 | N180: =SUMIFS(_TrackerTable35[Market Value (in USD)],_TrackerTable35[Country],L$169,_TrackerTable35[Sector],_USDashboardTable5254[[#This Row],[Sector]]) -> 0 | O180: =IF(_USDashboardTable5254[[#Totals],[Market Value (in USD)]]>0,_USDashboardTable5254[[#This Row],[Market Value (in USD)]]/_USDashboardTable5254[[#Totals],[Market Value (in USD)]],0) -> 0 | Q180: Real Estate | R180: =COUNTIFS(_TrackerTable35[Country],Q$169,_TrackerTable35[Sector],_USDashboardTable57276[[#This Row],[Sector]]) -> 1 | S180: =SUMIFS(_TrackerTable35[Market Value (in USD)],_TrackerTable35[Country],Q$169,_TrackerTable35[Sector],_USDashboardTable57276[[#This Row],[Sector]]) -> 2948.1481 | T180: =IF(_USDashboardTable57276[[#Totals],[Market Value (in USD)]]>0,_USDashboardTable57276[[#This Row],[Market Value (in USD)]]/_USDashboardTable57276[[#Totals],[Market Value (in USD)]],0) -> 1 | V180: Real Estate | W180: =COUNTIFS(_TrackerTable35[Country],V$169,_TrackerTable35[Sector],_USDashboardTable5714337[[#This Row],[Sector]]) -> 0 | X180: =SUMIFS(_TrackerTable35[Market Value (in USD)],_TrackerTable35[Country],V$169,_TrackerTable35[Sector],_USDashboardTable5714337[[#This Row],[Sector]]) -> 0 | Y180: =IF(_USDashboardTable5714337[[#Totals],[Market Value (in USD)]]>0,_USDashboardTable5714337[[#This Row],[Market Value (in USD)]]/_USDashboardTable5714337[[#Totals],[Market Value (in USD)]],0) -> 0
B181: Technology | C181: =COUNTIFS(_TrackerTable35[Sector],_USDashboardTable56265[[#This Row],[Sector]]) -> 1 | D181: =SUMIFS(_TrackerTable35[Market Value (in USD)],_TrackerTable35[Sector],_USDashboardTable56265[[#This Row],[Sector]]) -> 3194.22 | E181: =IF(_USDashboardTable56265[[#Totals],[Market Value (in USD)]]>0,_USDashboardTable56265[[#This Row],[Market Value (in USD)]]/_USDashboardTable56265[[#Totals],[Market Value (in USD)]],0) -> 0.060130822 | G181: Technology | H181: =COUNTIFS(_TrackerTable35[Country],G$169,_TrackerTable35[Sector],_USDashboardTable243[[#This Row],[Sector]]) -> 1 | I181: =SUMIFS(_TrackerTable35[Market Value (in USD)],_TrackerTable35[Country],G$169,_TrackerTable35[Sector],_USDashboardTable243[[#This Row],[Sector]]) -> 3194.22 | J181: =IF(_USDashboardTable243[[#Totals],[Market Value (in USD)]]>0,_USDashboardTable243[[#This Row],[Market Value (in USD)]]/_USDashboardTable243[[#Totals],[Market Value (in USD)]],0) -> 0.093753302 | L181: Technology | M181: =COUNTIFS(_TrackerTable35[Country],L$169,_TrackerTable35[Sector],_USDashboardTable5254[[#This Row],[Sector]]) -> 0 | N181: =SUMIFS(_TrackerTable35[Market Value (in USD)],_TrackerTable35[Country],L$169,_TrackerTable35[Sector],_USDashboardTable5254[[#This Row],[Sector]]) -> 0 | O181: =IF(_USDashboardTable5254[[#Totals],[Market Value (in USD)]]>0,_USDashboardTable5254[[#This Row],[Market Value (in USD)]]/_USDashboardTable5254[[#Totals],[Market Value (in USD)]],0) -> 0 | Q181: Technology | R181: =COUNTIFS(_TrackerTable35[Country],Q$169,_TrackerTable35[Sector],_USDashboardTable57276[[#This Row],[Sector]]) -> 0 | S181: =SUMIFS(_TrackerTable35[Market Value (in USD)],_TrackerTable35[Country],Q$169,_TrackerTable35[Sector],_USDashboardTable57276[[#This Row],[Sector]]) -> 0 | T181: =IF(_USDashboardTable57276[[#Totals],[Market Value (in USD)]]>0,_USDashboardTable57276[[#This Row],[Market Value (in USD)]]/_USDashboardTable57276[[#Totals],[Market Value (in USD)]],0) -> 0 | V181: Technology | W181: =COUNTIFS(_TrackerTable35[Country],V$169,_TrackerTable35[Sector],_USDashboardTable5714337[[#This Row],[Sector]]) -> 0 | X181: =SUMIFS(_TrackerTable35[Market Value (in USD)],_TrackerTable35[Country],V$169,_TrackerTable35[Sector],_USDashboardTable5714337[[#This Row],[Sector]]) -> 0 | Y181: =IF(_USDashboardTable5714337[[#Totals],[Market Value (in USD)]]>0,_USDashboardTable5714337[[#This Row],[Market Value (in USD)]]/_USDashboardTable5714337[[#Totals],[Market Value (in USD)]],0) -> 0
B182: Utilities | C182: =COUNTIFS(_TrackerTable35[Sector],_USDashboardTable56265[[#This Row],[Sector]]) -> 0 | D182: =SUMIFS(_TrackerTable35[Market Value (in USD)],_TrackerTable35[Sector],_USDashboardTable56265[[#This Row],[Sector]]) -> 0 | E182: =IF(_USDashboardTable56265[[#Totals],[Market Value (in USD)]]>0,_USDashboardTable56265[[#This Row],[Market Value (in USD)]]/_USDashboardTable56265[[#Totals],[Market Value (in USD)]],0) -> 0 | G182: Utilities | H182: =COUNTIFS(_TrackerTable35[Country],G$169,_TrackerTable35[Sector],_USDashboardTable243[[#This Row],[Sector]]) -> 0 | I182: =SUMIFS(_TrackerTable35[Market Value (in USD)],_TrackerTable35[Country],G$169,_TrackerTable35[Sector],_USDashboardTable243[[#This Row],[Sector]]) -> 0 | J182: =IF(_USDashboardTable243[[#Totals],[Market Value (in USD)]]>0,_USDashboardTable243[[#This Row],[Market Value (in USD)]]/_USDashboardTable243[[#Totals],[Market Value (in USD)]],0) -> 0 | L182: Utilities | M182: =COUNTIFS(_TrackerTable35[Country],L$169,_TrackerTable35[Sector],_USDashboardTable5254[[#This Row],[Sector]]) -> 0 | N182: =SUMIFS(_TrackerTable35[Market Value (in USD)],_TrackerTable35[Country],L$169,_TrackerTable35[Sector],_USDashboardTable5254[[#This Row],[Sector]]) -> 0 | O182: =IF(_USDashboardTable5254[[#Totals],[Market Value (in USD)]]>0,_USDashboardTable5254[[#This Row],[Market Value (in USD)]]/_USDashboardTable5254[[#Totals],[Market Value (in USD)]],0) -> 0 | Q182: Utilities | R182: =COUNTIFS(_TrackerTable35[Country],Q$169,_TrackerTable35[Sector],_USDashboardTable57276[[#This Row],[Sector]]) -> 0 | S182: =SUMIFS(_TrackerTable35[Market Value (in USD)],_TrackerTable35[Country],Q$169,_TrackerTable35[Sector],_USDashboardTable57276[[#This Row],[Sector]]) -> 0 | T182: =IF(_USDashboardTable57276[[#Totals],[Market Value (in USD)]]>0,_USDashboardTable57276[[#This Row],[Market Value (in USD)]]/_USDashboardTable57276[[#Totals],[Market Value (in USD)]],0) -> 0 | V182: Utilities | W182: =COUNTIFS(_TrackerTable35[Country],V$169,_TrackerTable35[Sector],_USDashboardTable5714337[[#This Row],[Sector]]) -> 0 | X182: =SUMIFS(_TrackerTable35[Market Value (in USD)],_TrackerTable35[Country],V$169,_TrackerTable35[Sector],_USDashboardTable5714337[[#This Row],[Sector]]) -> 0 | Y182: =IF(_USDashboardTable5714337[[#Totals],[Market Value (in USD)]]>0,_USDashboardTable5714337[[#This Row],[Market Value (in USD)]]/_USDashboardTable5714337[[#Totals],[Market Value (in USD)]],0) -> 0
B183: TOTAL | C183: =SUBTOTAL(109,_USDashboardTable56265[Count]) -> 9 | D183: =SUBTOTAL(109,_USDashboardTable56265[Market Value (in USD)]) -> 53121.177 | E183: =SUBTOTAL(109,_USDashboardTable56265[Percentage by Market Value]) -> 1 | G183: TOTAL | H183: =SUBTOTAL(109,_USDashboardTable243[Count]) -> 5 | I183: =SUBTOTAL(109,_USDashboardTable243[Market Value (in USD)]) -> 34070.48 | J183: =SUBTOTAL(109,_USDashboardTable243[Percentage by Market Value]) -> 1 | L183: TOTAL | M183: =SUBTOTAL(109,_USDashboardTable5254[Count]) -> 3 | N183: =SUBTOTAL(109,_USDashboardTable5254[Market Value (in USD)]) -> 16102.548 | O183: =SUBTOTAL(109,_USDashboardTable5254[Percentage by Market Value]) -> 1 | Q183: TOTAL | R183: =SUBTOTAL(109,_USDashboardTable57276[Count]) -> 1 | S183: =SUBTOTAL(109,_USDashboardTable57276[Market Value (in USD)]) -> 2948.1481 | T183: =SUBTOTAL(109,_USDashboardTable57276[Percentage by Market Value]) -> 1 | V183: TOTAL | W183: =SUBTOTAL(109,_USDashboardTable5714337[Count]) -> 0 | X183: =SUBTOTAL(109,_USDashboardTable5714337[Market Value (in USD)]) -> 0 | Y183: =SUBTOTAL(109,_USDashboardTable5714337[Percentage by Market Value]) -> 0
B235: Geographical Breakdown
B236: Country | C236: Count | D236: Market Value (in USD) | E236: Percentage by Market Value
B237: US | C237: =COUNTIFS(_TrackerTable35[Country],_USDashboardTable56828[[#This Row],[Country]]) -> 5 | D237: =SUMIFS(_TrackerTable35[Market Value (in USD)],_TrackerTable35[Country],_USDashboardTable56828[[#This Row],[Country]]) -> 34070.48 | E237: =IF(_USDashboardTable56828[[#Totals],[Market Value (in USD)]]>0,_USDashboardTable56828[[#This Row],[Market Value (in USD)]]/_USDashboardTable56828[[#Totals],[Market Value (in USD)]],0) -> 0.64137284
B238: China/HK | C238: =COUNTIFS(_TrackerTable35[Country],_USDashboardTable56828[[#This Row],[Country]]) -> 3 | D238: =SUMIFS(_TrackerTable35[Market Value (in USD)],_TrackerTable35[Country],_USDashboardTable56828[[#This Row],[Country]]) -> 16102.548 | E238: =IF(_USDashboardTable56828[[#Totals],[Market Value (in USD)]]>0,_USDashboardTable56828[[#This Row],[Market Value (in USD)]]/_USDashboardTable56828[[#Totals],[Market Value (in USD)]],0) -> 0.30312861
B239: Singapore | C239: =COUNTIFS(_TrackerTable35[Country],_USDashboardTable56828[[#This Row],[Country]]) -> 1 | D239: =SUMIFS(_TrackerTable35[Market Value (in USD)],_TrackerTable35[Country],_USDashboardTable56828[[#This Row],[Country]]) -> 2948.1481 | E239: =IF(_USDashboardTable56828[[#Totals],[Market Value (in USD)]]>0,_USDashboardTable56828[[#This Row],[Market Value (in USD)]]/_USDashboardTable56828[[#Totals],[Market Value (in USD)]],0) -> 0.055498548
B240: Europe | C240: =COUNTIFS(_TrackerTable35[Country],_USDashboardTable56828[[#This Row],[Country]]) -> 0 | D240: =SUMIFS(_TrackerTable35[Market Value (in USD)],_TrackerTable35[Country],_USDashboardTable56828[[#This Row],[Country]]) -> 0 | E240: =IF(_USDashboardTable56828[[#Totals],[Market Value (in USD)]]>0,_USDashboardTable56828[[#This Row],[Market Value (in USD)]]/_USDashboardTable56828[[#Totals],[Market Value (in USD)]],0) -> 0
B241: Canada | C241: =COUNTIFS(_TrackerTable35[Country],_USDashboardTable56828[[#This Row],[Country]]) -> 0 | D241: =SUMIFS(_TrackerTable35[Market Value (in USD)],_TrackerTable35[Country],_USDashboardTable56828[[#This Row],[Country]]) -> 0 | E241: =IF(_USDashboardTable56828[[#Totals],[Market Value (in USD)]]>0,_USDashboardTable56828[[#This Row],[Market Value (in USD)]]/_USDashboardTable56828[[#Totals],[Market Value (in USD)]],0) -> 0
B242: India | C242: =COUNTIFS(_TrackerTable35[Country],_USDashboardTable56828[[#This Row],[Country]]) -> 0 | D242: =SUMIFS(_TrackerTable35[Market Value (in USD)],_TrackerTable35[Country],_USDashboardTable56828[[#This Row],[Country]]) -> 0 | E242: =IF(_USDashboardTable56828[[#Totals],[Market Value (in USD)]]>0,_USDashboardTable56828[[#This Row],[Market Value (in USD)]]/_USDashboardTable56828[[#Totals],[Market Value (in USD)]],0) -> 0
B243: TOTAL | C243: =SUBTOTAL(109,_USDashboardTable56828[Count]) -> 9 | D243: =SUBTOTAL(109,_USDashboardTable56828[Market Value (in USD)]) -> 53121.177 | E243: =SUBTOTAL(109,_USDashboardTable56828[Percentage by Market Value]) -> 1
B301: ="© "&YEAR(TODAY())&" Piranha Ltd. All rights reserved." -> © 2026 Piranha Ltd. All rights reserved.

Sheet VMI Portfolio Manager
C2: PORTFOLIO MANAGER
C4: Cash USD | D4: 2410.23
C5: Equity Position | D5: =_TrackerTable35[[#Totals],[Market Value (in USD)]] -> 53121.177
C6: Net Liquidation | D6: =SUM(D4:D5) -> 55531.407
R7: Cost in USD | T7: Allocation in USD | W7: Discount/Premium | Y7: Market Value | AC7: Dividend
C8: Stock Information | I8: Currency | K8: Allocation | L8: Cost | N8: Valuation | P8: Dividend | Q8: Price | R8: NOTE: DO NOT MODIFY BELOW, THIS IS AUTO-CALCULATED
B9: # | C9: Ticker | D9: Name | E9: Sector | F9: Category | G9: Type | H9: Country | I9: Listed Currency | J9: Exchange Rate (1 USD to xxx Listed Currency) | K9: Planned Allocation (in Listed Currency) | L9: Quantity | M9: Avg Cost per Share (in Listed Currency) | N9: Valuation Date | O9: Intrinsic Value (in Listed Currency) | P9: Total Dividend Received (in Listed Currency) | Q9: Current Price (in Listed Currency) | R9: Avg Cost per Share (in USD) | S9: Total Cost (in USD) | T9: Planned Allocation (in USD) | U9: Planned Allocation (in %) | V9: % Allocated | W9: Intrinsic Value (in USD) | X9: Discount / Premium | Y9: Current Price (in USD) | Z9: Market Value (in USD) | AA9: % of Portfolio (by Market Value) | AB9: % Change (excludes Dividend) | AC9: Total Dividend Received (in USD) | AD9: Total Dividend Received (% of Total Cost) | AE9: % Change (includes Dividend)
B10: 1 | C10: C38U | D10: CapitaLand Integrated Commercial Trust | E10: Real Estate | F10: Cash Cow | G10: Cyclical | H10: Singapore | I10: SGD | J10: 1.35 | K10: 8000 | L10: 2000 | M10: 2.039 | N10: 44562 | O10: 2.3 | P10: 483.43 | Q10: 1.99 | R10: =IFERROR(_TrackerTable35[[#This Row],[Avg Cost per Share (in Listed Currency)]]/_TrackerTable35[[#This Row],[Exchange Rate (1 USD to xxx Listed Currency)]],"NA") -> 1.5103704 | S10: =IFERROR(_TrackerTable35[[#This Row],[Quantity]]*_TrackerTable35[[#This Row],[Avg Cost per Share (in USD)]],"NA") -> 3020.7407 | T10: =IFERROR(_TrackerTable35[[#This Row],[Planned Allocation (in Listed Currency)]]/_TrackerTable35[[#This Row],[Exchange Rate (1 USD to xxx Listed Currency)]],"NA") -> 5925.9259 | U10: =IFERROR(_TrackerTable35[[#This Row],[Planned Allocation (in USD)]]/_TrackerTable35[[#Totals],[Planned Allocation (in USD)]],"NA") -> 0.1289962 | V10: =IFERROR(_TrackerTable35[[#This Row],[Total Cost (in USD)]]/_TrackerTable35[[#This Row],[Planned Allocation (in USD)]],"NA") -> 0.50975 | W10: =IF(AND(_TrackerTable35[[#This Row],[Exchange Rate (1 USD to xxx Listed Currency)]]>0,_TrackerTable35[[#This Row],[Intrinsic Value (in Listed Currency)]]>0,_TrackerTable35[[#This Row],[Intrinsic Value (in Listed Currency)]]<>"NA"),_TrackerTable35[[#This Row],[Intrinsic Value (in Listed Currency)]]/_TrackerTable35[[#This Row],[Exchange Rate (1 USD to xxx Listed Currency)]],"NA") -> 1.7037037 | X10: =IFERROR(_TrackerTable35[[#This Row],[Current Price (in USD)]]/_TrackerTable35[[#This Row],[Intrinsic Value (in USD)]]-1,"NA") -> -0.13478261 | Y10: =IF(_TrackerTable35[[#This Row],[Exchange Rate (1 USD to xxx Listed Currency)]]>0,_TrackerTable35[[#This Row],[Current Price (in Listed Currency)]]/_TrackerTable35[[#This Row],[Exchange Rate (1 USD to xxx Listed Currency)]],"NA") -> 1.4740741 | Z10: =IFERROR(_TrackerTable35[[#This Row],[Current Price (in USD)]]*_TrackerTable35[[#This Row],[Quantity]],"NA") -> 2948.1481 | AA10: =IFERROR(IF(AND(_TrackerTable35[[#This Row],[Market Value (in USD)]]>0,_TrackerTable35[[#Totals],[Market Value (in USD)]]>0),_TrackerTable35[[#This Row],[Market Value (in USD)]]/_TrackerTable35[[#Totals],[Market Value (in USD)]],"NA"),"NA") -> 0.055498548 | AB10: =IFERROR(_TrackerTable35[[#This Row],[Market Value (in USD)]]/_TrackerTable35[[#This Row],[Total Cost (in USD)]]-1,"NA") -> -0.024031388 | AC10: =IFERROR(_TrackerTable35[[#This Row],[Total Dividend Received (in Listed Currency)]]/_TrackerTable35[[#This Row],[Exchange Rate (1 USD to xxx Listed Currency)]],"NA") -> 358.0963 | AD10: =IFERROR(_TrackerTable35[[#This Row],[Total Dividend Received (in USD)]]/_TrackerTable35[[#This Row],[Total Cost (in USD)]],"NA") -> 0.11854586 | AE10: =IFERROR((_TrackerTable35[[#This Row],[Total Dividend Received (in USD)]]+_TrackerTable35[[#This Row],[Market Value (in USD)]])/_TrackerTable35[[#This Row],[Total Cost (in USD)]]-1,"NA") -> 0.094514468
B11: 2 | C11: CME | D11: CME Group Inc | E11: Financials | F11: Predictable | G11: Moderate Cyclical | H11: US | I11: USD | J11: 1 | K11: 5000 | L11: 30 | M11: 164.69 | N11: 44562 | O11: 190 | P11: 0 | Q11: 226.18 | R11: =IFERROR(_TrackerTable35[[#This Row],[Avg Cost per Share (in Listed Currency)]]/_TrackerTable35[[#This Row],[Exchange Rate (1 USD to xxx Listed Currency)]],"NA") -> 164.69 | S11: =IFERROR(_TrackerTable35[[#This Row],[Quantity]]*_TrackerTable35[[#This Row],[Avg Cost per Share (in USD)]],"NA") -> 4940.7 | T11: =IFERROR(_TrackerTable35[[#This Row],[Planned Allocation (in Listed Currency)]]/_TrackerTable35[[#This Row],[Exchange Rate (1 USD to xxx Listed Currency)]],"NA") -> 5000 | U11: =IFERROR(_TrackerTable35[[#This Row],[Planned Allocation (in USD)]]/_TrackerTable35[[#Totals],[Planned Allocation (in USD)]],"NA") -> 0.10884055 | V11: =IFERROR(_TrackerTable35[[#This Row],[Total Cost (in USD)]]/_TrackerTable35[[#This Row],[Planned Allocation (in USD)]],"NA") -> 0.98814 | W11: =IF(AND(_TrackerTable35[[#This Row],[Exchange Rate (1 USD to xxx Listed Currency)]]>0,_TrackerTable35[[#This Row],[Intrinsic Value (in Listed Currency)]]>0,_TrackerTable35[[#This Row],[Intrinsic Value (in Listed Currency)]]<>"NA"),_TrackerTable35[[#This Row],[Intrinsic Value (in Listed Currency)]]/_TrackerTable35[[#This Row],[Exchange Rate (1 USD to xxx Listed Currency)]],"NA") -> 190 | X11: =IFERROR(_TrackerTable35[[#This Row],[Current Price (in USD)]]/_TrackerTable35[[#This Row],[Intrinsic Value (in USD)]]-1,"NA") -> 0.19042105 | Y11: =IF(_TrackerTable35[[#This Row],[Exchange Rate (1 USD to xxx Listed Currency)]]>0,_TrackerTable35[[#This Row],[Current Price (in Listed Currency)]]/_TrackerTable35[[#This Row],[Exchange Rate (1 USD to xxx Listed Currency)]],"NA") -> 226.18 | Z11: =IFERROR(_TrackerTable35[[#This Row],[Current Price (in USD)]]*_TrackerTable35[[#This Row],[Quantity]],"NA") -> 6785.4 | AA11: =IFERROR(IF(AND(_TrackerTable35[[#This Row],[Market Value (in USD)]]>0,_TrackerTable35[[#Totals],[Market Value (in USD)]]>0),_TrackerTable35[[#This Row],[Market Value (in USD)]]/_TrackerTable35[[#Totals],[Market Value (in USD)]],"NA"),"NA") -> 0.12773437 | AB11: =IFERROR(_TrackerTable35[[#This Row],[Market Value (in USD)]]/_TrackerTable35[[#This Row],[Total Cost (in USD)]]-1,"NA") -> 0.37336815 | AC11: =IFERROR(_TrackerTable35[[#This Row],[Total Dividend Received (in Listed Currency)]]/_TrackerTable35[[#This Row],[Exchange Rate (1 USD to xxx Listed Currency)]],"NA") -> 0 | AD11: =IFERROR(_TrackerTable35[[#This Row],[Total Dividend Received (in USD)]]/_TrackerTable35[[#This Row],[Total Cost (in USD)]],"NA") -> 0 | AE11: =IFERROR((_TrackerTable35[[#This Row],[Total Dividend Received (in USD)]]+_TrackerTable35[[#This Row],[Market Value (in USD)]])/_TrackerTable35[[#This Row],[Total Cost (in USD)]]-1,"NA") -> 0.37336815
B12: 3 | C12: ADBE | D12: Adobe | E12: Technology | F12: Growth | G12: Moderate Cyclical | H12: US | I12: USD | J12: 1 | K12: 5000 | L12: 6 | M12: 506.84 | N12: 44562 | O12: 592 | P12: 0 | Q12: 532.37 | R12: =IFERROR(_TrackerTable35[[#This Row],[Avg Cost per Share (in Listed Currency)]]/_TrackerTable35[[#This Row],[Exchange Rate (1 USD to xxx Listed Currency)]],"NA") -> 506.84 | S12: =IFERROR(_TrackerTable35[[#This Row],[Quantity]]*_TrackerTable35[[#This Row],[Avg Cost per Share (in USD)]],"NA") -> 3041.04 | T12: =IFERROR(_TrackerTable35[[#This Row],[Planned Allocation (in Listed Currency)]]/_TrackerTable35[[#This Row],[Exchange Rate (1 USD to xxx Listed Currency)]],"NA") -> 5000 | U12: =IFERROR(_TrackerTable35[[#This Row],[Planned Allocation (in USD)]]/_TrackerTable35[[#Totals],[Planned Allocation (in USD)]],"NA") -> 0.10884055 | V12: =IFERROR(_TrackerTable35[[#This Row],[Total Cost (in USD)]]/_TrackerTable35[[#This Row],[Planned Allocation (in USD)]],"NA") -> 0.608208 | W12: =IF(AND(_TrackerTable35[[#This Row],[Exchange Rate (1 USD to xxx Listed Currency)]]>0,_TrackerTable35[[#This Row],[Intrinsic Value (in Listed Currency)]]>0,_TrackerTable35[[#This Row],[Intrinsic Value (in Listed Currency)]]<>"NA"),_TrackerTable35[[#This Row],[Intrinsic Value (in Listed Currency)]]/_TrackerTable35[[#This Row],[Exchange Rate (1 USD to xxx Listed Currency)]],"NA") -> 592 | X12: =IFERROR(_TrackerTable35[[#This Row],[Current Price (in USD)]]/_TrackerTable35[[#This Row],[Intrinsic Value (in USD)]]-1,"NA") -> -0.10072635 | Y12: =IF(_TrackerTable35[[#This Row],[Exchange Rate (1 USD to xxx Listed Currency)]]>0,_TrackerTable35[[#This Row],[Current Price (in Listed Currency)]]/_TrackerTable35[[#This Row],[Exchange Rate (1 USD to xxx Listed Currency)]],"NA") -> 532.37 | Z12: =IFERROR(_TrackerTable35[[#This Row],[Current Price (in USD)]]*_TrackerTable35[[#This Row],[Quantity]],"NA") -> 3194.22 | AA12: =IFERROR(IF(AND(_TrackerTable35[[#This Row],[Market Value (in USD)]]>0,_TrackerTable35[[#Totals],[Market Value (in USD)]]>0),_TrackerTable35[[#This Row],[Market Value (in USD)]]/_TrackerTable35[[#Totals],[Market Value (in USD)]],"NA"),"NA") -> 0.060130822 | AB12: =IFERROR(_TrackerTable35[[#This Row],[Market Value (in USD)]]/_TrackerTable35[[#This Row],[Total Cost (in USD)]]-1,"NA") -> 0.050370926 | AC12: =IFERROR(_TrackerTable35[[#This Row],[Total Dividend Received (in Listed Currency)]]/_TrackerTable35[[#This Row],[Exchange Rate (1 USD to xxx Listed Currency)]],"NA") -> 0 | AD12: =IFERROR(_TrackerTable35[[#This Row],[Total Dividend Received (in USD)]]/_TrackerTable35[[#This Row],[Total Cost (in USD)]],"NA") -> 0 | AE12: =IFERROR((_TrackerTable35[[#This Row],[Total Dividend Received (in USD)]]+_TrackerTable35[[#This Row],[Market Value (in USD)]])/_TrackerTable35[[#This Row],[Total Cost (in USD)]]-1,"NA") -> 0.050370926
B13: 4 | C13: 0700 | D13: Tencent Holdings | E13: Communication Services | F13: Growth | G13: Moderate Cyclical | H13: China/HK | I13: HKD | J13: 7.79 | K13: 39000 | L13: 80 | M13: 475.86 | N13: 44562 | O13: 642 | P13: 0 | Q13: 481.2 | R13: =IFERROR(_TrackerTable35[[#This Row],[Avg Cost per Share (in Listed Currency)]]/_TrackerTable35[[#This Row],[Exchange Rate (1 USD to xxx Listed Currency)]],"NA") -> 61.086008 | S13: =IFERROR(_TrackerTable35[[#This Row],[Quantity]]*_TrackerTable35[[#This Row],[Avg Cost per Share (in USD)]],"NA") -> 4886.8806 | T13: =IFERROR(_TrackerTable35[[#This Row],[Planned Allocation (in Listed Currency)]]/_TrackerTable35[[#This Row],[Exchange Rate (1 USD to xxx Listed Currency)]],"NA") -> 5006.4185 | U13: =IFERROR(_TrackerTable35[[#This Row],[Planned Allocation (in USD)]]/_TrackerTable35[[#Totals],[Planned Allocation (in USD)]],"NA") -> 0.10898026 | V13: =IFERROR(_TrackerTable35[[#This Row],[Total Cost (in USD)]]/_TrackerTable35[[#This Row],[Planned Allocation (in USD)]],"NA") -> 0.97612308 | W13: =IF(AND(_TrackerTable35[[#This Row],[Exchange Rate (1 USD to xxx Listed Currency)]]>0,_TrackerTable35[[#This Row],[Intrinsic Value (in Listed Currency)]]>0,_TrackerTable35[[#This Row],[Intrinsic Value (in Listed Currency)]]<>"NA"),_TrackerTable35[[#This Row],[Intrinsic Value (in Listed Currency)]]/_TrackerTable35[[#This Row],[Exchange Rate (1 USD to xxx Listed Currency)]],"NA") -> 82.41335 | X13: =IFERROR(_TrackerTable35[[#This Row],[Current Price (in USD)]]/_TrackerTable35[[#This Row],[Intrinsic Value (in USD)]]-1,"NA") -> -0.25046729 | Y13: =IF(_TrackerTable35[[#This Row],[Exchange Rate (1 USD to xxx Listed Currency)]]>0,_TrackerTable35[[#This Row],[Current Price (in Listed Currency)]]/_TrackerTable35[[#This Row],[Exchange Rate (1 USD to xxx Listed Currency)]],"NA") -> 61.771502 | Z13: =IFERROR(_TrackerTable35[[#This Row],[Current Price (in USD)]]*_TrackerTable35[[#This Row],[Quantity]],"NA") -> 4941.7202 | AA13: =IFERROR(IF(AND(_TrackerTable35[[#This Row],[Market Value (in USD)]]>0,_TrackerTable35[[#Totals],[Market Value (in USD)]]>0),_TrackerTable35[[#This Row],[Market Value (in USD)]]/_TrackerTable35[[#Totals],[Market Value (in USD)]],"NA"),"NA") -> 0.09302731 | AB13: =IFERROR(_TrackerTable35[[#This Row],[Market Value (in USD)]]/_TrackerTable35[[#This Row],[Total Cost (in USD)]]-1,"NA") -> 0.011221788 | AC13: =IFERROR(_TrackerTable35[[#This Row],[Total Dividend Received (in Listed Currency)]]/_TrackerTable35[[#This Row],[Exchange Rate (1 USD to xxx Listed Currency)]],"NA") -> 0 | AD13: =IFERROR(_TrackerTable35[[#This Row],[Total Dividend Received (in USD)]]/_TrackerTable35[[#This Row],[Total Cost (in USD)]],"NA") -> 0 | AE13: =IFERROR((_TrackerTable35[[#This Row],[Total Dividend Received (in USD)]]+_TrackerTable35[[#This Row],[Market Value (in USD)]])/_TrackerTable35[[#This Row],[Total Cost (in USD)]]-1,"NA") -> 0.011221788
B14: 5 | C14: VEEV | D14: Veeva Systems | E14: Health Care | F14: Growth | G14: Defensive | H14: US | I14: USD | J14: 1 | K14: 5000 | L14: 25 | M14: 200.17 | N14: 44562 | O14: 285 | P14: 0 | Q14: 239.7 | R14: =IFERROR(_TrackerTable35[[#This Row],[Avg Cost per Share (in Listed Currency)]]/_TrackerTable35[[#This Row],[Exchange Rate (1 USD to xxx Listed Currency)]],"NA") -> 200.17 | S14: =IFERROR(_TrackerTable35[[#This Row],[Quantity]]*_TrackerTable35[[#This Row],[Avg Cost per Share (in USD)]],"NA") -> 5004.25 | T14: =IFERROR(_TrackerTable35[[#This Row],[Planned Allocation (in Listed Currency)]]/_TrackerTable35[[#This Row],[Exchange Rate (1 USD to xxx Listed Currency)]],"NA") -> 5000 | U14: =IFERROR(_TrackerTable35[[#This Row],[Planned Allocation (in USD)]]/_TrackerTable35[[#Totals],[Planned Allocation (in USD)]],"NA") -> 0.10884055 | V14: =IFERROR(_TrackerTable35[[#This Row],[Total Cost (in USD)]]/_TrackerTable35[[#This Row],[Planned Allocation (in USD)]],"NA") -> 1.00085 | W14: =IF(AND(_TrackerTable35[[#This Row],[Exchange Rate (1 USD to xxx Listed Currency)]]>0,_TrackerTable35[[#This Row],[Intrinsic Value (in Listed Currency)]]>0,_TrackerTable35[[#This Row],[Intrinsic Value (in Listed Currency)]]<>"NA"),_TrackerTable35[[#This Row],[Intrinsic Value (in Listed Currency)]]/_TrackerTable35[[#This Row],[Exchange Rate (1 USD to xxx Listed Currency)]],"NA") -> 285 | X14: =IFERROR(_TrackerTable35[[#This Row],[Current Price (in USD)]]/_TrackerTable35[[#This Row],[Intrinsic Value (in USD)]]-1,"NA") -> -0.15894737 | Y14: =IF(_TrackerTable35[[#This Row],[Exchange Rate (1 USD to xxx Listed Currency)]]>0,_TrackerTable35[[#This Row],[Current Price (in Listed Currency)]]/_TrackerTable35[[#This Row],[Exchange Rate (1 USD to xxx Listed Currency)]],"NA") -> 239.7 | Z14: =IFERROR(_TrackerTable35[[#This Row],[Current Price (in USD)]]*_TrackerTable35[[#This Row],[Quantity]],"NA") -> 5992.5 | AA14: =IFERROR(IF(AND(_TrackerTable35[[#This Row],[Market Value (in USD)]]>0,_TrackerTable35[[#Totals],[Market Value (in USD)]]>0),_TrackerTable35[[#This Row],[Market Value (in USD)]]/_TrackerTable35[[#Totals],[Market Value (in USD)]],"NA"),"NA") -> 0.11280812 | AB14: =IFERROR(_TrackerTable35[[#This Row],[Market Value (in USD)]]/_TrackerTable35[[#This Row],[Total Cost (in USD)]]-1,"NA") -> 0.19748214 | AC14: =IFERROR(_TrackerTable35[[#This Row],[Total Dividend Received (in Listed Currency)]]/_TrackerTable35[[#This Row],[Exchange Rate (1 USD to xxx Listed Currency)]],"NA") -> 0 | AD14: =IFERROR(_TrackerTable35[[#This Row],[Total Dividend Received (in USD)]]/_TrackerTable35[[#This Row],[Total Cost (in USD)]],"NA") -> 0 | AE14: =IFERROR((_TrackerTable35[[#This Row],[Total Dividend Received (in USD)]]+_TrackerTable35[[#This Row],[Market Value (in USD)]])/_TrackerTable35[[#This Row],[Total Cost (in USD)]]-1,"NA") -> 0.19748214
B15: 6 | C15: GOOGL | D15: Alphabet | E15: Communication Services | F15: Growth | G15: Moderate Cyclical | H15: US | I15: USD | J15: 1 | K15: 5000 | L15: 4 | M15: 1361.06 | N15: 44562 | O15: 3228 | P15: 0 | Q15: 2828.61 | R15: =IFERROR(_TrackerTable35[[#This Row],[Avg Cost per Share (in Listed Currency)]]/_TrackerTable35[[#This Row],[Exchange Rate (1 USD to xxx Listed Currency)]],"NA") -> 1361.06 | S15: =IFERROR(_TrackerTable35[[#This Row],[Quantity]]*_TrackerTable35[[#This Row],[Avg Cost per Share (in USD)]],"NA") -> 5444.24 | T15: =IFERROR(_TrackerTable35[[#This Row],[Planned Allocation (in Listed Currency)]]/_TrackerTable35[[#This Row],[Exchange Rate (1 USD to xxx Listed Currency)]],"NA") -> 5000 | U15: =IFERROR(_TrackerTable35[[#This Row],[Planned Allocation (in USD)]]/_TrackerTable35[[#Totals],[Planned Allocation (in USD)]],"NA") -> 0.10884055 | V15: =IFERROR(_TrackerTable35[[#This Row],[Total Cost (in USD)]]/_TrackerTable35[[#This Row],[Planned Allocation (in USD)]],"NA") -> 1.088848 | W15: =IF(AND(_TrackerTable35[[#This Row],[Exchange Rate (1 USD to xxx Listed Currency)]]>0,_TrackerTable35[[#This Row],[Intrinsic Value (in Listed Currency)]]>0,_TrackerTable35[[#This Row],[Intrinsic Value (in Listed Currency)]]<>"NA"),_TrackerTable35[[#This Row],[Intrinsic Value (in Listed Currency)]]/_TrackerTable35[[#This Row],[Exchange Rate (1 USD to xxx Listed Currency)]],"NA") -> 3228 | X15: =IFERROR(_TrackerTable35[[#This Row],[Current Price (in USD)]]/_TrackerTable35[[#This Row],[Intrinsic Value (in USD)]]-1,"NA") -> -0.12372677 | Y15: =IF(_TrackerTable35[[#This Row],[Exchange Rate (1 USD to xxx Listed Currency)]]>0,_TrackerTable35[[#This Row],[Current Price (in Listed Currency)]]/_TrackerTable35[[#This Row],[Exchange Rate (1 USD to xxx Listed Currency)]],"NA") -> 2828.61 | Z15: =IFERROR(_TrackerTable35[[#This Row],[Current Price (in USD)]]*_TrackerTable35[[#This Row],[Quantity]],"NA") -> 11314.44 | AA15: =IFERROR(IF(AND(_TrackerTable35[[#This Row],[Market Value (in USD)]]>0,_TrackerTable35[[#Totals],[Market Value (in USD)]]>0),_TrackerTable35[[#This Row],[Market Value (in USD)]]/_TrackerTable35[[#Totals],[Market Value (in USD)]],"NA"),"NA") -> 0.21299302 | AB15: =IFERROR(_TrackerTable35[[#This Row],[Market Value (in USD)]]/_TrackerTable35[[#This Row],[Total Cost (in USD)]]-1,"NA") -> 1.0782405 | AC15: =IFERROR(_TrackerTable35[[#This Row],[Total Dividend Received (in Listed Currency)]]/_TrackerTable35[[#This Row],[Exchange Rate (1 USD to xxx Listed Currency)]],"NA") -> 0 | AD15: =IFERROR(_TrackerTable35[[#This Row],[Total Dividend Received (in USD)]]/_TrackerTable35[[#This Row],[Total Cost (in USD)]],"NA") -> 0 | AE15: =IFERROR((_TrackerTable35[[#This Row],[Total Dividend Received (in USD)]]+_TrackerTable35[[#This Row],[Market Value (in USD)]])/_TrackerTable35[[#This Row],[Total Cost (in USD)]]-1,"NA") -> 1.0782405
B16: 7 | C16: 9618 | D16: JD.com | E16: Consumer Discretionary | F16: Growth | G16: Moderate Cyclical | H16: China/HK | I16: HKD | J16: 7.79 | K16: 39000 | L16: 137 | M16: 283.5 | N16: 44562 | O16: 416 | P16: 0 | Q16: 296 | R16: =IFERROR(_TrackerTable35[[#This Row],[Avg Cost per Share (in Listed Currency)]]/_TrackerTable35[[#This Row],[Exchange Rate (1 USD to xxx Listed Currency)]],"NA") -> 36.392811 | S16: =IFERROR(_TrackerTable35[[#This Row],[Quantity]]*_TrackerTable35[[#This Row],[Avg Cost per Share (in USD)]],"NA") -> 4985.8151 | T16: =IFERROR(_TrackerTable35[[#This Row],[Planned Allocation (in Listed Currency)]]/_TrackerTable35[[#This Row],[Exchange Rate (1 USD to xxx Listed Currency)]],"NA") -> 5006.4185 | U16: =IFERROR(_TrackerTable35[[#This Row],[Planned Allocation (in USD)]]/_TrackerTable35[[#Totals],[Planned Allocation (in USD)]],"NA") -> 0.10898026 | V16: =IFERROR(_TrackerTable35[[#This Row],[Total Cost (in USD)]]/_TrackerTable35[[#This Row],[Planned Allocation (in USD)]],"NA") -> 0.99588462 | W16: =IF(AND(_TrackerTable35[[#This Row],[Exchange Rate (1 USD to xxx Listed Currency)]]>0,_TrackerTable35[[#This Row],[Intrinsic Value (in Listed Currency)]]>0,_TrackerTable35[[#This Row],[Intrinsic Value (in Listed Currency)]]<>"NA"),_TrackerTable35[[#This Row],[Intrinsic Value (in Listed Currency)]]/_TrackerTable35[[#This Row],[Exchange Rate (1 USD to xxx Listed Currency)]],"NA") -> 53.401797 | X16: =IFERROR(_TrackerTable35[[#This Row],[Current Price (in USD)]]/_TrackerTable35[[#This Row],[Intrinsic Value (in USD)]]-1,"NA") -> -0.28846154 | Y16: =IF(_TrackerTable35[[#This Row],[Exchange Rate (1 USD to xxx Listed Currency)]]>0,_TrackerTable35[[#This Row],[Current Price (in Listed Currency)]]/_TrackerTable35[[#This Row],[Exchange Rate (1 USD to xxx Listed Currency)]],"NA") -> 37.997433 | Z16: =IFERROR(_TrackerTable35[[#This Row],[Current Price (in USD)]]*_TrackerTable35[[#This Row],[Quantity]],"NA") -> 5205.6483 | AA16: =IFERROR(IF(AND(_TrackerTable35[[#This Row],[Market Value (in USD)]]>0,_TrackerTable35[[#Totals],[Market Value (in USD)]]>0),_TrackerTable35[[#This Row],[Market Value (in USD)]]/_TrackerTable35[[#Totals],[Market Value (in USD)]],"NA"),"NA") -> 0.097995726 | AB16: =IFERROR(_TrackerTable35[[#This Row],[Market Value (in USD)]]/_TrackerTable35[[#This Row],[Total Cost (in USD)]]-1,"NA") -> 0.044091711 | AC16: =IFERROR(_TrackerTable35[[#This Row],[Total Dividend Received (in Listed Currency)]]/_TrackerTable35[[#This Row],[Exchange Rate (1 USD to xxx Listed Currency)]],"NA") -> 0 | AD16: =IFERROR(_TrackerTable35[[#This Row],[Total Dividend Received (in USD)]]/_TrackerTable35[[#This Row],[Total Cost (in USD)]],"NA") -> 0 | AE16: =IFERROR((_TrackerTable35[[#This Row],[Total Dividend Received (in USD)]]+_TrackerTable35[[#This Row],[Market Value (in USD)]])/_TrackerTable35[[#This Row],[Total Cost (in USD)]]-1,"NA") -> 0.044091711
B17: 8 | C17: ASHR | D17: CSI 300 China A-Shares | E17: Diversified | F17: ETF | G17: Moderate Cyclical | H17: China/HK | I17: USD | J17: 1 | K17: 5000 | L17: 154 | M17: 31.89 | N17: NA | O17: NA | P17: 0 | Q17: 38.67 | R17: =IFERROR(_TrackerTable35[[#This Row],[Avg Cost per Share (in Listed Currency)]]/_TrackerTable35[[#This Row],[Exchange Rate (1 USD to xxx Listed Currency)]],"NA") -> 31.89 | S17: =IFERROR(_TrackerTable35[[#This Row],[Quantity]]*_TrackerTable35[[#This Row],[Avg Cost per Share (in USD)]],"NA") -> 4911.06 | T17: =IFERROR(_TrackerTable35[[#This Row],[Planned Allocation (in Listed Currency)]]/_TrackerTable35[[#This Row],[Exchange Rate (1 USD to xxx Listed Currency)]],"NA") -> 5000 | U17: =IFERROR(_TrackerTable35[[#This Row],[Planned Allocation (in USD)]]/_TrackerTable35[[#Totals],[Planned Allocation (in USD)]],"NA") -> 0.10884055 | V17: =IFERROR(_TrackerTable35[[#This Row],[Total Cost (in USD)]]/_TrackerTable35[[#This Row],[Planned Allocation (in USD)]],"NA") -> 0.982212 | W17: =IF(AND(_TrackerTable35[[#This Row],[Exchange Rate (1 USD to xxx Listed Currency)]]>0,_TrackerTable35[[#This Row],[Intrinsic Value (in Listed Currency)]]>0,_TrackerTable35[[#This Row],[Intrinsic Value (in Listed Currency)]]<>"NA"),_TrackerTable35[[#This Row],[Intrinsic Value (in Listed Currency)]]/_TrackerTable35[[#This Row],[Exchange Rate (1 USD to xxx Listed Currency)]],"NA") -> NA | X17: =IFERROR(_TrackerTable35[[#This Row],[Current Price (in USD)]]/_TrackerTable35[[#This Row],[Intrinsic Value (in USD)]]-1,"NA") -> NA | Y17: =IF(_TrackerTable35[[#This Row],[Exchange Rate (1 USD to xxx Listed Currency)]]>0,_TrackerTable35[[#This Row],[Current Price (in Listed Currency)]]/_TrackerTable35[[#This Row],[Exchange Rate (1 USD to xxx Listed Currency)]],"NA") -> 38.67 | Z17: =IFERROR(_TrackerTable35[[#This Row],[Current Price (in USD)]]*_TrackerTable35[[#This Row],[Quantity]],"NA") -> 5955.18 | AA17: =IFERROR(IF(AND(_TrackerTable35[[#This Row],[Market Value (in USD)]]>0,_TrackerTable35[[#Totals],[Market Value (in USD)]]>0),_TrackerTable35[[#This Row],[Market Value (in USD)]]/_TrackerTable35[[#Totals],[Market Value (in USD)]],"NA"),"NA") -> 0.11210557 | AB17: =IFERROR(_TrackerTable35[[#This Row],[Market Value (in USD)]]/_TrackerTable35[[#This Row],[Total Cost (in USD)]]-1,"NA") -> 0.21260583 | AC17: =IFERROR(_TrackerTable35[[#This Row],[Total Dividend Received (in Listed Currency)]]/_TrackerTable35[[#This Row],[Exchange Rate (1 USD to xxx Listed Currency)]],"NA") -> 0 | AD17: =IFERROR(_TrackerTable35[[#This Row],[Total Dividend Received (in USD)]]/_TrackerTable35[[#This Row],[Total Cost (in USD)]],"NA") -> 0 | AE17: =IFERROR((_TrackerTable35[[#This Row],[Total Dividend Received (in USD)]]+_TrackerTable35[[#This Row],[Market Value (in USD)]])/_TrackerTable35[[#This Row],[Total Cost (in USD)]]-1,"NA") -> 0.21260583
B18: 9 | C18: MCD | D18: McDonald's | E18: Consumer Staples | F18: Predictable | G18: Defensive | H18: US | I18: USD | J18: 1 | K18: 5000 | L18: 26 | M18: 190.47 | N18: 44562 | O18: 234 | P18: 0 | Q18: 260.92 | R18: =IFERROR(_TrackerTable35[[#This Row],[Avg Cost per Share (in Listed Currency)]]/_TrackerTable35[[#This Row],[Exchange Rate (1 USD to xxx Listed Currency)]],"NA") -> 190.47 | S18: =IFERROR(_TrackerTable35[[#This Row],[Quantity]]*_TrackerTable35[[#This Row],[Avg Cost per Share (in USD)]],"NA") -> 4952.22 | T18: =IFERROR(_TrackerTable35[[#This Row],[Planned Allocation (in Listed Currency)]]/_TrackerTable35[[#This Row],[Exchange Rate (1 USD to xxx Listed Currency)]],"NA") -> 5000 | U18: =IFERROR(_TrackerTable35[[#This Row],[Planned Allocation (in USD)]]/_TrackerTable35[[#Totals],[Planned Allocation (in USD)]],"NA") -> 0.10884055 | V18: =IFERROR(_TrackerTable35[[#This Row],[Total Cost (in USD)]]/_TrackerTable35[[#This Row],[Planned Allocation (in USD)]],"NA") -> 0.990444 | W18: =IF(AND(_TrackerTable35[[#This Row],[Exchange Rate (1 USD to xxx Listed Currency)]]>0,_TrackerTable35[[#This Row],[Intrinsic Value (in Listed Currency)]]>0,_TrackerTable35[[#This Row],[Intrinsic Value (in Listed Currency)]]<>"NA"),_TrackerTable35[[#This Row],[Intrinsic Value (in Listed Currency)]]/_TrackerTable35[[#This Row],[Exchange Rate (1 USD to xxx Listed Currency)]],"NA") -> 234 | X18: =IFERROR(_TrackerTable35[[#This Row],[Current Price (in USD)]]/_TrackerTable35[[#This Row],[Intrinsic Value (in USD)]]-1,"NA") -> 0.11504274 | Y18: =IF(_TrackerTable35[[#This Row],[Exchange Rate (1 USD to xxx Listed Currency)]]>0,_TrackerTable35[[#This Row],[Current Price (in Listed Currency)]]/_TrackerTable35[[#This Row],[Exchange Rate (1 USD to xxx Listed Currency)]],"NA") -> 260.92 | Z18: =IFERROR(_TrackerTable35[[#This Row],[Current Price (in USD)]]*_TrackerTable35[[#This Row],[Quantity]],"NA") -> 6783.92 | AA18: =IFERROR(IF(AND(_TrackerTable35[[#This Row],[Market Value (in USD)]]>0,_TrackerTable35[[#Totals],[Market Value (in USD)]]>0),_TrackerTable35[[#This Row],[Market Value (in USD)]]/_TrackerTable35[[#Totals],[Market Value (in USD)]],"NA"),"NA") -> 0.12770651 | AB18: =IFERROR(_TrackerTable35[[#This Row],[Market Value (in USD)]]/_TrackerTable35[[#This Row],[Total Cost (in USD)]]-1,"NA") -> 0.36987452 | AC18: =IFERROR(_TrackerTable35[[#This Row],[Total Dividend Received (in Listed Currency)]]/_TrackerTable35[[#This Row],[Exchange Rate (1 USD to xxx Listed Currency)]],"NA") -> 0 | AD18: =IFERROR(_TrackerTable35[[#This Row],[Total Dividend Received (in USD)]]/_TrackerTable35[[#This Row],[Total Cost (in USD)]],"NA") -> 0 | AE18: =IFERROR((_TrackerTable35[[#This Row],[Total Dividend Received (in USD)]]+_TrackerTable35[[#This Row],[Market Value (in USD)]])/_TrackerTable35[[#This Row],[Total Cost (in USD)]]-1,"NA") -> 0.36987452
B19: 10 | R19: =IFERROR(_TrackerTable35[[#This Row],[Avg Cost per Share (in Listed Currency)]]/_TrackerTable35[[#This Row],[Exchange Rate (1 USD to xxx Listed Currency)]],"NA") -> NA | S19: =IFERROR(_TrackerTable35[[#This Row],[Quantity]]*_TrackerTable35[[#This Row],[Avg Cost per Share (in USD)]],"NA") -> NA | T19: =IFERROR(_TrackerTable35[[#This Row],[Planned Allocation (in Listed Currency)]]/_TrackerTable35[[#This Row],[Exchange Rate (1 USD to xxx Listed Currency)]],"NA") -> NA | U19: =IFERROR(_TrackerTable35[[#This Row],[Planned Allocation (in USD)]]/_TrackerTable35[[#Totals],[Planned Allocation (in USD)]],"NA") -> NA | V19: =IFERROR(_TrackerTable35[[#This Row],[Total Cost (in USD)]]/_TrackerTable35[[#This Row],[Planned Allocation (in USD)]],"NA") -> NA | W19: =IF(AND(_TrackerTable35[[#This Row],[Exchange Rate (1 USD to xxx Listed Currency)]]>0,_TrackerTable35[[#This Row],[Intrinsic Value (in Listed Currency)]]>0,_TrackerTable35[[#This Row],[Intrinsic Value (in Listed Currency)]]<>"NA"),_TrackerTable35[[#This Row],[Intrinsic Value (in Listed Currency)]]/_TrackerTable35[[#This Row],[Exchange Rate (1 USD to xxx Listed Currency)]],"NA") -> NA | X19: =IFERROR(_TrackerTable35[[#This Row],[Current Price (in USD)]]/_TrackerTable35[[#This Row],[Intrinsic Value (in USD)]]-1,"NA") -> NA | Y19: =IF(_TrackerTable35[[#This Row],[Exchange Rate (1 USD to xxx Listed Currency)]]>0,_TrackerTable35[[#This Row],[Current Price (in Listed Currency)]]/_TrackerTable35[[#This Row],[Exchange Rate (1 USD to xxx Listed Currency)]],"NA") -> NA | Z19: =IFERROR(_TrackerTable35[[#This Row],[Current Price (in USD)]]*_TrackerTable35[[#This Row],[Quantity]],"NA") -> NA | AA19: =IFERROR(IF(AND(_TrackerTable35[[#This Row],[Market Value (in USD)]]>0,_TrackerTable35[[#Totals],[Market Value (in USD)]]>0),_TrackerTable35[[#This Row],[Market Value (in USD)]]/_TrackerTable35[[#Totals],[Market Value (in USD)]],"NA"),"NA") -> NA | AB19: =IFERROR(_TrackerTable35[[#This Row],[Market Value (in USD)]]/_TrackerTable35[[#This Row],[Total Cost (in USD)]]-1,"NA") -> NA | AC19: =IFERROR(_TrackerTable35[[#This Row],[Total Dividend Received (in Listed Currency)]]/_TrackerTable35[[#This Row],[Exchange Rate (1 USD to xxx Listed Currency)]],"NA") -> NA | AD19: =IFERROR(_TrackerTable35[[#This Row],[Total Dividend Received (in USD)]]/_TrackerTable35[[#This Row],[Total Cost (in USD)]],"NA") -> NA | AE19: =IFERROR((_TrackerTable35[[#This Row],[Total Dividend Received (in USD)]]+_TrackerTable35[[#This Row],[Market Value (in USD)]])/_TrackerTable35[[#This Row],[Total Cost (in USD)]]-1,"NA") -> NA
B20: 11 | R20: =IFERROR(_TrackerTable35[[#This Row],[Avg Cost per Share (in Listed Currency)]]/_TrackerTable35[[#This Row],[Exchange Rate (1 USD to xxx Listed Currency)]],"NA") -> NA | S20: =IFERROR(_TrackerTable35[[#This Row],[Quantity]]*_TrackerTable35[[#This Row],[Avg Cost per Share (in USD)]],"NA") -> NA | T20: =IFERROR(_TrackerTable35[[#This Row],[Planned Allocation (in Listed Currency)]]/_TrackerTable35[[#This Row],[Exchange Rate (1 USD to xxx Listed Currency)]],"NA") -> NA | U20: =IFERROR(_TrackerTable35[[#This Row],[Planned Allocation (in USD)]]/_TrackerTable35[[#Totals],[Planned Allocation (in USD)]],"NA") -> NA | V20: =IFERROR(_TrackerTable35[[#This Row],[Total Cost (in USD)]]/_TrackerTable35[[#This Row],[Planned Allocation (in USD)]],"NA") -> NA | W20: =IF(AND(_TrackerTable35[[#This Row],[Exchange Rate (1 USD to xxx Listed Currency)]]>0,_TrackerTable35[[#This Row],[Intrinsic Value (in Listed Currency)]]>0,_TrackerTable35[[#This Row],[Intrinsic Value (in Listed Currency)]]<>"NA"),_TrackerTable35[[#This Row],[Intrinsic Value (in Listed Currency)]]/_TrackerTable35[[#This Row],[Exchange Rate (1 USD to xxx Listed Currency)]],"NA") -> NA | X20: =IFERROR(_TrackerTable35[[#This Row],[Current Price (in USD)]]/_TrackerTable35[[#This Row],[Intrinsic Value (in USD)]]-1,"NA") -> NA | Y20: =IF(_TrackerTable35[[#This Row],[Exchange Rate (1 USD to xxx Listed Currency)]]>0,_TrackerTable35[[#This Row],[Current Price (in Listed Currency)]]/_TrackerTable35[[#This Row],[Exchange Rate (1 USD to xxx Listed Currency)]],"NA") -> NA | Z20: =IFERROR(_TrackerTable35[[#This Row],[Current Price (in USD)]]*_TrackerTable35[[#This Row],[Quantity]],"NA") -> NA | AA20: =IFERROR(IF(AND(_TrackerTable35[[#This Row],[Market Value (in USD)]]>0,_TrackerTable35[[#Totals],[Market Value (in USD)]]>0),_TrackerTable35[[#This Row],[Market Value (in USD)]]/_TrackerTable35[[#Totals],[Market Value (in USD)]],"NA"),"NA") -> NA | AB20: =IFERROR(_TrackerTable35[[#This Row],[Market Value (in USD)]]/_TrackerTable35[[#This Row],[Total Cost (in USD)]]-1,"NA") -> NA | AC20: =IFERROR(_TrackerTable35[[#This Row],[Total Dividend Received (in Listed Currency)]]/_TrackerTable35[[#This Row],[Exchange Rate (1 USD to xxx Listed Currency)]],"NA") -> NA | AD20: =IFERROR(_TrackerTable35[[#This Row],[Total Dividend Received (in USD)]]/_TrackerTable35[[#This Row],[Total Cost (in USD)]],"NA") -> NA | AE20: =IFERROR((_TrackerTable35[[#This Row],[Total Dividend Received (in USD)]]+_TrackerTable35[[#This Row],[Market Value (in USD)]])/_TrackerTable35[[#This Row],[Total Cost (in USD)]]-1,"NA") -> NA
B21: 12 | R21: =IFERROR(_TrackerTable35[[#This Row],[Avg Cost per Share (in Listed Currency)]]/_TrackerTable35[[#This Row],[Exchange Rate (1 USD to xxx Listed Currency)]],"NA") -> NA | S21: =IFERROR(_TrackerTable35[[#This Row],[Quantity]]*_TrackerTable35[[#This Row],[Avg Cost per Share (in USD)]],"NA") -> NA | T21: =IFERROR(_TrackerTable35[[#This Row],[Planned Allocation (in Listed Currency)]]/_TrackerTable35[[#This Row],[Exchange Rate (1 USD to xxx Listed Currency)]],"NA") -> NA | U21: =IFERROR(_TrackerTable35[[#This Row],[Planned Allocation (in USD)]]/_TrackerTable35[[#Totals],[Planned Allocation (in USD)]],"NA") -> NA | V21: =IFERROR(_TrackerTable35[[#This Row],[Total Cost (in USD)]]/_TrackerTable35[[#This Row],[Planned Allocation (in USD)]],"NA") -> NA | W21: =IF(AND(_TrackerTable35[[#This Row],[Exchange Rate (1 USD to xxx Listed Currency)]]>0,_TrackerTable35[[#This Row],[Intrinsic Value (in Listed Currency)]]>0,_TrackerTable35[[#This Row],[Intrinsic Value (in Listed Currency)]]<>"NA"),_TrackerTable35[[#This Row],[Intrinsic Value (in Listed Currency)]]/_TrackerTable35[[#This Row],[Exchange Rate (1 USD to xxx Listed Currency)]],"NA") -> NA | X21: =IFERROR(_TrackerTable35[[#This Row],[Current Price (in USD)]]/_TrackerTable35[[#This Row],[Intrinsic Value (in USD)]]-1,"NA") -> NA | Y21: =IF(_TrackerTable35[[#This Row],[Exchange Rate (1 USD to xxx Listed Currency)]]>0,_TrackerTable35[[#This Row],[Current Price (in Listed Currency)]]/_TrackerTable35[[#This Row],[Exchange Rate (1 USD to xxx Listed Currency)]],"NA") -> NA | Z21: =IFERROR(_TrackerTable35[[#This Row],[Current Price (in USD)]]*_TrackerTable35[[#This Row],[Quantity]],"NA") -> NA | AA21: =IFERROR(IF(AND(_TrackerTable35[[#This Row],[Market Value (in USD)]]>0,_TrackerTable35[[#Totals],[Market Value (in USD)]]>0),_TrackerTable35[[#This Row],[Market Value (in USD)]]/_TrackerTable35[[#Totals],[Market Value (in USD)]],"NA"),"NA") -> NA | AB21: =IFERROR(_TrackerTable35[[#This Row],[Market Value (in USD)]]/_TrackerTable35[[#This Row],[Total Cost (in USD)]]-1,"NA") -> NA | AC21: =IFERROR(_TrackerTable35[[#This Row],[Total Dividend Received (in Listed Currency)]]/_TrackerTable35[[#This Row],[Exchange Rate (1 USD to xxx Listed Currency)]],"NA") -> NA | AD21: =IFERROR(_TrackerTable35[[#This Row],[Total Dividend Received (in USD)]]/_TrackerTable35[[#This Row],[Total Cost (in USD)]],"NA") -> NA | AE21: =IFERROR((_TrackerTable35[[#This Row],[Total Dividend Received (in USD)]]+_TrackerTable35[[#This Row],[Market Value (in USD)]])/_TrackerTable35[[#This Row],[Total Cost (in USD)]]-1,"NA") -> NA
B22: 13 | R22: =IFERROR(_TrackerTable35[[#This Row],[Avg Cost per Share (in Listed Currency)]]/_TrackerTable35[[#This Row],[Exchange Rate (1 USD to xxx Listed Currency)]],"NA") -> NA | S22: =IFERROR(_TrackerTable35[[#This Row],[Quantity]]*_TrackerTable35[[#This Row],[Avg Cost per Share (in USD)]],"NA") -> NA | T22: =IFERROR(_TrackerTable35[[#This Row],[Planned Allocation (in Listed Currency)]]/_TrackerTable35[[#This Row],[Exchange Rate (1 USD to xxx Listed Currency)]],"NA") -> NA | U22: =IFERROR(_TrackerTable35[[#This Row],[Planned Allocation (in USD)]]/_TrackerTable35[[#Totals],[Planned Allocation (in USD)]],"NA") -> NA | V22: =IFERROR(_TrackerTable35[[#This Row],[Total Cost (in USD)]]/_TrackerTable35[[#This Row],[Planned Allocation (in USD)]],"NA") -> NA | W22: =IF(AND(_TrackerTable35[[#This Row],[Exchange Rate (1 USD to xxx Listed Currency)]]>0,_TrackerTable35[[#This Row],[Intrinsic Value (in Listed Currency)]]>0,_TrackerTable35[[#This Row],[Intrinsic Value (in Listed Currency)]]<>"NA"),_TrackerTable35[[#This Row],[Intrinsic Value (in Listed Currency)]]/_TrackerTable35[[#This Row],[Exchange Rate (1 USD to xxx Listed Currency)]],"NA") -> NA | X22: =IFERROR(_TrackerTable35[[#This Row],[Current Price (in USD)]]/_TrackerTable35[[#This Row],[Intrinsic Value (in USD)]]-1,"NA") -> NA | Y22: =IF(_TrackerTable35[[#This Row],[Exchange Rate (1 USD to xxx Listed Currency)]]>0,_TrackerTable35[[#This Row],[Current Price (in Listed Currency)]]/_TrackerTable35[[#This Row],[Exchange Rate (1 USD to xxx Listed Currency)]],"NA") -> NA | Z22: =IFERROR(_TrackerTable35[[#This Row],[Current Price (in USD)]]*_TrackerTable35[[#This Row],[Quantity]],"NA") -> NA | AA22: =IFERROR(IF(AND(_TrackerTable35[[#This Row],[Market Value (in USD)]]>0,_TrackerTable35[[#Totals],[Market Value (in USD)]]>0),_TrackerTable35[[#This Row],[Market Value (in USD)]]/_TrackerTable35[[#Totals],[Market Value (in USD)]],"NA"),"NA") -> NA | AB22: =IFERROR(_TrackerTable35[[#This Row],[Market Value (in USD)]]/_TrackerTable35[[#This Row],[Total Cost (in USD)]]-1,"NA") -> NA | AC22: =IFERROR(_TrackerTable35[[#This Row],[Total Dividend Received (in Listed Currency)]]/_TrackerTable35[[#This Row],[Exchange Rate (1 USD to xxx Listed Currency)]],"NA") -> NA | AD22: =IFERROR(_TrackerTable35[[#This Row],[Total Dividend Received (in USD)]]/_TrackerTable35[[#This Row],[Total Cost (in USD)]],"NA") -> NA | AE22: =IFERROR((_TrackerTable35[[#This Row],[Total Dividend Received (in USD)]]+_TrackerTable35[[#This Row],[Market Value (in USD)]])/_TrackerTable35[[#This Row],[Total Cost (in USD)]]-1,"NA") -> NA
B23: 14 | R23: =IFERROR(_TrackerTable35[[#This Row],[Avg Cost per Share (in Listed Currency)]]/_TrackerTable35[[#This Row],[Exchange Rate (1 USD to xxx Listed Currency)]],"NA") -> NA | S23: =IFERROR(_TrackerTable35[[#This Row],[Quantity]]*_TrackerTable35[[#This Row],[Avg Cost per Share (in USD)]],"NA") -> NA | T23: =IFERROR(_TrackerTable35[[#This Row],[Planned Allocation (in Listed Currency)]]/_TrackerTable35[[#This Row],[Exchange Rate (1 USD to xxx Listed Currency)]],"NA") -> NA | U23: =IFERROR(_TrackerTable35[[#This Row],[Planned Allocation (in USD)]]/_TrackerTable35[[#Totals],[Planned Allocation (in USD)]],"NA") -> NA | V23: =IFERROR(_TrackerTable35[[#This Row],[Total Cost (in USD)]]/_TrackerTable35[[#This Row],[Planned Allocation (in USD)]],"NA") -> NA | W23: =IF(AND(_TrackerTable35[[#This Row],[Exchange Rate (1 USD to xxx Listed Currency)]]>0,_TrackerTable35[[#This Row],[Intrinsic Value (in Listed Currency)]]>0,_TrackerTable35[[#This Row],[Intrinsic Value (in Listed Currency)]]<>"NA"),_TrackerTable35[[#This Row],[Intrinsic Value (in Listed Currency)]]/_TrackerTable35[[#This Row],[Exchange Rate (1 USD to xxx Listed Currency)]],"NA") -> NA | X23: =IFERROR(_TrackerTable35[[#This Row],[Current Price (in USD)]]/_TrackerTable35[[#This Row],[Intrinsic Value (in USD)]]-1,"NA") -> NA | Y23: =IF(_TrackerTable35[[#This Row],[Exchange Rate (1 USD to xxx Listed Currency)]]>0,_TrackerTable35[[#This Row],[Current Price (in Listed Currency)]]/_TrackerTable35[[#This Row],[Exchange Rate (1 USD to xxx Listed Currency)]],"NA") -> NA | Z23: =IFERROR(_TrackerTable35[[#This Row],[Current Price (in USD)]]*_TrackerTable35[[#This Row],[Quantity]],"NA") -> NA | AA23: =IFERROR(IF(AND(_TrackerTable35[[#This Row],[Market Value (in USD)]]>0,_TrackerTable35[[#Totals],[Market Value (in USD)]]>0),_TrackerTable35[[#This Row],[Market Value (in USD)]]/_TrackerTable35[[#Totals],[Market Value (in USD)]],"NA"),"NA") -> NA | AB23: =IFERROR(_TrackerTable35[[#This Row],[Market Value (in USD)]]/_TrackerTable35[[#This Row],[Total Cost (in USD)]]-1,"NA") -> NA | AC23: =IFERROR(_TrackerTable35[[#This Row],[Total Dividend Received (in Listed Currency)]]/_TrackerTable35[[#This Row],[Exchange Rate (1 USD to xxx Listed Currency)]],"NA") -> NA | AD23: =IFERROR(_TrackerTable35[[#This Row],[Total Dividend Received (in USD)]]/_TrackerTable35[[#This Row],[Total Cost (in USD)]],"NA") -> NA | AE23: =IFERROR((_TrackerTable35[[#This Row],[Total Dividend Received (in USD)]]+_TrackerTable35[[#This Row],[Market Value (in USD)]])/_TrackerTable35[[#This Row],[Total Cost (in USD)]]-1,"NA") -> NA
B24: 15 | R24: =IFERROR(_TrackerTable35[[#This Row],[Avg Cost per Share (in Listed Currency)]]/_TrackerTable35[[#This Row],[Exchange Rate (1 USD to xxx Listed Currency)]],"NA") -> NA | S24: =IFERROR(_TrackerTable35[[#This Row],[Quantity]]*_TrackerTable35[[#This Row],[Avg Cost per Share (in USD)]],"NA") -> NA | T24: =IFERROR(_TrackerTable35[[#This Row],[Planned Allocation (in Listed Currency)]]/_TrackerTable35[[#This Row],[Exchange Rate (1 USD to xxx Listed Currency)]],"NA") -> NA | U24: =IFERROR(_TrackerTable35[[#This Row],[Planned Allocation (in USD)]]/_TrackerTable35[[#Totals],[Planned Allocation (in USD)]],"NA") -> NA | V24: =IFERROR(_TrackerTable35[[#This Row],[Total Cost (in USD)]]/_TrackerTable35[[#This Row],[Planned Allocation (in USD)]],"NA") -> NA | W24: =IF(AND(_TrackerTable35[[#This Row],[Exchange Rate (1 USD to xxx Listed Currency)]]>0,_TrackerTable35[[#This Row],[Intrinsic Value (in Listed Currency)]]>0,_TrackerTable35[[#This Row],[Intrinsic Value (in Listed Currency)]]<>"NA"),_TrackerTable35[[#This Row],[Intrinsic Value (in Listed Currency)]]/_TrackerTable35[[#This Row],[Exchange Rate (1 USD to xxx Listed Currency)]],"NA") -> NA | X24: =IFERROR(_TrackerTable35[[#This Row],[Current Price (in USD)]]/_TrackerTable35[[#This Row],[Intrinsic Value (in USD)]]-1,"NA") -> NA | Y24: =IF(_TrackerTable35[[#This Row],[Exchange Rate (1 USD to xxx Listed Currency)]]>0,_TrackerTable35[[#This Row],[Current Price (in Listed Currency)]]/_TrackerTable35[[#This Row],[Exchange Rate (1 USD to xxx Listed Currency)]],"NA") -> NA | Z24: =IFERROR(_TrackerTable35[[#This Row],[Current Price (in USD)]]*_TrackerTable35[[#This Row],[Quantity]],"NA") -> NA | AA24: =IFERROR(IF(AND(_TrackerTable35[[#This Row],[Market Value (in USD)]]>0,_TrackerTable35[[#Totals],[Market Value (in USD)]]>0),_TrackerTable35[[#This Row],[Market Value (in USD)]]/_TrackerTable35[[#Totals],[Market Value (in USD)]],"NA"),"NA") -> NA | AB24: =IFERROR(_TrackerTable35[[#This Row],[Market Value (in USD)]]/_TrackerTable35[[#This Row],[Total Cost (in USD)]]-1,"NA") -> NA | AC24: =IFERROR(_TrackerTable35[[#This Row],[Total Dividend Received (in Listed Currency)]]/_TrackerTable35[[#This Row],[Exchange Rate (1 USD to xxx Listed Currency)]],"NA") -> NA | AD24: =IFERROR(_TrackerTable35[[#This Row],[Total Dividend Received (in USD)]]/_TrackerTable35[[#This Row],[Total Cost (in USD)]],"NA") -> NA | AE24: =IFERROR((_TrackerTable35[[#This Row],[Total Dividend Received (in USD)]]+_TrackerTable35[[#This Row],[Market Value (in USD)]])/_TrackerTable35[[#This Row],[Total Cost (in USD)]]-1,"NA") -> NA
B25: 16 | R25: =IFERROR(_TrackerTable35[[#This Row],[Avg Cost per Share (in Listed Currency)]]/_TrackerTable35[[#This Row],[Exchange Rate (1 USD to xxx Listed Currency)]],"NA") -> NA | S25: =IFERROR(_TrackerTable35[[#This Row],[Quantity]]*_TrackerTable35[[#This Row],[Avg Cost per Share (in USD)]],"NA") -> NA | T25: =IFERROR(_TrackerTable35[[#This Row],[Planned Allocation (in Listed Currency)]]/_TrackerTable35[[#This Row],[Exchange Rate (1 USD to xxx Listed Currency)]],"NA") -> NA | U25: =IFERROR(_TrackerTable35[[#This Row],[Planned Allocation (in USD)]]/_TrackerTable35[[#Totals],[Planned Allocation (in USD)]],"NA") -> NA | V25: =IFERROR(_TrackerTable35[[#This Row],[Total Cost (in USD)]]/_TrackerTable35[[#This Row],[Planned Allocation (in USD)]],"NA") -> NA | W25: =IF(AND(_TrackerTable35[[#This Row],[Exchange Rate (1 USD to xxx Listed Currency)]]>0,_TrackerTable35[[#This Row],[Intrinsic Value (in Listed Currency)]]>0,_TrackerTable35[[#This Row],[Intrinsic Value (in Listed Currency)]]<>"NA"),_TrackerTable35[[#This Row],[Intrinsic Value (in Listed Currency)]]/_TrackerTable35[[#This Row],[Exchange Rate (1 USD to xxx Listed Currency)]],"NA") -> NA | X25: =IFERROR(_TrackerTable35[[#This Row],[Current Price (in USD)]]/_TrackerTable35[[#This Row],[Intrinsic Value (in USD)]]-1,"NA") -> NA | Y25: =IF(_TrackerTable35[[#This Row],[Exchange Rate (1 USD to xxx Listed Currency)]]>0,_TrackerTable35[[#This Row],[Current Price (in Listed Currency)]]/_TrackerTable35[[#This Row],[Exchange Rate (1 USD to xxx Listed Currency)]],"NA") -> NA | Z25: =IFERROR(_TrackerTable35[[#This Row],[Current Price (in USD)]]*_TrackerTable35[[#This Row],[Quantity]],"NA") -> NA | AA25: =IFERROR(IF(AND(_TrackerTable35[[#This Row],[Market Value (in USD)]]>0,_TrackerTable35[[#Totals],[Market Value (in USD)]]>0),_TrackerTable35[[#This Row],[Market Value (in USD)]]/_TrackerTable35[[#Totals],[Market Value (in USD)]],"NA"),"NA") -> NA | AB25: =IFERROR(_TrackerTable35[[#This Row],[Market Value (in USD)]]/_TrackerTable35[[#This Row],[Total Cost (in USD)]]-1,"NA") -> NA | AC25: =IFERROR(_TrackerTable35[[#This Row],[Total Dividend Received (in Listed Currency)]]/_TrackerTable35[[#This Row],[Exchange Rate (1 USD to xxx Listed Currency)]],"NA") -> NA | AD25: =IFERROR(_TrackerTable35[[#This Row],[Total Dividend Received (in USD)]]/_TrackerTable35[[#This Row],[Total Cost (in USD)]],"NA") -> NA | AE25: =IFERROR((_TrackerTable35[[#This Row],[Total Dividend Received (in USD)]]+_TrackerTable35[[#This Row],[Market Value (in USD)]])/_TrackerTable35[[#This Row],[Total Cost (in USD)]]-1,"NA") -> NA
B26: 17 | R26: =IFERROR(_TrackerTable35[[#This Row],[Avg Cost per Share (in Listed Currency)]]/_TrackerTable35[[#This Row],[Exchange Rate (1 USD to xxx Listed Currency)]],"NA") -> NA | S26: =IFERROR(_TrackerTable35[[#This Row],[Quantity]]*_TrackerTable35[[#This Row],[Avg Cost per Share (in USD)]],"NA") -> NA | T26: =IFERROR(_TrackerTable35[[#This Row],[Planned Allocation (in Listed Currency)]]/_TrackerTable35[[#This Row],[Exchange Rate (1 USD to xxx Listed Currency)]],"NA") -> NA | U26: =IFERROR(_TrackerTable35[[#This Row],[Planned Allocation (in USD)]]/_TrackerTable35[[#Totals],[Planned Allocation (in USD)]],"NA") -> NA | V26: =IFERROR(_TrackerTable35[[#This Row],[Total Cost (in USD)]]/_TrackerTable35[[#This Row],[Planned Allocation (in USD)]],"NA") -> NA | W26: =IF(AND(_TrackerTable35[[#This Row],[Exchange Rate (1 USD to xxx Listed Currency)]]>0,_TrackerTable35[[#This Row],[Intrinsic Value (in Listed Currency)]]>0,_TrackerTable35[[#This Row],[Intrinsic Value (in Listed Currency)]]<>"NA"),_TrackerTable35[[#This Row],[Intrinsic Value (in Listed Currency)]]/_TrackerTable35[[#This Row],[Exchange Rate (1 USD to xxx Listed Currency)]],"NA") -> NA | X26: =IFERROR(_TrackerTable35[[#This Row],[Current Price (in USD)]]/_TrackerTable35[[#This Row],[Intrinsic Value (in USD)]]-1,"NA") -> NA | Y26: =IF(_TrackerTable35[[#This Row],[Exchange Rate (1 USD to xxx Listed Currency)]]>0,_TrackerTable35[[#This Row],[Current Price (in Listed Currency)]]/_TrackerTable35[[#This Row],[Exchange Rate (1 USD to xxx Listed Currency)]],"NA") -> NA | Z26: =IFERROR(_TrackerTable35[[#This Row],[Current Price (in USD)]]*_TrackerTable35[[#This Row],[Quantity]],"NA") -> NA | AA26: =IFERROR(IF(AND(_TrackerTable35[[#This Row],[Market Value (in USD)]]>0,_TrackerTable35[[#Totals],[Market Value (in USD)]]>0),_TrackerTable35[[#This Row],[Market Value (in USD)]]/_TrackerTable35[[#Totals],[Market Value (in USD)]],"NA"),"NA") -> NA | AB26: =IFERROR(_TrackerTable35[[#This Row],[Market Value (in USD)]]/_TrackerTable35[[#This Row],[Total Cost (in USD)]]-1,"NA") -> NA | AC26: =IFERROR(_TrackerTable35[[#This Row],[Total Dividend Received (in Listed Currency)]]/_TrackerTable35[[#This Row],[Exchange Rate (1 USD to xxx Listed Currency)]],"NA") -> NA | AD26: =IFERROR(_TrackerTable35[[#This Row],[Total Dividend Received (in USD)]]/_TrackerTable35[[#This Row],[Total Cost (in USD)]],"NA") -> NA | AE26: =IFERROR((_TrackerTable35[[#This Row],[Total Dividend Received (in USD)]]+_TrackerTable35[[#This Row],[Market Value (in USD)]])/_TrackerTable35[[#This Row],[Total Cost (in USD)]]-1,"NA") -> NA
B27: 18 | R27: =IFERROR(_TrackerTable35[[#This Row],[Avg Cost per Share (in Listed Currency)]]/_TrackerTable35[[#This Row],[Exchange Rate (1 USD to xxx Listed Currency)]],"NA") -> NA | S27: =IFERROR(_TrackerTable35[[#This Row],[Quantity]]*_TrackerTable35[[#This Row],[Avg Cost per Share (in USD)]],"NA") -> NA | T27: =IFERROR(_TrackerTable35[[#This Row],[Planned Allocation (in Listed Currency)]]/_TrackerTable35[[#This Row],[Exchange Rate (1 USD to xxx Listed Currency)]],"NA") -> NA | U27: =IFERROR(_TrackerTable35[[#This Row],[Planned Allocation (in USD)]]/_TrackerTable35[[#Totals],[Planned Allocation (in USD)]],"NA") -> NA | V27: =IFERROR(_TrackerTable35[[#This Row],[Total Cost (in USD)]]/_TrackerTable35[[#This Row],[Planned Allocation (in USD)]],"NA") -> NA | W27: =IF(AND(_TrackerTable35[[#This Row],[Exchange Rate (1 USD to xxx Listed Currency)]]>0,_TrackerTable35[[#This Row],[Intrinsic Value (in Listed Currency)]]>0,_TrackerTable35[[#This Row],[Intrinsic Value (in Listed Currency)]]<>"NA"),_TrackerTable35[[#This Row],[Intrinsic Value (in Listed Currency)]]/_TrackerTable35[[#This Row],[Exchange Rate (1 USD to xxx Listed Currency)]],"NA") -> NA | X27: =IFERROR(_TrackerTable35[[#This Row],[Current Price (in USD)]]/_TrackerTable35[[#This Row],[Intrinsic Value (in USD)]]-1,"NA") -> NA | Y27: =IF(_TrackerTable35[[#This Row],[Exchange Rate (1 USD to xxx Listed Currency)]]>0,_TrackerTable35[[#This Row],[Current Price (in Listed Currency)]]/_TrackerTable35[[#This Row],[Exchange Rate (1 USD to xxx Listed Currency)]],"NA") -> NA | Z27: =IFERROR(_TrackerTable35[[#This Row],[Current Price (in USD)]]*_TrackerTable35[[#This Row],[Quantity]],"NA") -> NA | AA27: =IFERROR(IF(AND(_TrackerTable35[[#This Row],[Market Value (in USD)]]>0,_TrackerTable35[[#Totals],[Market Value (in USD)]]>0),_TrackerTable35[[#This Row],[Market Value (in USD)]]/_TrackerTable35[[#Totals],[Market Value (in USD)]],"NA"),"NA") -> NA | AB27: =IFERROR(_TrackerTable35[[#This Row],[Market Value (in USD)]]/_TrackerTable35[[#This Row],[Total Cost (in USD)]]-1,"NA") -> NA | AC27: =IFERROR(_TrackerTable35[[#This Row],[Total Dividend Received (in Listed Currency)]]/_TrackerTable35[[#This Row],[Exchange Rate (1 USD to xxx Listed Currency)]],"NA") -> NA | AD27: =IFERROR(_TrackerTable35[[#This Row],[Total Dividend Received (in USD)]]/_TrackerTable35[[#This Row],[Total Cost (in USD)]],"NA") -> NA | AE27: =IFERROR((_TrackerTable35[[#This Row],[Total Dividend Received (in USD)]]+_TrackerTable35[[#This Row],[Market Value (in USD)]])/_TrackerTable35[[#This Row],[Total Cost (in USD)]]-1,"NA") -> NA
B28: 19 | R28: =IFERROR(_TrackerTable35[[#This Row],[Avg Cost per Share (in Listed Currency)]]/_TrackerTable35[[#This Row],[Exchange Rate (1 USD to xxx Listed Currency)]],"NA") -> NA | S28: =IFERROR(_TrackerTable35[[#This Row],[Quantity]]*_TrackerTable35[[#This Row],[Avg Cost per Share (in USD)]],"NA") -> NA | T28: =IFERROR(_TrackerTable35[[#This Row],[Planned Allocation (in Listed Currency)]]/_TrackerTable35[[#This Row],[Exchange Rate (1 USD to xxx Listed Currency)]],"NA") -> NA | U28: =IFERROR(_TrackerTable35[[#This Row],[Planned Allocation (in USD)]]/_TrackerTable35[[#Totals],[Planned Allocation (in USD)]],"NA") -> NA | V28: =IFERROR(_TrackerTable35[[#This Row],[Total Cost (in USD)]]/_TrackerTable35[[#This Row],[Planned Allocation (in USD)]],"NA") -> NA | W28: =IF(AND(_TrackerTable35[[#This Row],[Exchange Rate (1 USD to xxx Listed Currency)]]>0,_TrackerTable35[[#This Row],[Intrinsic Value (in Listed Currency)]]>0,_TrackerTable35[[#This Row],[Intrinsic Value (in Listed Currency)]]<>"NA"),_TrackerTable35[[#This Row],[Intrinsic Value (in Listed Currency)]]/_TrackerTable35[[#This Row],[Exchange Rate (1 USD to xxx Listed Currency)]],"NA") -> NA | X28: =IFERROR(_TrackerTable35[[#This Row],[Current Price (in USD)]]/_TrackerTable35[[#This Row],[Intrinsic Value (in USD)]]-1,"NA") -> NA | Y28: =IF(_TrackerTable35[[#This Row],[Exchange Rate (1 USD to xxx Listed Currency)]]>0,_TrackerTable35[[#This Row],[Current Price (in Listed Currency)]]/_TrackerTable35[[#This Row],[Exchange Rate (1 USD to xxx Listed Currency)]],"NA") -> NA | Z28: =IFERROR(_TrackerTable35[[#This Row],[Current Price (in USD)]]*_TrackerTable35[[#This Row],[Quantity]],"NA") -> NA | AA28: =IFERROR(IF(AND(_TrackerTable35[[#This Row],[Market Value (in USD)]]>0,_TrackerTable35[[#Totals],[Market Value (in USD)]]>0),_TrackerTable35[[#This Row],[Market Value (in USD)]]/_TrackerTable35[[#Totals],[Market Value (in USD)]],"NA"),"NA") -> NA | AB28: =IFERROR(_TrackerTable35[[#This Row],[Market Value (in USD)]]/_TrackerTable35[[#This Row],[Total Cost (in USD)]]-1,"NA") -> NA | AC28: =IFERROR(_TrackerTable35[[#This Row],[Total Dividend Received (in Listed Currency)]]/_TrackerTable35[[#This Row],[Exchange Rate (1 USD to xxx Listed Currency)]],"NA") -> NA | AD28: =IFERROR(_TrackerTable35[[#This Row],[Total Dividend Received (in USD)]]/_TrackerTable35[[#This Row],[Total Cost (in USD)]],"NA") -> NA | AE28: =IFERROR((_TrackerTable35[[#This Row],[Total Dividend Received (in USD)]]+_TrackerTable35[[#This Row],[Market Value (in USD)]])/_TrackerTable35[[#This Row],[Total Cost (in USD)]]-1,"NA") -> NA
B29: 20 | R29: =IFERROR(_TrackerTable35[[#This Row],[Avg Cost per Share (in Listed Currency)]]/_TrackerTable35[[#This Row],[Exchange Rate (1 USD to xxx Listed Currency)]],"NA") -> NA | S29: =IFERROR(_TrackerTable35[[#This Row],[Quantity]]*_TrackerTable35[[#This Row],[Avg Cost per Share (in USD)]],"NA") -> NA | T29: =IFERROR(_TrackerTable35[[#This Row],[Planned Allocation (in Listed Currency)]]/_TrackerTable35[[#This Row],[Exchange Rate (1 USD to xxx Listed Currency)]],"NA") -> NA | U29: =IFERROR(_TrackerTable35[[#This Row],[Planned Allocation (in USD)]]/_TrackerTable35[[#Totals],[Planned Allocation (in USD)]],"NA") -> NA | V29: =IFERROR(_TrackerTable35[[#This Row],[Total Cost (in USD)]]/_TrackerTable35[[#This Row],[Planned Allocation (in USD)]],"NA") -> NA | W29: =IF(AND(_TrackerTable35[[#This Row],[Exchange Rate (1 USD to xxx Listed Currency)]]>0,_TrackerTable35[[#This Row],[Intrinsic Value (in Listed Currency)]]>0,_TrackerTable35[[#This Row],[Intrinsic Value (in Listed Currency)]]<>"NA"),_TrackerTable35[[#This Row],[Intrinsic Value (in Listed Currency)]]/_TrackerTable35[[#This Row],[Exchange Rate (1 USD to xxx Listed Currency)]],"NA") -> NA | X29: =IFERROR(_TrackerTable35[[#This Row],[Current Price (in USD)]]/_TrackerTable35[[#This Row],[Intrinsic Value (in USD)]]-1,"NA") -> NA | Y29: =IF(_TrackerTable35[[#This Row],[Exchange Rate (1 USD to xxx Listed Currency)]]>0,_TrackerTable35[[#This Row],[Current Price (in Listed Currency)]]/_TrackerTable35[[#This Row],[Exchange Rate (1 USD to xxx Listed Currency)]],"NA") -> NA | Z29: =IFERROR(_TrackerTable35[[#This Row],[Current Price (in USD)]]*_TrackerTable35[[#This Row],[Quantity]],"NA") -> NA | AA29: =IFERROR(IF(AND(_TrackerTable35[[#This Row],[Market Value (in USD)]]>0,_TrackerTable35[[#Totals],[Market Value (in USD)]]>0),_TrackerTable35[[#This Row],[Market Value (in USD)]]/_TrackerTable35[[#Totals],[Market Value (in USD)]],"NA"),"NA") -> NA | AB29: =IFERROR(_TrackerTable35[[#This Row],[Market Value (in USD)]]/_TrackerTable35[[#This Row],[Total Cost (in USD)]]-1,"NA") -> NA | AC29: =IFERROR(_TrackerTable35[[#This Row],[Total Dividend Received (in Listed Currency)]]/_TrackerTable35[[#This Row],[Exchange Rate (1 USD to xxx Listed Currency)]],"NA") -> NA | AD29: =IFERROR(_TrackerTable35[[#This Row],[Total Dividend Received (in USD)]]/_TrackerTable35[[#This Row],[Total Cost (in USD)]],"NA") -> NA | AE29: =IFERROR((_TrackerTable35[[#This Row],[Total Dividend Received (in USD)]]+_TrackerTable35[[#This Row],[Market Value (in USD)]])/_TrackerTable35[[#This Row],[Total Cost (in USD)]]-1,"NA") -> NA
R30: TOTAL | S30: =SUBTOTAL(109,_TrackerTable35[Total Cost (in USD)]) -> 41186.947 | T30: =SUBTOTAL(109,_TrackerTable35[Planned Allocation (in USD)]) -> 45938.763 | Z30: =SUBTOTAL(109,_TrackerTable35[Market Value (in USD)]) -> 53121.177 | AC30: =SUBTOTAL(109,_TrackerTable35[Total Dividend Received (in USD)]) -> 358.0963
C37: ="© "&YEAR(TODAY())&" Piranha Ltd. All rights reserved." -> © 2026 Piranha Ltd. All rights reserved.

Sheet VMI Closed Position
C2: CLOSED POSITION
C4: Total Profit & Loss | D4: =_TrackerTable3543[[#Totals],[Total Profit & Loss]] -> 6912.9733
O5: Cost in USD | Q5: Profit & Loss
C6: Stock Information | I6: Currency | K6: Cost | M6: Dividend | N6: Price | O6: NOTE: DO NOT MODIFY BELOW, THIS IS AUTO-CALCULATED
B7: # | C7: Ticker | D7: Name | E7: Sector | F7: Category | G7: Type | H7: Country | I7: Listed Currency | J7: Exchange Rate (1 USD to xxx Listed Currency) | K7: Quantity | L7: Avg Cost per Share (in Listed Currency) | M7: Total Dividend Received (in Listed Currency) | N7: Closed Price (in Listed Currency) | O7: Avg Cost per Share (in USD) | P7: Total Cost (in USD) | Q7: Closed Price (in USD) | R7: Closed Value (in USD) | S7: Total Dividend Received (in USD) | T7: Total Profit & Loss | U7: % Total Profit and Loss
B8: 1 | C8: GOOGL | D8: Alphabet | E8: Communication Services | F8: Growth | G8: Moderate Cyclical | H8: US | I8: USD | J8: 1 | K8: 4 | L8: 1361.06 | M8: 0 | N8: 3000.02 | O8: =IFERROR(_TrackerTable3543[[#This Row],[Avg Cost per Share (in Listed Currency)]]/_TrackerTable3543[[#This Row],[Exchange Rate (1 USD to xxx Listed Currency)]],"NA") -> 1361.06 | P8: =IFERROR(_TrackerTable3543[[#This Row],[Quantity]]*_TrackerTable3543[[#This Row],[Avg Cost per Share (in USD)]],"NA") -> 5444.24 | Q8: =IF(_TrackerTable3543[[#This Row],[Exchange Rate (1 USD to xxx Listed Currency)]]>0,_TrackerTable3543[[#This Row],[Closed Price (in Listed Currency)]]/_TrackerTable3543[[#This Row],[Exchange Rate (1 USD to xxx Listed Currency)]],"NA") -> 3000.02 | R8: =IFERROR(_TrackerTable3543[[#This Row],[Closed Price (in USD)]]*_TrackerTable3543[[#This Row],[Quantity]],"NA") -> 12000.08 | S8: =IFERROR(_TrackerTable3543[[#This Row],[Total Dividend Received (in Listed Currency)]]/_TrackerTable3543[[#This Row],[Exchange Rate (1 USD to xxx Listed Currency)]],"NA") -> 0 | T8: =IFERROR(_TrackerTable3543[[#This Row],[Closed Value (in USD)]]+_TrackerTable3543[[#This Row],[Total Dividend Received (in USD)]]-_TrackerTable3543[[#This Row],[Total Cost (in USD)]],"NA") -> 6555.84 | U8: =IFERROR(_TrackerTable3543[[#This Row],[Total Profit & Loss]]/_TrackerTable3543[[#This Row],[Total Cost (in USD)]],"NA") -> 1.2041791
B9: 2 | C9: CWCU | D9: Cromwell European REIT | E9: Real Estate | F9: Cash Cow | G9: Cyclical | H9: Singapore | I9: SGD | J9: 1.35 | K9: 1000 | L9: 3.63 | M9: 212.13 | N9: 3.9 | O9: =IFERROR(_TrackerTable3543[[#This Row],[Avg Cost per Share (in Listed Currency)]]/_TrackerTable3543[[#This Row],[Exchange Rate (1 USD to xxx Listed Currency)]],"NA") -> 2.6888889 | P9: =IFERROR(_TrackerTable3543[[#This Row],[Quantity]]*_TrackerTable3543[[#This Row],[Avg Cost per Share (in USD)]],"NA") -> 2688.8889 | Q9: =IF(_TrackerTable3543[[#This Row],[Exchange Rate (1 USD to xxx Listed Currency)]]>0,_TrackerTable3543[[#This Row],[Closed Price (in Listed Currency)]]/_TrackerTable3543[[#This Row],[Exchange Rate (1 USD to xxx Listed Currency)]],"NA") -> 2.8888889 | R9: =IFERROR(_TrackerTable3543[[#This Row],[Closed Price (in USD)]]*_TrackerTable3543[[#This Row],[Quantity]],"NA") -> 2888.8889 | S9: =IFERROR(_TrackerTable3543[[#This Row],[Total Dividend Received (in Listed Currency)]]/_TrackerTable3543[[#This Row],[Exchange Rate (1 USD to xxx Listed Currency)]],"NA") -> 157.13333 | T9: =IFERROR(_TrackerTable3543[[#This Row],[Closed Value (in USD)]]+_TrackerTable3543[[#This Row],[Total Dividend Received (in USD)]]-_TrackerTable3543[[#This Row],[Total Cost (in USD)]],"NA") -> 357.13333 | U9: =IFERROR(_TrackerTable3543[[#This Row],[Total Profit & Loss]]/_TrackerTable3543[[#This Row],[Total Cost (in USD)]],"NA") -> 0.13281818
B10: 3 | O10: =IFERROR(_TrackerTable3543[[#This Row],[Avg Cost per Share (in Listed Currency)]]/_TrackerTable3543[[#This Row],[Exchange Rate (1 USD to xxx Listed Currency)]],"NA") -> NA | P10: =IFERROR(_TrackerTable3543[[#This Row],[Quantity]]*_TrackerTable3543[[#This Row],[Avg Cost per Share (in USD)]],"NA") -> NA | Q10: =IF(_TrackerTable3543[[#This Row],[Exchange Rate (1 USD to xxx Listed Currency)]]>0,_TrackerTable3543[[#This Row],[Closed Price (in Listed Currency)]]/_TrackerTable3543[[#This Row],[Exchange Rate (1 USD to xxx Listed Currency)]],"NA") -> NA | R10: =IFERROR(_TrackerTable3543[[#This Row],[Closed Price (in USD)]]*_TrackerTable3543[[#This Row],[Quantity]],"NA") -> NA | S10: =IFERROR(_TrackerTable3543[[#This Row],[Total Dividend Received (in Listed Currency)]]/_TrackerTable3543[[#This Row],[Exchange Rate (1 USD to xxx Listed Currency)]],"NA") -> NA | T10: =IFERROR(_TrackerTable3543[[#This Row],[Closed Value (in USD)]]+_TrackerTable3543[[#This Row],[Total Dividend Received (in USD)]]-_TrackerTable3543[[#This Row],[Total Cost (in USD)]],"NA") -> NA | U10: =IFERROR(_TrackerTable3543[[#This Row],[Total Profit & Loss]]/_TrackerTable3543[[#This Row],[Total Cost (in USD)]],"NA") -> NA
B11: 4 | O11: =IFERROR(_TrackerTable3543[[#This Row],[Avg Cost per Share (in Listed Currency)]]/_TrackerTable3543[[#This Row],[Exchange Rate (1 USD to xxx Listed Currency)]],"NA") -> NA | P11: =IFERROR(_TrackerTable3543[[#This Row],[Quantity]]*_TrackerTable3543[[#This Row],[Avg Cost per Share (in USD)]],"NA") -> NA | Q11: =IF(_TrackerTable3543[[#This Row],[Exchange Rate (1 USD to xxx Listed Currency)]]>0,_TrackerTable3543[[#This Row],[Closed Price (in Listed Currency)]]/_TrackerTable3543[[#This Row],[Exchange Rate (1 USD to xxx Listed Currency)]],"NA") -> NA | R11: =IFERROR(_TrackerTable3543[[#This Row],[Closed Price (in USD)]]*_TrackerTable3543[[#This Row],[Quantity]],"NA") -> NA | S11: =IFERROR(_TrackerTable3543[[#This Row],[Total Dividend Received (in Listed Currency)]]/_TrackerTable3543[[#This Row],[Exchange Rate (1 USD to xxx Listed Currency)]],"NA") -> NA | T11: =IFERROR(_TrackerTable3543[[#This Row],[Closed Value (in USD)]]+_TrackerTable3543[[#This Row],[Total Dividend Received (in USD)]]-_TrackerTable3543[[#This Row],[Total Cost (in USD)]],"NA") -> NA | U11: =IFERROR(_TrackerTable3543[[#This Row],[Total Profit & Loss]]/_TrackerTable3543[[#This Row],[Total Cost (in USD)]],"NA") -> NA
B12: 5 | O12: =IFERROR(_TrackerTable3543[[#This Row],[Avg Cost per Share (in Listed Currency)]]/_TrackerTable3543[[#This Row],[Exchange Rate (1 USD to xxx Listed Currency)]],"NA") -> NA | P12: =IFERROR(_TrackerTable3543[[#This Row],[Quantity]]*_TrackerTable3543[[#This Row],[Avg Cost per Share (in USD)]],"NA") -> NA | Q12: =IF(_TrackerTable3543[[#This Row],[Exchange Rate (1 USD to xxx Listed Currency)]]>0,_TrackerTable3543[[#This Row],[Closed Price (in Listed Currency)]]/_TrackerTable3543[[#This Row],[Exchange Rate (1 USD to xxx Listed Currency)]],"NA") -> NA | R12: =IFERROR(_TrackerTable3543[[#This Row],[Closed Price (in USD)]]*_TrackerTable3543[[#This Row],[Quantity]],"NA") -> NA | S12: =IFERROR(_TrackerTable3543[[#This Row],[Total Dividend Received (in Listed Currency)]]/_TrackerTable3543[[#This Row],[Exchange Rate (1 USD to xxx Listed Currency)]],"NA") -> NA | T12: =IFERROR(_TrackerTable3543[[#This Row],[Closed Value (in USD)]]+_TrackerTable3543[[#This Row],[Total Dividend Received (in USD)]]-_TrackerTable3543[[#This Row],[Total Cost (in USD)]],"NA") -> NA | U12: =IFERROR(_TrackerTable3543[[#This Row],[Total Profit & Loss]]/_TrackerTable3543[[#This Row],[Total Cost (in USD)]],"NA") -> NA
B13: 6 | O13: =IFERROR(_TrackerTable3543[[#This Row],[Avg Cost per Share (in Listed Currency)]]/_TrackerTable3543[[#This Row],[Exchange Rate (1 USD to xxx Listed Currency)]],"NA") -> NA | P13: =IFERROR(_TrackerTable3543[[#This Row],[Quantity]]*_TrackerTable3543[[#This Row],[Avg Cost per Share (in USD)]],"NA") -> NA | Q13: =IF(_TrackerTable3543[[#This Row],[Exchange Rate (1 USD to xxx Listed Currency)]]>0,_TrackerTable3543[[#This Row],[Closed Price (in Listed Currency)]]/_TrackerTable3543[[#This Row],[Exchange Rate (1 USD to xxx Listed Currency)]],"NA") -> NA | R13: =IFERROR(_TrackerTable3543[[#This Row],[Closed Price (in USD)]]*_TrackerTable3543[[#This Row],[Quantity]],"NA") -> NA | S13: =IFERROR(_TrackerTable3543[[#This Row],[Total Dividend Received (in Listed Currency)]]/_TrackerTable3543[[#This Row],[Exchange Rate (1 USD to xxx Listed Currency)]],"NA") -> NA | T13: =IFERROR(_TrackerTable3543[[#This Row],[Closed Value (in USD)]]+_TrackerTable3543[[#This Row],[Total Dividend Received (in USD)]]-_TrackerTable3543[[#This Row],[Total Cost (in USD)]],"NA") -> NA | U13: =IFERROR(_TrackerTable3543[[#This Row],[Total Profit & Loss]]/_TrackerTable3543[[#This Row],[Total Cost (in USD)]],"NA") -> NA
B14: 7 | O14: =IFERROR(_TrackerTable3543[[#This Row],[Avg Cost per Share (in Listed Currency)]]/_TrackerTable3543[[#This Row],[Exchange Rate (1 USD to xxx Listed Currency)]],"NA") -> NA | P14: =IFERROR(_TrackerTable3543[[#This Row],[Quantity]]*_TrackerTable3543[[#This Row],[Avg Cost per Share (in USD)]],"NA") -> NA | Q14: =IF(_TrackerTable3543[[#This Row],[Exchange Rate (1 USD to xxx Listed Currency)]]>0,_TrackerTable3543[[#This Row],[Closed Price (in Listed Currency)]]/_TrackerTable3543[[#This Row],[Exchange Rate (1 USD to xxx Listed Currency)]],"NA") -> NA | R14: =IFERROR(_TrackerTable3543[[#This Row],[Closed Price (in USD)]]*_TrackerTable3543[[#This Row],[Quantity]],"NA") -> NA | S14: =IFERROR(_TrackerTable3543[[#This Row],[Total Dividend Received (in Listed Currency)]]/_TrackerTable3543[[#This Row],[Exchange Rate (1 USD to xxx Listed Currency)]],"NA") -> NA | T14: =IFERROR(_TrackerTable3543[[#This Row],[Closed Value (in USD)]]+_TrackerTable3543[[#This Row],[Total Dividend Received (in USD)]]-_TrackerTable3543[[#This Row],[Total Cost (in USD)]],"NA") -> NA | U14: =IFERROR(_TrackerTable3543[[#This Row],[Total Profit & Loss]]/_TrackerTable3543[[#This Row],[Total Cost (in USD)]],"NA") -> NA
B15: 8 | O15: =IFERROR(_TrackerTable3543[[#This Row],[Avg Cost per Share (in Listed Currency)]]/_TrackerTable3543[[#This Row],[Exchange Rate (1 USD to xxx Listed Currency)]],"NA") -> NA | P15: =IFERROR(_TrackerTable3543[[#This Row],[Quantity]]*_TrackerTable3543[[#This Row],[Avg Cost per Share (in USD)]],"NA") -> NA | Q15: =IF(_TrackerTable3543[[#This Row],[Exchange Rate (1 USD to xxx Listed Currency)]]>0,_TrackerTable3543[[#This Row],[Closed Price (in Listed Currency)]]/_TrackerTable3543[[#This Row],[Exchange Rate (1 USD to xxx Listed Currency)]],"NA") -> NA | R15: =IFERROR(_TrackerTable3543[[#This Row],[Closed Price (in USD)]]*_TrackerTable3543[[#This Row],[Quantity]],"NA") -> NA | S15: =IFERROR(_TrackerTable3543[[#This Row],[Total Dividend Received (in Listed Currency)]]/_TrackerTable3543[[#This Row],[Exchange Rate (1 USD to xxx Listed Currency)]],"NA") -> NA | T15: =IFERROR(_TrackerTable3543[[#This Row],[Closed Value (in USD)]]+_TrackerTable3543[[#This Row],[Total Dividend Received (in USD)]]-_TrackerTable3543[[#This Row],[Total Cost (in USD)]],"NA") -> NA | U15: =IFERROR(_TrackerTable3543[[#This Row],[Total Profit & Loss]]/_TrackerTable3543[[#This Row],[Total Cost (in USD)]],"NA") -> NA
B16: 9 | O16: =IFERROR(_TrackerTable3543[[#This Row],[Avg Cost per Share (in Listed Currency)]]/_TrackerTable3543[[#This Row],[Exchange Rate (1 USD to xxx Listed Currency)]],"NA") -> NA | P16: =IFERROR(_TrackerTable3543[[#This Row],[Quantity]]*_TrackerTable3543[[#This Row],[Avg Cost per Share (in USD)]],"NA") -> NA | Q16: =IF(_TrackerTable3543[[#This Row],[Exchange Rate (1 USD to xxx Listed Currency)]]>0,_TrackerTable3543[[#This Row],[Closed Price (in Listed Currency)]]/_TrackerTable3543[[#This Row],[Exchange Rate (1 USD to xxx Listed Currency)]],"NA") -> NA | R16: =IFERROR(_TrackerTable3543[[#This Row],[Closed Price (in USD)]]*_TrackerTable3543[[#This Row],[Quantity]],"NA") -> NA | S16: =IFERROR(_TrackerTable3543[[#This Row],[Total Dividend Received (in Listed Currency)]]/_TrackerTable3543[[#This Row],[Exchange Rate (1 USD to xxx Listed Currency)]],"NA") -> NA | T16: =IFERROR(_TrackerTable3543[[#This Row],[Closed Value (in USD)]]+_TrackerTable3543[[#This Row],[Total Dividend Received (in USD)]]-_TrackerTable3543[[#This Row],[Total Cost (in USD)]],"NA") -> NA | U16: =IFERROR(_TrackerTable3543[[#This Row],[Total Profit & Loss]]/_TrackerTable3543[[#This Row],[Total Cost (in USD)]],"NA") -> NA
B17: 10 | O17: =IFERROR(_TrackerTable3543[[#This Row],[Avg Cost per Share (in Listed Currency)]]/_TrackerTable3543[[#This Row],[Exchange Rate (1 USD to xxx Listed Currency)]],"NA") -> NA | P17: =IFERROR(_TrackerTable3543[[#This Row],[Quantity]]*_TrackerTable3543[[#This Row],[Avg Cost per Share (in USD)]],"NA") -> NA | Q17: =IF(_TrackerTable3543[[#This Row],[Exchange Rate (1 USD to xxx Listed Currency)]]>0,_TrackerTable3543[[#This Row],[Closed Price (in Listed Currency)]]/_TrackerTable3543[[#This Row],[Exchange Rate (1 USD to xxx Listed Currency)]],"NA") -> NA | R17: =IFERROR(_TrackerTable3543[[#This Row],[Closed Price (in USD)]]*_TrackerTable3543[[#This Row],[Quantity]],"NA") -> NA | S17: =IFERROR(_TrackerTable3543[[#This Row],[Total Dividend Received (in Listed Currency)]]/_TrackerTable3543[[#This Row],[Exchange Rate (1 USD to xxx Listed Currency)]],"NA") -> NA | T17: =IFERROR(_TrackerTable3543[[#This Row],[Closed Value (in USD)]]+_TrackerTable3543[[#This Row],[Total Dividend Received (in USD)]]-_TrackerTable3543[[#This Row],[Total Cost (in USD)]],"NA") -> NA | U17: =IFERROR(_TrackerTable3543[[#This Row],[Total Profit & Loss]]/_TrackerTable3543[[#This Row],[Total Cost (in USD)]],"NA") -> NA
B18: 11 | O18: =IFERROR(_TrackerTable3543[[#This Row],[Avg Cost per Share (in Listed Currency)]]/_TrackerTable3543[[#This Row],[Exchange Rate (1 USD to xxx Listed Currency)]],"NA") -> NA | P18: =IFERROR(_TrackerTable3543[[#This Row],[Quantity]]*_TrackerTable3543[[#This Row],[Avg Cost per Share (in USD)]],"NA") -> NA | Q18: =IF(_TrackerTable3543[[#This Row],[Exchange Rate (1 USD to xxx Listed Currency)]]>0,_TrackerTable3543[[#This Row],[Closed Price (in Listed Currency)]]/_TrackerTable3543[[#This Row],[Exchange Rate (1 USD to xxx Listed Currency)]],"NA") -> NA | R18: =IFERROR(_TrackerTable3543[[#This Row],[Closed Price (in USD)]]*_TrackerTable3543[[#This Row],[Quantity]],"NA") -> NA | S18: =IFERROR(_TrackerTable3543[[#This Row],[Total Dividend Received (in Listed Currency)]]/_TrackerTable3543[[#This Row],[Exchange Rate (1 USD to xxx Listed Currency)]],"NA") -> NA | T18: =IFERROR(_TrackerTable3543[[#This Row],[Closed Value (in USD)]]+_TrackerTable3543[[#This Row],[Total Dividend Received (in USD)]]-_TrackerTable3543[[#This Row],[Total Cost (in USD)]],"NA") -> NA | U18: =IFERROR(_TrackerTable3543[[#This Row],[Total Profit & Loss]]/_TrackerTable3543[[#This Row],[Total Cost (in USD)]],"NA") -> NA
B19: 12 | O19: =IFERROR(_TrackerTable3543[[#This Row],[Avg Cost per Share (in Listed Currency)]]/_TrackerTable3543[[#This Row],[Exchange Rate (1 USD to xxx Listed Currency)]],"NA") -> NA | P19: =IFERROR(_TrackerTable3543[[#This Row],[Quantity]]*_TrackerTable3543[[#This Row],[Avg Cost per Share (in USD)]],"NA") -> NA | Q19: =IF(_TrackerTable3543[[#This Row],[Exchange Rate (1 USD to xxx Listed Currency)]]>0,_TrackerTable3543[[#This Row],[Closed Price (in Listed Currency)]]/_TrackerTable3543[[#This Row],[Exchange Rate (1 USD to xxx Listed Currency)]],"NA") -> NA | R19: =IFERROR(_TrackerTable3543[[#This Row],[Closed Price (in USD)]]*_TrackerTable3543[[#This Row],[Quantity]],"NA") -> NA | S19: =IFERROR(_TrackerTable3543[[#This Row],[Total Dividend Received (in Listed Currency)]]/_TrackerTable3543[[#This Row],[Exchange Rate (1 USD to xxx Listed Currency)]],"NA") -> NA | T19: =IFERROR(_TrackerTable3543[[#This Row],[Closed Value (in USD)]]+_TrackerTable3543[[#This Row],[Total Dividend Received (in USD)]]-_TrackerTable3543[[#This Row],[Total Cost (in USD)]],"NA") -> NA | U19: =IFERROR(_TrackerTable3543[[#This Row],[Total Profit & Loss]]/_TrackerTable3543[[#This Row],[Total Cost (in USD)]],"NA") -> NA
B20: 13 | O20: =IFERROR(_TrackerTable3543[[#This Row],[Avg Cost per Share (in Listed Currency)]]/_TrackerTable3543[[#This Row],[Exchange Rate (1 USD to xxx Listed Currency)]],"NA") -> NA | P20: =IFERROR(_TrackerTable3543[[#This Row],[Quantity]]*_TrackerTable3543[[#This Row],[Avg Cost per Share (in USD)]],"NA") -> NA | Q20: =IF(_TrackerTable3543[[#This Row],[Exchange Rate (1 USD to xxx Listed Currency)]]>0,_TrackerTable3543[[#This Row],[Closed Price (in Listed Currency)]]/_TrackerTable3543[[#This Row],[Exchange Rate (1 USD to xxx Listed Currency)]],"NA") -> NA | R20: =IFERROR(_TrackerTable3543[[#This Row],[Closed Price (in USD)]]*_TrackerTable3543[[#This Row],[Quantity]],"NA") -> NA | S20: =IFERROR(_TrackerTable3543[[#This Row],[Total Dividend Received (in Listed Currency)]]/_TrackerTable3543[[#This Row],[Exchange Rate (1 USD to xxx Listed Currency)]],"NA") -> NA | T20: =IFERROR(_TrackerTable3543[[#This Row],[Closed Value (in USD)]]+_TrackerTable3543[[#This Row],[Total Dividend Received (in USD)]]-_TrackerTable3543[[#This Row],[Total Cost (in USD)]],"NA") -> NA | U20: =IFERROR(_TrackerTable3543[[#This Row],[Total Profit & Loss]]/_TrackerTable3543[[#This Row],[Total Cost (in USD)]],"NA") -> NA
B21: 14 | O21: =IFERROR(_TrackerTable3543[[#This Row],[Avg Cost per Share (in Listed Currency)]]/_TrackerTable3543[[#This Row],[Exchange Rate (1 USD to xxx Listed Currency)]],"NA") -> NA | P21: =IFERROR(_TrackerTable3543[[#This Row],[Quantity]]*_TrackerTable3543[[#This Row],[Avg Cost per Share (in USD)]],"NA") -> NA | Q21: =IF(_TrackerTable3543[[#This Row],[Exchange Rate (1 USD to xxx Listed Currency)]]>0,_TrackerTable3543[[#This Row],[Closed Price (in Listed Currency)]]/_TrackerTable3543[[#This Row],[Exchange Rate (1 USD to xxx Listed Currency)]],"NA") -> NA | R21: =IFERROR(_TrackerTable3543[[#This Row],[Closed Price (in USD)]]*_TrackerTable3543[[#This Row],[Quantity]],"NA") -> NA | S21: =IFERROR(_TrackerTable3543[[#This Row],[Total Dividend Received (in Listed Currency)]]/_TrackerTable3543[[#This Row],[Exchange Rate (1 USD to xxx Listed Currency)]],"NA") -> NA | T21: =IFERROR(_TrackerTable3543[[#This Row],[Closed Value (in USD)]]+_TrackerTable3543[[#This Row],[Total Dividend Received (in USD)]]-_TrackerTable3543[[#This Row],[Total Cost (in USD)]],"NA") -> NA | U21: =IFERROR(_TrackerTable3543[[#This Row],[Total Profit & Loss]]/_TrackerTable3543[[#This Row],[Total Cost (in USD)]],"NA") -> NA
... B28: 20 | O28: =IFERROR(_TrackerTable3543[[#This Row],[Avg Cost per Share (in Listed Currency)]]/_TrackerTable3543[[#This Row],[Exchange Rate (1 USD to xxx Listed Currency)]],"NA") -> NA | P28: =IFERROR(_TrackerTable3543[[#This Row],[Quantity]]*_TrackerTable3543[[#This Row],[Avg Cost per Share (in USD)]],"NA") -> NA | Q28: =IF(_TrackerTable3543[[#This Row],[Exchange Rate (1 USD to xxx Listed Currency)]]>0,_TrackerTable3543[[#This Row],[Closed Price (in Listed Currency)]]/_TrackerTable3543[[#This Row],[Exchange Rate (1 USD to xxx Listed Currency)]],"NA") -> NA | R28: =IFERROR(_TrackerTable3543[[#This Row],[Closed Price (in USD)]]*_TrackerTable3543[[#This Row],[Quantity]],"NA") -> NA | S28: =IFERROR(_TrackerTable3543[[#This Row],[Total Dividend Received (in Listed Currency)]]/_TrackerTable3543[[#This Row],[Exchange Rate (1 USD to xxx Listed Currency)]],"NA") -> NA | T28: =IFERROR(_TrackerTable3543[[#This Row],[Closed Value (in USD)]]+_TrackerTable3543[[#This Row],[Total Dividend Received (in USD)]]-_TrackerTable3543[[#This Row],[Total Cost (in USD)]],"NA") -> NA | U28: =IFERROR(_TrackerTable3543[[#This Row],[Total Profit & Loss]]/_TrackerTable3543[[#This Row],[Total Cost (in USD)]],"NA") -> NA
O29: TOTAL | P29: =SUBTOTAL(109,_TrackerTable3543[Total Cost (in USD)]) -> 8133.1289 | R29: =SUBTOTAL(109,_TrackerTable3543[Closed Value (in USD)]) -> 14888.969 | S29: =SUBTOTAL(109,_TrackerTable3543[Total Dividend Received (in USD)]) -> 157.13333 | T29: =SUBTOTAL(109,_TrackerTable3543[Total Profit & Loss]) -> 6912.9733 | U29: =_xlfn.IFNA(_TrackerTable3543[[#Totals],[Total Profit & Loss]]/_TrackerTable3543[[#Totals],[Total Cost (in USD)]]-1,"NA") -> -0.1500229
C36: ="© "&YEAR(TODAY())&" Piranha Ltd. All rights reserved." -> © 2026 Piranha Ltd. All rights reserved.

Sheet VMI Portfolio Parameter
B2: This sheet contains information that's used in the VMI Portfolio Manager and VMI Closed Position.
B3: NOTE: You can expand the DATA VALIDATION for each category by adding a new row to the category!
B5: Sector
B6: Communication Services
B7: Consumer Discretionary
B8: Consumer Staples
B9: Diversified
B10: Energy
B11: Financials
B12: Health Care
B13: Industrials
B14: Materials
... B46: Moderate Cyclical
B51: ="© "&YEAR(TODAY())&" Piranha Ltd. All rights reserved." -> © 2026 Piranha Ltd. All rights reserved.

Sheet Currency Data
C2: Currency Data
C4: KEY IN NEW CURRENCIES IN THE WHITE BOXES
C6: SYMBOL | D6: CURRENCY
C7: USD$ | D7: US Dollar
C8: AUD$ | D8: Australian Dollar
C9: GBP$ | D9: British Pound Sterling
C10: CAD$ | D10: Canadian Dollar
C11: RMB$ | D11: Chinese Ren Min Bi
C12: DKK$ | D12: Danish Krone
C13: EUR$ | D13: Euro Dollar
C14: HKD$ | D14: Hong Kong Dollar
C15: HUF$ | D15: Hungarian Forint
C16: INR$ | D16: Indian Rupee
C17: IDR$ | D17: Indonesian Rupiah
... C35: VND$ | D35: Vietnamese Dong
C54: ="© "&YEAR(TODAY())&" Piranha Ltd. All rights reserved." -> © 2026 Piranha Ltd. All rights reserved.

Sheet Discount Rate Data
B2: Discount Rate Breakdown
B4: Updated on: | C4: 46092
B6: US
B7: Source: | C7: https://www.market-risk-premia.com/us.html
B9: Risk Free Rate (Rf) | E9: Market Risk Premium (MRP)
B10: Date | C10: Value | E10: Date | F10: Value
B11: 46022 | C11: 4.18 | E11: 46022 | F11: 2.37
B12: =DATE(YEAR(B11)-1,MONTH(B11),DAY(B11)) -> 45657 | C12: 4.58 | E12: =DATE(YEAR(E11)-1,MONTH(E11),DAY(E11)) -> 45657 | F12: 2.18
B13: =DATE(YEAR(B12)-1,MONTH(B12),DAY(B12)) -> 45291 | C13: 3.88 | E13: =DATE(YEAR(E12)-1,MONTH(E12),DAY(E12)) -> 45291 | F13: 2.73
B14: =DATE(YEAR(B13)-1,MONTH(B13),DAY(B13)) -> 44926 | C14: 3.88 | E14: =DATE(YEAR(E13)-1,MONTH(E13),DAY(E13)) -> 44926 | F14: 3.07
B15: =DATE(YEAR(B14)-1,MONTH(B14),DAY(B14)) -> 44561 | C15: 1.52 | E15: =DATE(YEAR(E14)-1,MONTH(E14),DAY(E14)) -> 44561 | F15: 3.29
B17: Rf Average | C17: =AVERAGE(C11:C15)/100 -> 0.03608 | E17: MRP Average | F17: =AVERAGE(F11:F15)/100 -> 0.02728
B20: China/HK Stocks
B21: Source: | C21: https://www.market-risk-premia.com/hk.html
B23: Risk Free Rate (Rf) | E23: Market Risk Premium (MRP)
B24: Date | C24: Value | E24: Date | F24: Value
B25: 46022 | C25: 3.1 | E25: 46022 | F25: 5.35
B26: =DATE(YEAR(B25)-1,MONTH(B25),DAY(B25)) -> 45657 | C26: 3.81 | E26: =DATE(YEAR(E25)-1,MONTH(E25),DAY(E25)) -> 45657 | F26: 6.14
B27: =DATE(YEAR(B26)-1,MONTH(B26),DAY(B26)) -> 45291 | C27: 3.27 | E27: =DATE(YEAR(E26)-1,MONTH(E26),DAY(E26)) -> 45291 | F27: 8.47
B28: =DATE(YEAR(B27)-1,MONTH(B27),DAY(B27)) -> 44926 | C28: 3.71 | E28: =DATE(YEAR(E27)-1,MONTH(E27),DAY(E27)) -> 44926 | F28: 6.01
B29: =DATE(YEAR(B28)-1,MONTH(B28),DAY(B28)) -> 44561 | C29: 1.45 | E29: =DATE(YEAR(E28)-1,MONTH(E28),DAY(E28)) -> 44561 | F29: 8.34
B31: Rf Average | C31: =AVERAGE(C25:C29)/100 -> 0.03068 | E31: MRP Average | F31: =AVERAGE(F25:F29)/100 -> 0.06862
D36: ="© "&YEAR(TODAY())&" Piranha Ltd. All rights reserved." -> © 2026 Piranha Ltd. All rights reserved.
